Workbook

Sheet SOURCES
K1: il faut donner la possibilliter de prioriser ou numéroter les réponses | L1: https://www.intelligences-multiples.org/intelligences-multiples2/les-8-types-dintelligences/
B2: Soft skills | C2: https://moodwork.com/blog/well-being/liste-des-soft-skills/
B3: MBTI | C3: https://www.windtopik.fr/profil-mbti-affecter-vos-choix-metiers/#Quels_sont_les_types_de_MBTI
B4: Intélligence multiples | C4: https://www.intelligences-multiples.org/intelligences-multiples2/les-8-types-dintelligences/

Sheet Questionnaire 
A1: Questionnaire Soft Skills & MBTI — Version Lycée / Adulte (48 questions) | L1: Sélectionnez A,B,C ou D grâce à la liste déroulante.
A2: Question | B2: Remarque | C2: Soft skill | D2: Catégorie | E2: Classe MBTI | F2: Explication | G2: Question | H2: A | I2: B | J2: C | K2: D | L2: Votre choix | M2: Explication réponse | N2: Point soft skill | O2: Sélection soft skills | P2: Soft skill à développer ? | Q2: remarque affirmation | R2: A | S2: B | T2: C | U2: D | W2: Lettre MBTI (calculée)
A3: {=_xlfn.SEQUENCE(COUNTA(C3:C100))} | C3: Communication écrite | D3: Communication | E3: Energie (E-extraverti ou I-Introverti) | F3: Capacité à être facilement lu et compris mais aussi de susciter l'intérêt lorsque l'on transmet un message par écrit. | G3: Lorsque vous rédigez une note ou un écrit à destination d'autres individus : | H3: Vous ne recevez jamais de retour négatif car vous êtes un expert de la communication écrite. | I3: Vous recevez rarement des retours d'incompréhension. | J3: On comprend mais certains vous signalent qu'il y a beaucoup de fautes de français. | K3: Vous recevez plusieurs messages vous demandant d'être plus explicite parce qu'on ne comprend rien du tout. | L3: A | M3: =_xlfn.XLOOKUP(L3,'Questionnaire '!$R$2:$U$2,'Questionnaire '!R3:U3,,1) | N3: =IF(L3="A",2,IF(L3="B",1,0)) | O3: Soft skills | P3: =IF(N3>=1,"","À développer") | R3: Vous êtes particulièrement doué à l'écrit. | S3: Vous savez aussi vous exprimer à l'écrit. En général, les gens comprennent facilement vos propos quand ils vous lisent. | T3: Vous faites beaucoup de faute de français à l'écrit. | U3: Vous avez certaines difficultés à structurer vos phrases à l'écrit. Vous pouvez faire des fautes de français.
A4: 1 | C4: L’audace (ou le culot) | D4: Communication | E4: Mode d'action ou style de vie (J-Organisation ou P-perception) | F4: Capacité à mettre en place ou réaliser des actions qui semblent risquées, difficiles et/ou irréalisables. | G4: Lors d'une réunion professionnelle, on vous propose soudainement de présenter vos idées sur un projet complexe devant plusieurs supérieurs. Vous n'avez pas préparé de présentation formelle. Comment réagissez-vous ? | H4: J'accepte l'opportunité spontanément, en me fiant à ma connaissance du sujet pour guider ma présentation. | I4: Bien que surpris, je saisis l'occasion de partager mes idées, en improvisant une présentation concise basée sur mes connaissances actuelles. | J4: Je m'excuse en expliquant que je ne suis pas prêt à présenter et je suggère de reporter à un moment où je pourrais mieux me préparer. | K4: La situation me met mal à l'aise, donc je décline poliment, préférant ne pas prendre le risque de me présenter sans préparation. | L4: C | M4: =_xlfn.XLOOKUP(L4,'Questionnaire '!$R$2:$U$2,'Questionnaire '!$R4:$U4) | N4: =IF(L4="A",2,IF(L4="B",1,0)) | O4: Soft skills | P4: =IF(N4>=1,"","À développer") | R4: Vous avez de l'audace et êtes relativement spontané. | S4: Vous avez de l'audace et êtes relativement spontané. | T4: Vous êtes quelqu'un de timide et réservé. | U4: Cependant vous avez peu d'audace ou de culot quand il s'agit de s'adresser aux personnes qui vous semblent impressionnantes. | W4: =IF(N4>0,"N","S")
A5: 2 | C5: La clarté de communication | D5: Communication | E5: Energie (E-extraverti ou I-Introverti) | F5: Capacité à exprimer clairement ses idées lorsque l’on s’adresse à un ou plusieurs individus. | G5: Lorsque vous parlez, devez-vous répéter régulièrement vos phrases pour être parfaitement compris ? | H5: Non, ça ne m'arrive jamais. | I5: Rarement, une fois comme ça. | J5: Ça m'arrive régulièrement. | K5: Ça m'arrive tout le temps, je dois souvent reprendre depuis le début. | M5: =_xlfn.XLOOKUP(L5,'Questionnaire '!$R$2:$U$2,'Questionnaire '!$R5:$U5) | N5: =IF(L5="A",2,IF(L5="B",1,0)) | O5: Soft skills | P5: =IF(N5>=1,"","À développer") | R5: Vous savez vous exprimer extrêmement bien. | S5: Vous êtes clair quand vous vous exprimez à l'oral, ceux qui vous écoutent comprennent facilement vos propos. | T5: Vous avez du mal à vous exprimer correctement. | U5: Vous avez des problèmes d'élocution. Vous avez du mal à structurer des phrases claires et précises. | W5: =IF(N5>0,"E","I")
A6: 3 | C6: La diplomatie | D6: Communication | E6: Prise de décision (T-pensée ou F-sentiment) | F6: Qualité qui permet d'apprécier intuitivement ce qu'il convient de dire, de faire ou d'éviter dans les relations humaines. | G6: Lorsqu'on vous demande de donner votre avis sur un sujet sensible, vous avez tendance à : | H6: Donner votre opinion sans mentir, même si votre avis peut blesser. | I6: Expliquer quels sont les faits, sans chercher à transformer la réalité. | J6: Mesurer votre franchise afin de ne pas créer de malaise. | K6: Bien choisir vos mots afin de ne blesser personne. | M6: =_xlfn.XLOOKUP(L6,'Questionnaire '!$R$2:$U$2,'Questionnaire '!$R6:$U6) | N6: =IF(L6="C",2,IF(L6="D",1,0)) | O6: Soft skills | P6: =IF(N6>=1,"","À développer") | R6: Vous pouvez parfois manquer de diplomatie et de tact quand vous vous adressez aux gens. | S6: Vous aimez relater les faits de façon claire et précise, vous n'aimez pas les discours fallacieux. | T6: Vous avez tendance à éviter de blesser les gens lorsque vous débattez. | U6: Vous êtes extrêmement diplomate dans vos propos, vous cherchez toujours les termes et tournures de phrases les moins choquantes. | W6: =IF(N6>0,"F","T")
A7: 4 | C7: La négociation | D7: Communication | E7: Energie (E-extraverti ou I-Introverti) | F7: Capacité à trouver un accord avec un ou plusieurs partis. | G7: Vous trouvez un objet que vous souhaitiez acheter depuis longtemps, simplement le prix est trop élevé par rapport à votre budget. | H7: Vous contactez le vendeur pour trouver un accord gagnant-gagnant qui satisfait les deux parties. | I7: Vous argumentez sur la valeur réelle de l'objet et ses éventuels défauts pour obtenir un prix plus juste. | J7: Vous allez voir chez un concurrent pour trouver moins cher sans entrer dans une négociation. | K7: Vous préférez attendre d'avoir plus d'argent ou que le prix baisse de lui-même. | M7: =_xlfn.XLOOKUP(L7,'Questionnaire '!$R$2:$U$2,'Questionnaire '!$R7:$U7) | N7: =IF(L7="A",2,IF(L7="B",1,0)) | O7: Soft skills | P7: =IF(N7>=1,"","À développer") | R7: Vous maîtrisez l'art de la négociation. Vous savez construire des accords profitables pour toutes les parties. | S7: Vous savez négocier en vous appuyant sur des arguments concrets pour obtenir un meilleur prix. | T7: Vous évitez la négociation directe et préférez chercher une alternative. | U7: Vous n'aimez pas négocier et préférez attendre que la situation évolue d'elle-même. | W7: =IF(N7>0,"E","I")
A8: 5 | C8: Prise de parole en public | D8: Communication | E8: Energie (E-extraverti ou I-Introverti) | F8: Capacité à s'exprimer devant une foule, ou lors d'événements. | G8: Lorsqu'on vous demande de vous présenter devant une foule de personnes, votre première pensée est : | H8: Super vous allez faire le show, vous êtes pressé d'être sur la scène. | I8: Ça ne me dérange pas, je vais le faire. | J8: Je n’aime pas trop ça, mais je vais quand même essayer. | K8: Ce n'est pas du tout mon truc. Je vais paniquer et perdre mes moyens. | M8: =_xlfn.XLOOKUP(L8,'Questionnaire '!$R$2:$U$2,'Questionnaire '!$R8:$U8) | N8: =IF(L8="A",2,IF(L8="B",1,0)) | O8: Soft skills | P8: =IF(N8>=1,"","À développer") | R8: Vous aimez être le centre de l'attention et vous exprimer en public. | S8: Vous n'avez aucun problème à vous exprimer devant une foule. Vous n'êtes pas timide. | T8: Vous avez aussi tendance à éviter les prises de paroles en public. Ce n'est pas votre truc. | U8: Parler devant une foule vous met mal à l'aise et peut vous stresser. | W8: =IF(N8>0,"E","I")
A9: 6 | C9: Rhétorique ou storytelling | D9: Communication | E9: Energie (E-extraverti ou I-Introverti) | F9: L’art de savoir raconter ou narrer une histoire. | G9: Lorsque vous racontez une histoire, un évènement ou le résumé d'un film : | H9: Les personnes qui écoutent sont captivées et ont envie d'en savoir plus. | I9: Les auditeurs sont attentifs. | J9: Les auditeurs comprennent l’histoire mais ont l'air de s'ennuyer. | K9: Les personnes qui écoutent froncent les sourcils, comme si vous parliez un langage extraterrestre. | M9: =_xlfn.XLOOKUP(L9,'Questionnaire '!$R$2:$U$2,'Questionnaire '!$R9:$U9) | N9: =IF(L9="A",2,IF(L9="B",1,0)) | O9: Soft skills | P9: =IF(N9>=1,"","À développer") | R9: Vous avez un sens de l'art oratoire développé. | S9: Vous savez raconter les histoires et les anecdotes. En général, les gens vous écoutent attentivement. | T9: Vous avez du mal à capter l'attention des autres quand vous vous exprimez. | U9: Vous avez de vraies difficultés à structurer vos pensées et votre discours lorsque vous évoquez un évènement ou des anecdotes. | W9: =IF(N9>0,"E","I")
A10: 7 | C10: Actualisation des connaissances | D10: Esprit critique | E10: Recueil d'information ou perception (S-sensation ou N-intuition) | F10: Capacité à renouveler les connaissances et les compétences acquises. | G10: Lors d'une conversation avec des collègues, un nouveau logiciel révolutionnaire dans votre secteur est mentionné, mais vous ne le connaissez pas. Que faites-vous ensuite ? | H10: Lire les articles et les ouvrages les plus récents sur le sujet et allez aux conférences sur le sujet. | I10: je pose des questions à mes collègues pour en savoir plus, et j'envisage de m'informer davantage par la suite. | J10: Je ne m'en préoccupe pas vraiment, si c'est important, quelqu'un m'en parlera plus en détail. | K10: Je ne suis pas sûr(e) de vouloir investir du temps pour comprendre ce logiciel, s'il ne m'apporte rien immédiatement. | M10: =_xlfn.XLOOKUP(L10,'Questionnaire '!$R$2:$U$2,'Questionnaire '!$R10:$U10) | N10: =IF(L10="A",2,IF(L10="B",1,0)) | O10: Soft skills | P10: =IF(N10>=1,"","À développer") | R10: Vous aimez vous documenter, et cela, même sur un sujet où vous avez déjà une certaine expertise. | S10: Vous aimez vous documenter, et cela, même sur un sujet où vous avez déjà une certaine expertise. | T10: Vous n'êtes pas du type à systématiquement actualiser vos connaissances lorsque vous parlez d'un sujet. Vous préférez utiliser votre expérience et vos souvenirs. | U10: Vous n'êtes pas du type à systématiquement actualiser vos connaissances lorsque vous parlez d'un sujet. Vous préférez utiliser votre expérience et vos souvenirs. | W10: =IF(N10>0,"N","S")
A11: 8 | C11: L’acuité et le discernement | D11: Esprit critique | E11: Recueil d'information ou perception (S-sensation ou N-intuition) | F11: Capacité de l'esprit à juger clairement et sainement des choses | G11: Un de vos amis de confiance partage une publication qui affirme que l'utilisation fréquente des téléphones mobiles peut causer de graves problèmes de santé. Quelle est votre réaction ? | H11: Vous vérifierez l'information en cherchant des sources vraisemblables et des études scientifiques sur le sujet. | I11: Vous lui demandez où il a obtenu cette information. | J11: Vous partagez immédiatement l'information sur vos propres réseaux sociaux pour alerter vos amis et votre famille. | K11: Vous arrêtez d'utiliser votre téléphone mobile par peur des risques pour la santé. | M11: =_xlfn.XLOOKUP(L11,'Questionnaire '!$R$2:$U$2,'Questionnaire '!$R11:$U11) | N11: =IF(L11="A",2,IF(L11="B",1,0)) | O11: Soft skills | P11: =IF(N11>=1,"","À développer") | R11: Vous avez une faculté de discernement élevéee. | S11: Vous avez une faculté de discernement élevéee. | T11: Vous pouvez parfois manquer de discernement quand la situation l'impose. | U11: Vous pouvez parfois manquer de discernement quand la situation l'impose. | W11: =IF(N11>0,"N","S")
A12: 9 | C12: L’ouverture d'esprit | D12: Esprit critique | E12: Mode d'action ou style de vie (J-Organisation ou P-perception) | F12: Tolérer et manifester de l'intérêt, de la curiosité et de la compréhension pour les idées qui diffèrent en partie ou totalement des siennes. | G12: Une nouvelle personne intègre votre groupe de travail. Elle vous informe qu'une des méthodes que vous utilisez est totalement obsolète. | H12: Vous l'envoyez balader. Elle devrait écouter au lieu de critiquer dès son arrivée. | I12: Vous ne changez pas de méthode car elle a déjà fonctionné. | J12: Vous vous renseignez quand même sur les autres méthodes existantes. | K12: Par curiosité vous lui demandez quelle méthode serait la meilleure selon elle. | M12: =_xlfn.XLOOKUP(L12,'Questionnaire '!$R$2:$U$2,'Questionnaire '!$R12:$U12) | N12: =IF(L12="C",2,IF(L12="D",1,0)) | O12: Soft skills | P12: =IF(N12>=1,"","À développer") | R12: Votre ouverture d’esprit s’arrête au moment où vous vous sentez directement visé par les critiques. | S12: Vous pouvez souvent manquer d'ouverture si on remet en question vos capacités ou vos avis. | T12: Vous pouvez vous montrer ouvert d'esprit même quand une personne n'est pas d'accord avec vous sur un sujet qui vous concerne. | U12: Vous pouvez vous montrer ouvert d'esprit même quand une personne n'est pas d'accord avec vous sur certains sujets. | W12: =IF(N12>0,"N","S")
A13: 10 | C13: La créativité ou l'imagination | D13: Esprit critique | E13: Recueil d'information ou perception (S-sensation ou N-intuition) | F13: Faculté de former des images d'objets qui n'ont pas été perçus ou de créer de nouvelles combinaisons d'images ou d'idées, de se représenter des situations possibles. | G13: On vous demande de créer une histoire : | H13: Vous n'arrivez pas à imaginer quoi que ce soit, et vous détestez cet exercice. | I13: Vous demandez de l'aide à une amie qui a plus d'imagination que vous. | J13: Vous arrivez immédiatement à imaginer une trame et quelques personnages. | K13: Vous arrivez tout de suite à imaginer les lieux, l'époque, les costumes, des personnages, les langues, les voix et accents des personnages. | M13: =_xlfn.XLOOKUP(L13,'Questionnaire '!$R$2:$U$2,'Questionnaire '!$R13:$U13) | N13: =IF(L13="C",2,IF(L13="D",1,0)) | O13: Soft skills | P13: =IF(N13>=1,"","À développer") | R13: Vous pouvez souvent manquer d’imagination ou de créativité. | S13: Vous pouvez souvent manquer d’imagination ou de créativité. | T13: Vous êtes quelqu'un de créatif. | U13: Vous êtes quelqu'un de créatif. Vous avez beaucoup d'imagination. | W13: =IF(N13>0,"N","S")
A14: 11 | C14: Pensée critique | D14: Esprit critique | E14: Recueil d'information ou perception (S-sensation ou N-intuition) | F14: Disposition intellectuelle qui permet de raisonner correctement, de tirer des conclusions qui ne soient pas prématurées, mais réfléchies et étayées par des arguments.Capacité à questionner et remettre en cause des préjugés et des opinions "toutes faites". | G14: Vous devez partir en voyage dans un pays pour les vacances. Vous découvrez que le journal télévisé décrit ce pays comme dangereux. | H14: Je vais me renseigner auprès de personnes qui y sont déjà allées, afin d'avoir un avis précis de la situation. | I14: Avant d'acheter mon billet, je vais me renseigner auprès de l'ambassade du pays. | J14: Je vais me fier à l'information transmise par le journal télévisé et changer de destination. | K14: Je préfère me fier à mon intuition pour me décider. | M14: =_xlfn.XLOOKUP(L14,'Questionnaire '!$R$2:$U$2,'Questionnaire '!$R14:$U14) | N14: =IF(L14="A",2,IF(L14="B",1,0)) | O14: Soft skills | P14: =IF(N14>=1,"","À développer") | R14: Vous êtes attentif aux détails et aimez suggérer des améliorations à ce que vous observez. | S14: Vous utilisez plus vos sens que votre intuition pour juger et prendre des décisions. Vous aimez les éléments tangibles aux théories. Vous êtes observateur. | T14: Vous avez tendance à écouter facilement les avis des autres plutôt que vérifier les informations de vous-même. | U14: Vous préférez vous servir de votre intuition plutôt que de vos sens afin d'émettre un jugement. | W14: =IF(N14>0,"N","S")
A15: 12 | C15: Savoir rechercher pour résoudre un problème | D15: Esprit critique | E15: Recueil d'information ou perception (S-sensation ou N-intuition) | F15: Savoir mener des recherches, pour répondre à une question, pour résoudre un problème. | G15: Vous devez assembler un meuble complexe chez vous. Cependant, vous vous rendez compte que vous avez perdu le mode d'emploi. | H15: Vous allez contacter le constructeur ou le magasin afin qu’il vous fournisse le mode d'emploi. | I15: Vous allez rechercher sur internet si vous trouvez des vidéos explicatives. | J15: Vous appelez un expert pour qu'il construise le meuble à votre place. | K15: Vous utilisez votre intuition pour construire le meuble au fur et à mesure, et vous adapter. | M15: =_xlfn.XLOOKUP(L15,'Questionnaire '!$R$2:$U$2,'Questionnaire '!$R15:$U15) | N15: =IF(L15="A",2,IF(L15="B",1,0)) | O15: Soft skills | P15: =IF(N15>=1,"","À développer") | R15: Face à un problème, vous êtes du genre à rechercher toutes les informations pouvant vous permettre de le résoudre avant de demander l'aide d'un expert. | S15: Face à une complexité, vous préférez vous renseigner sur la source du problème pour pouvoir le résoudre. | T15: Vous avez tendance à rapidement demander de l'aide lorsque vous rencontrez un problème complexe. | U15: Face à une complexité, vous préférez vous servir de votre intuition plutôt que de rechercher la source du problème pour pouvoir le résoudre. | W15: =IF(N15>0,"N","S")
A16: 13 | C16: L’intégrité | D16: Ethique | E16: Prise de décision (T-pensée ou F-sentiment) | F16: Capacité à ne pas être corrompu ou influencé, à respecter les règles établis sans tricher. Être droit en toutes circonstances. | G16: Après avoir payé vos achats, vous remarquez que le caissier vous a rendu trop de monnaie. Comment réagissez-vous ? | H16: Je signale l'erreur au caissier et lui rends l'argent en trop. | I16: Je vérifie le montant rendu et, constatant l'erreur, je retourne à la caisse pour rectifier la situation. | J16: Je garde l'argent, car c'est une chance inattendue. | K16: Je garde l'argent, car c'est le caissier qui a fait l'erreur, pas moi. | M16: =_xlfn.XLOOKUP(L16,'Questionnaire '!$R$2:$U$2,'Questionnaire '!$R16:$U16) | N16: =IF(L16="A",2,IF(L16="B",1,0)) | O16: Soft skills | P16: =IF(N16>=1,"","À développer") | R16: Vous avez de l'intégrité. Vous signalez immédiatement l'erreur sans hésiter.. | S16: Vous avez de l'intégrité. Vous vérifiez et rectifiez l'erreur, même si personne ne vous a vu.. | T16: Vous manquez d'intégrité. Vous gardez l'argent sans hésiter.. | U16: Vous manquez d'intégrité. Vous gardez l'argent sans hésiter.. | W16: =IF(N16>0,"F","T")
A17: 14 | C17: La conscience professionnelle | D17: Ethique | E17: Prise de décision (T-pensée ou F-sentiment) | F17: Être soigneux et appliqué dans la réalisation d’une tâche ou d'un projet, d'un travail peu importe son état mental. | G17: Vous avez un travail de groupe important à finir pour le lendemain. Votre meilleur(e) ami(e) vous appelle, en vous expliquant qu'il/elle part 6 mois au Mexique et qu'il/elle aimerait passer sa dernière soirée avec vous. | H17: Vous terminez votre travail dans les délais prévus, en gérant votre émotion pour ne pas impacter le groupe. | I17: Vous faites une courte pause pour prendre des nouvelles, puis vous reprenez immédiatement votre travail afin de respecter l'engagement collectif. | J17: Vous lâchez tout pour rejoindre votre ami(e), car vous estimez que l'amitié passe avant tout. | K17: Vous demandez aux autres membres du groupe de finir sans vous, car le travail ne doit pas prendre le dessus sur les relations humaines. | M17: =_xlfn.XLOOKUP(L17,'Questionnaire '!$R$2:$U$2,'Questionnaire '!$R17:$U17) | N17: =IF(L17="A",2,IF(L17="B",1,0)) | O17: Soft skills | P17: =IF(N17>=1,"","À développer") | R17: Vous avez une conscience professionnelle très développée. Vous savez gérer vos émotions pour honorer vos engagements. | S17: Vous avez une bonne conscience professionnelle. Vous trouvez un équilibre entre vos engagements et votre vie personnelle. | T17: Votre conscience professionnelle est peu développée. Vous avez du mal à respecter vos engagements quand la vie personnelle s'invite. | U17: Vous manquez de conscience professionnelle. Vous n'hésitez pas à reporter vos responsabilités sur les autres. | W17: =IF(N17>0,"F","T")
A18: 15 | C18: La loyauté | D18: Ethique | E18: Prise de décision (T-pensée ou F-sentiment) | F18: Capacité à respecter les engagements fixés et être fidèle envers un organisme, un ou plusieurs individus, une loi, une doctrine, une croyance une religion…etc. | G18: Vous devez réaliser un travail de groupe entre amis. Cependant, le groupe de travail sympathique dans lequel vous êtes ne fonctionne pas du tout. Votre réaction : | H18: Vous restez dans le groupe et cherchez à les remotiver, les aider à s'organiser pour améliorer la performance collective. | I18: Vous restez fidèle au groupe et compensez leur manque en travaillant davantage pour ne pas les laisser tomber. | J18: Vous les quittez pour intégrer un groupe plus performant, car vous ne voulez pas être pénalisé par eux. | K18: Vous préférez travailler seul pour être sûr que le travail soit bien fait. | M18: =_xlfn.XLOOKUP(L18,'Questionnaire '!$R$2:$U$2,'Questionnaire '!$R18:$U18) | N18: =IF(L18="A",2,IF(L18="B",1,0)) | O18: Soft skills | P18: =IF(N18>=1,"","À développer") | R18: Vous êtes quelqu'un de loyal et de fédérateur. Vous ne lâchez pas les gens et cherchez à les faire progresser. | S18: Vous êtes loyal. Vous préférez rester fidèle à votre groupe et compenser plutôt que de les abandonner. | T18: Votre loyauté est limitée. Vous êtes prêt à abandonner le groupe dès que cela ne vous avantage plus. | U18: Vous n'êtes pas particulièrement loyal en groupe. Vous préférez votre réussite personnelle à la cohésion collective. | W18: =IF(N18>0,"F","T")
A19: 16 | C19: Le sens des responsabilités | D19: Ethique | E19: Prise de décision (T-pensée ou F-sentiment) | F19: Aptitude à s'assurer de la qualité des actions entreprises et en assumer les conséquences, qu'elles soient bonnes ou mauvaises. | G19: En jouant au foot près d'une maison vous brisez une fenêtre. Tous vos amis se mettent à courir, votre réaction : | H19: Je m'enfuis aussi. Il serait bête de rester là et se faire attraper. Pas vu pas pris. | I19: Je fais comme si je ne jouais pas au foot et j'indique que le coupable est parti en courant. | J19: J’attends dehors afin de me dénoncer. Si on doit me sanctionner on me sanctionnera. | K19: Je me dirige vers la maison pour m'excuser et trouver un moyen de réparer l'erreur. | M19: =_xlfn.XLOOKUP(L19,'Questionnaire '!$R$2:$U$2,'Questionnaire '!$R19:$U19) | N19: =IF(L19="C",2,IF(L19="D",1,0)) | O19: Soft skills | P19: =IF(N19>=1,"","À développer") | R19: Vous n'aimez pas vous mettre en danger, même quand vous êtes le responsable des tracas. | S19: Vous n'aimez pas vous mettre en danger, même quand vous êtes le responsable des tracas. | T19: Vous avez le sens des responsabilités et souhaitez souvent assumer vos erreurs. | U19: Vous avez le sens des responsabilités et souhaitez souvent assumer vos erreurs. | W19: =IF(N19>0,"F","T")
A20: 17 | C20: L'éco-responsabilité | D20: Ethique | E20: Prise de décision (T-pensée ou F-sentiment) | F20: Respecter les règles de protection de l'environnement | G20: Vous avez la possibilité d'acheter une voiture, vous avez le choix entre plusieurs possibilités : | H20: Je préfère acheter un vélo ou une trottinette électrique, car c'est le choix le moins polluant. | I20: J'achète une voiture 100% électrique, pour réduire au maximum mon impact environnemental. | J20: J'achète une voiture simple, fiable et durable qui correspond à mes besoins du quotidien. | K20: J'achète une grosse voiture à essence puissante, car ce qui compte c'est le plaisir de conduire. | M20: =_xlfn.XLOOKUP(L20,'Questionnaire '!$R$2:$U$2,'Questionnaire '!$R20:$U20) | N20: =IF(L20="A",2,IF(L20="B",1,0)) | O20: Soft skills | P20: =IF(N20>=1,"","À développer") | R20: Vous avez une forte conscience écologique. Vous faites des choix radicaux pour limiter votre impact sur l'environnement. | S20: Vous êtes éco-responsable. Vous faites des choix de mobilité en tenant compte de l'impact environnemental. | T20: Vous avez une conscience écologique modérée. Vous faites des choix pratiques sans priorité environnementale marquée. | U20: Vous avez peu de conscience écologique. Votre choix de mobilité ne tient pas compte de l'impact environnemental. | W20: =IF(N20>0,"F","T")
A21: 18 | C21: Respect des autres (doublon tolérance) | D21: Ethique | E21: Prise de décision (T-pensée ou F-sentiment) | F21: Avoir de la considération pour les idées, les opinions, les sentiments, les croyances, les coutumes d'un ou plusieurs individus sans émettre de jugement à leur encontre. | G21: Pourriez-vous prendre en considération une opinion qui bafoue vos principes, vos croyances et/ou votre culture ? | H21: Oui, c'est tout à fait possible. | I21: Oui, ça ne me dérange pas. | J21: Non, je ne préfère pas. | K21: Non, c'est tout à fait impossible. | M21: =_xlfn.XLOOKUP(L21,'Questionnaire '!$R$2:$U$2,'Questionnaire '!$R21:$U21) | N21: =IF(L21="A",2,IF(L21="B",1,0)) | O21: Soft skills | P21: =IF(N21>=1,"","À développer") | R21: Vous êtes tolérant envers les autres et prenez en considération leur avis même s'ils sont à l'opposé de vos croyances.. | S21: Vous êtes tolérant envers les autres et prenez en considération leur avis même s'ils sont à l'opposé de vos croyances.. | T21: Vous pouvez souvent faire preuve d'intolérance quant aux avis des autres. | U21: Vous pouvez souvent faire preuve d'intolérance quant aux avis des autres, surtout quand ils sont en contradiction avec les vôtres. | W21: =IF(N21>0,"F","T")
A22: 19 | C22: Acceptation des retours et critiques | D22: Intelligence émotionnelle | E22: Prise de décision (T-pensée ou F-sentiment) | F22: Capacité à recevoir des critiques constructives sans se vexer. | G22: Vous avez mis 3 mois à réaliser un dossier complexe, vous le montrez à un inconnu qui juge les résultats déplorables. | H22: Vous vous empressez de noter ses commentaires afin de comprendre ce qui ne va pas. | I22: Ça vous énerve, mais vous savez qu'aucun travail n'est parfait donc vous écoutez. | J22: Vous l'ignorez tout simplement, cette personne vous veut du mal. | K22: Vous l'envoyez valser, il ne sait pas à quel point vous vous êtes appliqué(e) dans votre travail. | M22: =_xlfn.XLOOKUP(L22,'Questionnaire '!$R$2:$U$2,'Questionnaire '!$R22:$U22) | N22: =IF(L22="A",2,IF(L22="B",1,0)) | O22: Soft skills | P22: =IF(N22>=1,"","À développer") | R22: Votre recherche d'amélioration vous permet d'apprécier et étudier les critiques. | S22: Les critiques vous irritent, mais vous préférez les écouter que de perdre un moyen de vous améliorer. | T22: Vous détestez être critiqué, surtout par des inconnus. | U22: Vous détestez être critiqué, surtout par des inconnus. | W22: =IF(N22>0,"F","T")
A23: 20 | C23: Introspection | D23: Intelligence émotionnelle | E23: Prise de décision (T-pensée ou F-sentiment) | F23: Aptitude à analyser ses propres émotions, ses aptitudes, ses faiblesses dans le but de se perfectionner. | G23: Si on vous demande de citer vos qualités et vos défauts, y arrivez-vous facilement ? | H23: Non, je n'y arrive jamais. | I23: En général, j'ai besoin qu'on m'aide à le faire. | J23: Plutôt oui. | K23: Oui, j'y arrive très facilement. | M23: =_xlfn.XLOOKUP(L23,'Questionnaire '!$R$2:$U$2,'Questionnaire '!$R23:$U23) | N23: =IF(L23="C",2,IF(L23="D",1,0)) | O23: Soft skills | P23: =IF(N23>=1,"","À développer") | R23: Vous avez des difficultés à expliquer qui vous êtes vraiment. Comme si vous ne vous connaissiez pas réellement.. | S23: Vous avez des difficultés à expliquer qui vous êtes vraiment. Comme si vous ne vous connaissiez pas réellement.. | T23: Vous arrivez à comprendre vos émotions et à les expliquer, mais pas facilement. | U23: Vous arrivez à comprendre vos émotions et à les expliquer facilement. | W23: =IF(N23>0,"F","T")
A24: 21 | C24: L’empathie | D24: Intelligence émotionnelle | E24: Energie (E-extraverti ou I-Introverti) | F24: Capacité à ressentir les émotions d’autres individus (joie, tristesse, honte, frustration, etc.). | G24: Vous assistez à un spectacle, l'un des acteurs oublie son texte et ne sait plus quoi dire. C'est le silence | H24: Vous ressentez une forte gêne et avez envie de l'aider en lui soufflant son texte ou en applaudissant pour l'encourager. | I24: Vous vous sentez mal à l'aise et ressentez profondément son embarras, comme si vous étiez à sa place. | J24: Vous trouvez la situation comique et cela vous fait sourire. | K24: Vous êtes déçu par sa prestation et trouvez cela peu professionnel. | M24: =_xlfn.XLOOKUP(L24,'Questionnaire '!$R$2:$U$2,'Questionnaire '!$R24:$U24) | N24: =IF(L24="A",2,IF(L24="B",1,0)) | O24: Soft skills | P24: =IF(N24>=1,"","À développer") | R24: Vous êtes très empathique. Vous ressentez les émotions des autres et avez le réflexe d'agir pour les soutenir. | S24: Vous êtes empathique. Vous savez vous mettre à la place des autres et ressentir ce qu'ils vivent. | T24: Votre empathie est peu développée. Vous avez du mal à ressentir les émotions des autres et prenez du recul. | U24: Vous manquez d'empathie. Vous jugez les situations de façon détachée sans vous mettre à la place des autres. | W24: =IF(N24>0,"E","I")
A25: 22 | C25: La confiance en soi | D25: Intelligence émotionnelle | E25: Energie (E-extraverti ou I-Introverti) | F25: Avoir toujours confiance en ses capacités ou ses actions. | G25: Vous avez l'opportunité de diriger un projet important au travail. Cela implique de prendre des décisions clés et de gérer une équipe. | H25: Je suis excité(e) par le défi et confiant(e) dans ma capacité à diriger le projet et à prendre les bonnes décisions. | I25: Même si je ressens une certaine pression, je suis sûr(e) de mes compétences et prêt(e) à assumer ce rôle de leadership. | J25: Je suis inquiet(e) à l'idée de ne pas être à la hauteur et j'hésite à accepter le rôle. | K25: La peur de l'échec me pousse à envisager de décliner l'offre, même si une partie de moi sait que je suis capable. | M25: =_xlfn.XLOOKUP(L25,'Questionnaire '!$R$2:$U$2,'Questionnaire '!$R25:$U25) | N25: =IF(L25="A",2,IF(L25="B",1,0)) | O25: Soft skills | P25: =IF(N25>=1,"","À développer") | R25: Vous débordez de confiance en vous, ce qui peut vous rendre téméraire parfois. | S25: En général, vous avez confiance en vos capacités. Vous êtes courageux dans ce que vous entreprenez | T25: Vous manquez parfois de confiance en vos capacités. | U25: Vous manquez parfois de confiance en vos capacités. | W25: =IF(N25>0,"E","I")
A26: 23 | C26: La gestion du stress | D26: Intelligence émotionnelle | E26: Mode d'action ou style de vie (J-Organisation ou P-perception) | F26: Capacité à supporter la pression liée à la réalisation d’une ou plusieurs tâches sans paniquer (examens, projets, demandes hiérarchiques, présentations, etc.). | G26: Une heure avant une présentation orale importante, votre ordinateur plante et vous perdez tous vos documents. Votre réaction : | H26: Vous déprimez et perdez vos moyens car tout est fini. Vous avez les larmes aux yeux. | I26: Vous faites tout pour annuler la présentation car vous ne pourrez pas vous souvenir de tout. | J26: Vous prenez une respiration, et tentez de reproduire votre présentation en puisant dans vos souvenirs. | K26: Vous y allez au talent. Ça passe ou ça casse. | M26: =_xlfn.XLOOKUP(L26,'Questionnaire '!$R$2:$U$2,'Questionnaire '!$R26:$U26) | N26: =IF(L26="C",2,IF(L26="D",1,0)) | O26: Soft skills | P26: =IF(N26>=1,"","À développer") | R26: Vous avez du mal à supporter les situations de stress intenses. Au point de perdre vos moyens. | S26: Vous avez du mal à supporter les situations de stress intenses. Au point de perdre vos moyens. | T26: Vous savez gérer vos émotions dans une situation stressantes. | U26: Vous pouvez être décalé en situation de stress, comme si vous étiez insensible à la situation. | W26: =IF(N26>0,"N","S")
A27: 24 | C27: La sensibilité | D27: Intelligence émotionnelle | E27: Prise de décision (T-pensée ou F-sentiment) | F27: Aptitude à s'émouvoir, à éprouver des sentiments d'humanité, de compassion, de tendresse envers autrui, autre chose ou un évènement. | G27: Vous venez d'apprendre que la femme d'un voisin, avec qui vous avez peu d'affinités, vient d'être hospitalisée dans un état grave, vous êtes du genre à : | H27: À ne rien ressentir, car vous n'êtes pas très proche de votre voisin. | I27: À ne pas vouloir vous mêler de ce qui ne vous regarde pas. | J27: À vouloir pleurer quand vous voyez votre voisin triste et désespéré. | K27: À vouloir l'aider et le réconforter même si vous n'êtes pas très proche. | M27: =_xlfn.XLOOKUP(L27,'Questionnaire '!$R$2:$U$2,'Questionnaire '!$R27:$U27) | N27: =IF(L27="C",2,IF(L27="D",1,0)) | O27: Soft skills | P27: =IF(N27>=1,"","À développer") | R27: Vous pouvez parfois manquer de sensibilité sur des sujets que d'autres trouveraient émouvant. | S27: Vous n'êtes pas quelqu'un que l'on peut émouvoir facilement.. | T27: Vous êtes quelqu'un de sensible et on peut vous émouvoir facilement. | U27: Vous êtes quelqu'un de sensible et on peut vous émouvoir facilement. | W27: =IF(N27>0,"F","T")
A28: 25 | C28: Altruisme | D28: Intelligence sociale | E28: Energie (E-extraverti ou I-Introverti) | F28: Capacité à se soucier du bien des autres et de s'y consacrer de façon désintéressée. | G28: Vous vous rendez compte que vous êtes le seul à avoir bien noté les informations liées à un examen important. | H28: Vous les partagez immédiatement avec tous ceux qui doivent passer l'examen, sans distinction. | I28: Vous les partagez en priorité avec ceux qui ont des difficultés dans la matière, pour les aider à réussir. | J28: Vous les partagez avec ceux qui pourraient vous apporter quelque chose en retour. | K28: Vous gardez cette information pour vous afin d'avoir un avantage sur les autres. | M28: =_xlfn.XLOOKUP(L28,'Questionnaire '!$R$2:$U$2,'Questionnaire '!$R28:$U28) | N28: =IF(L28="A",2,IF(L28="B",1,0)) | O28: Soft skills | P28: =IF(N28>=1,"","À développer") | R28: Vous êtes très altruiste. Vous partagez sans réfléchir et sans condition, car vous voulez que tout le monde réussisse. | S28: Vous êtes altruiste, avec une attention particulière pour ceux qui en ont le plus besoin. | T28: Votre altruisme est conditionnel. Vous aidez si vous pouvez en tirer quelque chose. | U28: Vous n'êtes pas altruiste. Vous préférez garder vos avantages pour vous. | W28: =IF(N28>0,"E","I")
A29: 26 | C29: Esprit d'équipe | D29: Intelligence sociale | E29: Energie (E-extraverti ou I-Introverti) | F29: Aptitude à faire preuve d'altruisme et de solidarité avec les membres de son groupe. | G29: Vous devez réaliser un travail, mais il sera pris en compte uniquement si vous le réalisez en groupe, votre réaction : | H29: Vous êtes heureux de pouvoir travailler à plusieurs, c'est plus amusant. | I29: Vous êtes pressé(e) de connaître vos futurs collaborateurs. | J29: Vous le faites mais uniquement parce que vous n'avez pas le choix. Sinon, vous auriez évité. | K29: Cette idée vous fatigue déjà. Vous détestez les travaux de groupe. | M29: =_xlfn.XLOOKUP(L29,'Questionnaire '!$R$2:$U$2,'Questionnaire '!$R29:$U29) | N29: =IF(L29="A",2,IF(L29="B",1,0)) | O29: Soft skills | P29: =IF(N29>=1,"","À développer") | R29: Vous aimez le travail en équipe. | S29: Vous aimez le travail en équipe tant que vous avez des affinité avec vos collaborateurs. | T29: Vous êtes du genre à travailler en équipe uniquement si cela est nécessaire.. Dans le cas contraire non. | U29: Vous êtes du genre à travailler en équipe uniquement si cela est nécessaire.. Dans le cas contraire non. | W29: =IF(N29>0,"E","I")
A30: 27 | C30: Intelligence culturelle | D30: Intelligence sociale | E30: Energie (E-extraverti ou I-Introverti) | F30: Capacité de s'adapter à différents contextes ou groupes culturels. | G30: Si vous deviez aller dans un pays étranger en vacances, vous seriez : | H30: La personne qui va essayer de parler la langue, apprendre les coutumes, aborder les styles vestimentaires. | I30: La personne qui va vouloir aller dormir chez les gens, aller visiter les lieux historiques. | J30: Celle qui va préférer aller au Macdonald à la place de découvrir la cuisine locale. | K30: La personne qui va préférer rester à l'hôtel pour profiter du calme et de la piscine un maximum. | M30: =_xlfn.XLOOKUP(L30,'Questionnaire '!$R$2:$U$2,'Questionnaire '!$R30:$U30) | N30: =IF(L30="A",2,IF(L30="B",1,0)) | O30: Soft skills | P30: =IF(N30>=1,"","À développer") | R30: Vous avez un attrait pour la découverte d'autres cultures et d'autres langues. | S30: Vous avez un attrait pour la découverte d'autres cultures et d'autres langues. | T30: Vous n'avez pas la particularité de vouloir découvrir d'autres cultures ou apprendre d'autres langues si ce n'est pas nécessaire. | U30: Vous n'avez pas la particularité de vouloir découvrir d'autres cultures ou apprendre d'autres langues si ce n'est pas nécessaire. | W30: =IF(N30>0,"E","I")
A31: 28 | C31: La coopération, la collaboration | D31: Intelligence sociale | E31: Energie (E-extraverti ou I-Introverti) | F31: Aptitude à travailler avec un ou plusieurs autres individus dans le but d'une réalisation commune. | G31: Avez-vous une facilité à collaborer avec des personnes avec qui vous n'avez aucunes affinités ? | H31: Oui, je m'adapte à n'importe quel profil et je sais travailler efficacement avec tout le monde, quelles que soient mes affinités. | I31: Oui, tant qu'on se respecte mutuellement, on peut collaborer sans nécessairement s'apprécier. | J31: Pas vraiment, il me faut un minimum de points communs pour travailler sereinement avec quelqu'un. | K31: Non, j'ai besoin d'apprécier les personnes avec qui je travaille pour être efficace. | M31: =_xlfn.XLOOKUP(L31,'Questionnaire '!$R$2:$U$2,'Questionnaire '!$R31:$U31) | N31: =IF(L31="A",2,IF(L31="B",1,0)) | O31: Soft skills | P31: =IF(N31>=1,"","À développer") | R31: Vous avez une excellente capacité de coopération. Vous savez mettre de côté vos affinités personnelles pour travailler avec n'importe qui. | S31: Vous savez coopérer avec des personnes que vous n'appréciez pas forcément, tant qu'il y a un respect mutuel. | T31: Votre capacité de coopération est limitée. Vous avez besoin d'un minimum d'affinités pour bien travailler avec quelqu'un. | U31: Vous avez du mal à collaborer avec des personnes que vous n'appréciez pas. Cela peut limiter votre efficacité en équipe. | W31: =IF(N31>0,"E","I")
A32: 29 | C32: Le networking | D32: Intelligence sociale | E32: Energie (E-extraverti ou I-Introverti) | F32: Capacité à nouer et maintenir des liens avec d'autres individus et de se créer un réseau sur le long terme. | G32: Aimez-vous nouer des liens avec les gens et entretenir les relations sur le long terme ? | H32: Oui carrément j'adore ça, et je le fais très bien. | I32: Plutôt oui, mais je ne suis pas encore expert en la matière. | J32: Non pas du tout, je préfère avoir un petit groupe d'amis. | K32: Non, je préfère être seul. | M32: =_xlfn.XLOOKUP(L32,'Questionnaire '!$R$2:$U$2,'Questionnaire '!$R32:$U32) | N32: =IF(L32="A",2,IF(L32="B",1,0)) | O32: Soft skills | P32: =IF(N32>=1,"","À développer") | R32: Vous prenez du plaisir à créer une communauté ou un réseau autour de vous. Vous êtes du genre à vous faire des amis rapidement. | S32: Vous prenez du plaisir à créer une communauté ou un réseau autour de vous. Vous êtes du genre à vous faire des amis rapidement. | T32: Vous préférez avoir un petit groupe d'amis plutôt qu’une multitude de connaissances. Ce qui peut vous empêcher d’avoir un réseau de connaissances large. | U32: Vous êtes quelqu'un de solitaire. | W32: =IF(N32>0,"E","I")
A33: 30 | C33: Sociabilité | D33: Intelligence sociale | E33: Energie (E-extraverti ou I-Introverti) | F33: Capacité à vivre en société ou avec un groupe d'individu. Recherche de compagnie. | G33: Lorsque vous devez aller en soirée ou à un anniversaire vous êtes du genre à : | H33: Aller parler à tout le monde car vous voulez absolument savoir qui est qui. | I33: Lancer les conversations même si vous n'y êtes pas obligé. | J33: A chercher un moyen de vous échapper pour éviter de parler aux gens. | K33: Essayer de ne pas aller en soirée ou aux anniversaires. | M33: =_xlfn.XLOOKUP(L33,'Questionnaire '!$R$2:$U$2,'Questionnaire '!$R33:$U33) | N33: =IF(L33="A",2,IF(L33="B",1,0)) | O33: Soft skills | P33: =IF(N33>=1,"","À développer") | R33: Vous êtes extrêmement sociable.. | S33: Vous n'aimez pas les moments de silence et de gène. Votre sociabilité vous incite à lancer les conversations. | T33: Vous n'êtes pas quelqu'un de très sociable. | U33: Vous n'êtes pas quelqu'un de très sociable. | W33: =IF(N33>0,"E","I")
A34: 31 | B34: Etats d'esprit et attitude | C34: L’Autonomie | D34: Management de projet | E34: Mode d'action ou style de vie (J-Organisation ou P-perception) | F34: Ne pas avoir besoin d’accompagnement lorsque l’on entreprend une action. | G34: Lorsqu'on vous confie un projet ou une tâche sans instructions détaillées, comment procédez-vous ? | H34: Je me fixe mes propres objectifs et échéances, j'organise mon travail de façon autonome et je cherche les ressources nécessaires par moi-même.. | I34: Je recherche des informations en ligne — tutoriels, forums, articles — pour trouver comment réaliser le travail au mieux. | J34: Je préfère me faire accompagner par un expert pour être sûr que le travail soit bien réalisé. | K34: Je demande de l'aide à des amis ou collègues qui s'y connaissent mieux que moi. | M34: =_xlfn.XLOOKUP(L34,'Questionnaire '!$R$2:$U$2,'Questionnaire '!$R34:$U34) | N34: =IF(L34="A",2,IF(L34="B",1,0)) | O34: Soft skills | P34: =IF(N34>=1,"","À développer") | R34: Vous êtes très autonome. Vous savez vous organiser, vous fixer des objectifs et trouver les ressources nécessaires sans aide extérieure. | S34: Vous êtes autonome. Vous n'hésitez pas à chercher par vous-même les informations dont vous avez besoin pour avancer. | T34: Votre autonomie est limitée. Vous avez besoin d'être accompagné pour réaliser des tâches sans instructions détaillées. | U34: Vous manquez d'autonomie. Vous cherchez rapidement de l'aide plutôt que d'essayer de trouver des solutions par vous-même. | W34: =IF(N34>0,"N","S")
A35: 32 | C35: La fixation d'objectifs | D35: Management de projet | E35: Prise de décision (T-pensée ou F-sentiment) | F35: Capacité à fixer des objectifs spécifiques, mesurables, atteignables, réalistes et temporels. | G35: Vous envisagez d'apprendre une nouvelle langue cette année. Comment prévoyez-vous de gérer ce projet ? | H35: Je planifie un certain nombre d'heures par semaine à l'étude de la langue et je fixe des délais pour évaluer mes progrès, comme maîtriser les bases d'ici trois mois. | I35: Je m'inscris à un cours en ligne et je me fixe des objectifs clairs, par exemple atteindre un niveau intermédiaire en six mois, en suivant régulièrement les leçons et en pratiquant quotidiennement. | J35: J'achète des livres de langue et des applications, mais sans plan précis sur comment et quand les utiliser. | K35: J'ai l'intention d'apprendre quand j'ai du temps libre, sans me fixer d'objectifs ou de calendrier spécifiques. | M35: =_xlfn.XLOOKUP(L35,'Questionnaire '!$R$2:$U$2,'Questionnaire '!$R35:$U35) | N35: =IF(L35="A",2,IF(L35="B",1,0)) | O35: Soft skills | P35: =IF(N35>=1,"","À développer") | R35: Vous n'aimez pas vous fixer des objectifs qui vous semblent disproportionnés par rapport à vos capacités. Vous êtes réaliste. | S35: Vous n'aimez pas vous fixer des objectifs qui vous semblent disproportionnés par rapport à vos capacités. Vous êtes réaliste. | T35: Vous êtes très ambitieux. Cependant, vous avez tendance à vous fixer des objectifs sans prendre en compte vos capacités réelles. | U35: Vous êtes très ambitieux. Cependant, vous avez tendance à vous fixer des objectifs sans prendre en compte vos capacités réelles. | W35: =IF(N35>0,"F","T")
A36: 33 | C36: La gestion des risques | D36: Management de projet | E36: Prise de décision (T-pensée ou F-sentiment) | F36: Capacité à lister et évaluer les scénarios problématiques et trouver des solutions pouvant les résoudre. | G36: Lorsque l'on met en place un projet, quel qu’il soit, que faut-il prendre en compte en premier lieu ? | H36: Les divers évènements qui pourraient faire en sorte que le projet soit annulé. | I36: Avoir un plan de secours pour chaque imprévu. | J36: Que la qualité de l'évènement soit bien au rendez-vous. | K36: L’avis des participants, car l'essentiel c'est que ça leurs plaise. | M36: =_xlfn.XLOOKUP(L36,'Questionnaire '!$R$2:$U$2,'Questionnaire '!$R36:$U36) | N36: =IF(L36="A",2,IF(L36="B",1,0)) | O36: Soft skills | P36: =IF(N36>=1,"","À développer") | R36: Vous préférez prévoir les évènements néfastes d’un projet avant de le commencer, par peur de ne pas le mener à bien. | S36: Vous préférez prévoir les évènements néfastes d’un projet avant de le commencer, par peur de ne pas le mener à bien. | T36: Vous n'êtes pas du genre à vouloir prévoir les évènements nuisibles. Vous préférez réagir aux conséquences que les prévenir. | U36: Vous n'êtes pas du genre à vouloir prévoir les évènements nuisibles. Vous préférez réagir aux conséquences que les prévenir. | W36: =IF(N36>0,"F","T")
A37: 34 | C37: La prise de décision | D37: Management de projet | E37: Prise de décision (T-pensée ou F-sentiment) | F37: Aptitude à effectuer un choix entre plusieurs modalités d'actions possibles lors de la confrontation à un problème. | G37: Il reste 3 mois à vivre à une personne que vous aimez. Un médecin propose une solution qui pourrait prolonger sa vie de 10 ans en cas de réussite, ou le tuer en cas d'échec. | H37: Vous lisez toutes les études disponibles sur l'opération, évaluez les risques et bénéfices, puis prenez votre décision de façon éclairée. | I37: Vous prenez la décision de mettre en place la solution, car face à l'urgence, il vaut mieux agir que d'attendre. | J37: Vous réunissez les proches pour décider collectivement, car une telle décision ne doit pas reposer sur une seule personne. | K37: Vous ne parvenez pas à prendre de décision, car l'enjeu est trop lourd à porter. | M37: =_xlfn.XLOOKUP(L37,'Questionnaire '!$R$2:$U$2,'Questionnaire '!$R37:$U37) | N37: =IF(L37="A",2,IF(L37="B",1,0)) | O37: Soft skills | P37: =IF(N37>=1,"","À développer") | R37: Vous prenez vos décisions difficiles avec rigueur et méthode. Vous vous informez avant d'agir, même sous pression. | S37: Vous savez prendre des décisions difficiles et les assumer, même quand elles comportent une part d'incertitude. | T37: Vous avez du mal à prendre seul des décisions difficiles. Vous cherchez à diluer la responsabilité. | U37: Vous avez des difficultés à prendre des décisions sous pression. La peur de vous tromper vous paralyse. | W37: =IF(N37>0,"F","T")
A38: 35 | C38: La supervision | D38: Management de projet | E38: Mode d'action ou style de vie (J-Organisation ou P-perception) | F38: Capacité à exercer un contrôle et à effectuer une vérification sur l'activité ou le travail d'une ou plusieurs personnes. | G38: Lorsque vous effectuez un travail de groupe, ce que vous préférez c'est : | H38: Etablir des outils qui permettront de contrôler l'avancée des travaux. | I38: Vérifier au fur et à mesure que les tâches ont bien été réalisées | J38: Terminer vite, contrôler la qualité, et ensuite tout corriger. | K38: Réaliser en premier lieu les tâches qui vous plaisent le plus et les autres ensuite. | M38: =_xlfn.XLOOKUP(L38,'Questionnaire '!$R$2:$U$2,'Questionnaire '!$R38:$U38) | N38: =IF(L38="A",2,IF(L38="B",1,0)) | O38: Soft skills | P38: =IF(N38>=1,"","À développer") | R38: Vous aimez superviser et surveiller les activités ou les tâches qui doivent être réalisées. | S38: Lorsque vous travaillez en groupe, vous aimez contrôler régulièrement l'avancée des travaux. vous avez un attrait pour la supervision. | T38: Dans un travail de groupe, vous vous concentrez plus sur votre travail que celui des autres. Vous n'aimez pas contrôler et surveiller. | U38: Dans un travail de groupe, vous vous concentrez plus sur votre travail que celui des autres. Vous n'aimez pas contrôler et surveiller. | W38: =IF(N38>0,"N","S")
A39: 36 | C39: L'agilité cognitive | D39: Management de projet | E39: Mode d'action ou style de vie (J-Organisation ou P-perception) | F39: Aptitude à s'adapter facilement aux changements et à réagir aux problématiques qui ne répondent pas à notre mode de fonctionnement mental. | G39: Imaginons que vous êtes en train de jouer à un jeu de société avec des amis. D'un coup, toutes les règles établies sont modifiées. Comment réagissez-vous ? | H39: J'arrête de jouer car il n'est pas normal de changer les règles en cours de jeu. | I39: Ce changement me perturbe et m’énerve au plus haut point. Je ne sais pas quoi faire. | J39: Je lis les nouvelles règles du jeu et j'essaie de gagner quand même. | K39: Je continue à jouer car ça pourra être amusant. | M39: =_xlfn.XLOOKUP(L39,'Questionnaire '!$R$2:$U$2,'Questionnaire '!$R39:$U39) | N39: =IF(L39="C",2,IF(L39="D",1,0)) | O39: Soft skills | P39: =IF(N39>=1,"","À développer") | R39: Vous détestez être pris de court. Vous avez d'ailleurs du mal à gérer émotionnellement avec les évènements imprévus. | S39: Vous détestez être pris de court. Vous avez d'ailleurs du mal à gérer émotionnellement avec les évènements imprévus. | T39: Vous n'êtes pas perturbé par l'apparition d'évènements imprévus. | U39: Vous n'êtes pas perturbé par l'apparition d'évènements imprévus. Vous les trouvez parfois galvanisant. | W39: =IF(N39>0,"N","S")
A40: 37 | C40: Équité | D40: Management et gestion d'équipe | E40: Prise de décision (T-pensée ou F-sentiment) | F40: Capacité à traiter les situations et les individus de manière juste et impartiale, sans parti pris. | G40: Comment pensez-vous que les richesses du monde devraient être réparties ? | H40: Les pays riches devraient aider les pays pauvres. | I40: Tout le monde devrait avoir assez pour vivre correctement. | J40: Je pense que la répartition des richesses est un reflet de la compétence et du talent individuel, et qu'il n'est pas nécessaire d'ajuster le système. | K40: Je ne crois pas qu'il soit nécessaire de redistribuer les richesses du monde ; si certains pays ou personnes sont plus riches, c'est parce qu'ils ont travaillé plus dur pour l'être. | M40: =_xlfn.XLOOKUP(L40,'Questionnaire '!$R$2:$U$2,'Questionnaire '!$R40:$U40) | N40: =IF(L40="A",2,IF(L40="B",1,0)) | O40: Soft skills | P40: =IF(N40>=1,"","À développer") | R40: Vous cherchez à être équitable dans vos choix et décisions. Surtout quand cela peut impacter la vie des gens. | S40: Vous cherchez à être équitable dans vos choix et décisions. Surtout quand cela peut impacter la vie des gens. | T40: Vous recherchez plus l'égalité de traitement à l'équité de traitement. Vous aimez que tout le monde soit traité de la même façon, peu importe leur condition. | U40: Vous recherchez plus l'égalité de traitement à l'équité de traitement. Vous aimez que tout le monde soit traité de la même façon, peu importe leur condition. | W40: =IF(N40>0,"F","T")
A41: 38 | C41: Gérer et résoudre les conflits | D41: Management et gestion d'équipe | E41: Prise de décision (T-pensée ou F-sentiment) | F41: Capacité à être médiateur et trouver les solutions aux situations de tension entre deux ou plusieurs individus. | G41: Lorsque deux personnes que vous connaissez sont en conflit, vous avez tendance à : | H41: Vous cherchez l'origine du conflit, vous comprenez les deux points de vue et vous proposez une solution concrète. | I41: Vous mettez en place une médiation pour que les deux parties puissent s'exprimer calmement et trouver un terrain d'entente. | J41: Vous préférez ne pas intervenir par peur que cela vous retombe dessus. | K41: Vous ne vous impliquez pas, car vous craignez d'aggraver la situation. | M41: =_xlfn.XLOOKUP(L41,'Questionnaire '!$R$2:$U$2,'Questionnaire '!$R41:$U41) | N41: =IF(L41="A",2,IF(L41="B",1,0)) | O41: Soft skills | P41: =IF(N41>=1,"","À développer") | R41: Vous gérez les conflits avec efficacité. Vous analysez la situation et proposez des solutions concrètes. | S41: Vous savez gérer les conflits en facilitant le dialogue entre les parties concernées. | T41: Vous évitez les conflits par peur des répercussions. Vous manquez d'initiative dans ce domaine. | U41: Vous ne savez pas gérer les conflits et préférez vous en tenir à l'écart. | W41: =IF(N41>0,"F","T")
A42: 39 | C42: Inclusivité | D42: Management et gestion d'équipe | E42: Energie (E-extraverti ou I-Introverti) | F42: Aptitude à intégrer facilement un individu à un groupe. C'est différent de l'exclusion. | G42: Vous êtes dans une soirée en appartement, vous remarquez qu'un(e) des invité(e)s est seul(e) dans son coin : | H42: Vous allez le/la chercher pour l'intégrer à votre groupe de discussion. | I42: Vous allez lui parler pour qu'il/elle se sente moins seul(e). | J42: Vous le/la laissez dans son coin il/elle se fera des amis par il/elle-même. | K42: Vous faites comme si vous ne l'avez pas vu. | M42: =_xlfn.XLOOKUP(L42,'Questionnaire '!$R$2:$U$2,'Questionnaire '!$R42:$U42) | N42: =IF(L42="A",2,IF(L42="B",1,0)) | O42: Soft skills | P42: =IF(N42>=1,"","À développer") | R42: Vous n'aimez pas l'exclusion. Vous avez tendance à inclure les gens dans votre groupe si vous les sentez seuls ou isolés. | S42: Vous n'aimez pas l'exclusion. Vous avez tendance à inclure les gens dans votre groupe si vous les sentez seuls ou isolés. | T42: Vous n'êtes pas du genre à vouloir inclure des gens dans votre groupe si vous estimez qu'ils ne vous apporteront rien. | U42: Vous n'êtes pas du genre à vouloir inclure des gens dans votre groupe si vous estimez qu'ils ne vous apporteront rien. | W42: =IF(N42>0,"E","I")
A43: 40 | B43: Etats d'esprit et attitude | C43: L’esprit d’initiative | D43: Management et gestion d'équipe | E43: Mode d'action ou style de vie (J-Organisation ou P-perception) | F43: Capacité à entreprendre des actions sans que l'on y soit poussé. | G43: Vous êtes en face d'un travail qui nécessite une compétence que vous n'avez pas, allez-vous chercher à le réaliser quand même ? | H43: Non, car le travail sera mal réalisé. | I43: Non, sauf si un expert peut m'aider. | J43: Oui et je vais m'autoformer grâce à internet. | K43: Oui, et je m'adapterai au fur et à mesure. | M43: =_xlfn.XLOOKUP(L43,'Questionnaire '!$R$2:$U$2,'Questionnaire '!$R43:$U43) | N43: =IF(L43="C",2,IF(L43="D",1,0)) | O43: Soft skills | P43: =IF(N43>=1,"","À développer") | R43: Vous pouvez parfois manquer d'esprit d'initiative. | S43: Vous pouvez parfois manquer d'esprit d'initiative. | T43: Vous avez un esprit d'initiative développé. | U43: Vous avez un esprit d'initiative développé, et êtes courageux dans ce que vous entreprenez. | W43: =IF(N43>0,"N","S")
A44: 41 | C44: Le coaching des autres | D44: Management et gestion d'équipe | E44: Energie (E-extraverti ou I-Introverti) | F44: Capacité à stimuler l'intérêt des autres sur un sujet, une mission, un travail et faire ressortir le meilleur d'eux même. | G44: Vous remarquez qu’un membre de votre groupe de travail a du mal à réaliser les travaux qui lui sont confiés. | H44: Vous cherchez d'abord à comprendre ses difficultés, puis vous l'accompagnez avec une formation adaptée pour qu'il progresse durablement. | I44: Vous prenez le temps de comprendre pourquoi il bloque et vous lui prodiguez des conseils ciblés pour l'aider à avancer. | J44: Vous le laissez trouver les solutions par lui-même, car c'est en cherchant qu'on apprend. | K44: Vous prenez en charge les travaux vous-même pour éviter de perdre du temps. | M44: =_xlfn.XLOOKUP(L44,'Questionnaire '!$R$2:$U$2,'Questionnaire '!$R44:$U44) | N44: =IF(L44="A",2,IF(L44="B",1,0)) | O44: Soft skills | P44: =IF(N44>=1,"","À développer") | R44: Vous êtes un excellent coach. Vous diagnostiquez les difficultés et accompagnez les autres vers une progression durable. | S44: Vous aimez aider les autres à progresser en leur donnant des conseils pertinents et adaptés. | T44: Vous croyez en l'apprentissage autonome, mais vous pouvez manquer de soutien envers ceux qui ont besoin d'aide. | U44: Vous préférez faire à la place des autres plutôt que de les aider à progresser. Le coaching n'est pas votre priorité. | W44: =IF(N44>0,"E","I")
A45: 42 | C45: Leadership | D45: Management et gestion d'équipe | E45: Mode d'action ou style de vie (J-Organisation ou P-perception) | F45: Capacité à réunir et diriger plusieurs individus sans utiliser la force, pour mener à bien un projet ou une action. | G45: Lorsque vous êtes dans un groupe de travail, vous êtes celui : | H45: qu'on laisse prendre la direction du groupe pour montrer la direction à suivre. | I45: dont les idées sont écoutées et réalisées. | J45: qui va suivre le plan de manière rigoureuse, pour que tout se passe bien. | K45: qui écoute ce que les gens ont à dire d'intéressant sans s'imposer. | M45: =_xlfn.XLOOKUP(L45,'Questionnaire '!$R$2:$U$2,'Questionnaire '!$R45:$U45) | N45: =IF(L45="A",2,IF(L45="B",1,0)) | O45: Soft skills | P45: =IF(N45>=1,"","À développer") | R45: Vous aimez prendre le lead quand un projet doit se mettre en place. Vous aimez montrer la voie à suivre. | S45: Vous aimez prendre le lead quand un projet doit se mettre en place. Vous aimez montrer la voie à suivre. | T45: Vous n'aimez pas prendre le lead même quand vous le pouvez. Vous préférez laisser ça aux autres. | U45: Vous n'aimez pas prendre le lead même quand vous le pouvez. Vous préférez laisser ça aux autres. | W45: =IF(N45>0,"N","S")
A46: 43 | C46: L’auto-formation | D46: Organisation | E46: Mode d'action ou style de vie (J-Organisation ou P-perception) | F46: Capacité à se former sans aide extérieure d’un mentor, professeur ou guide | G46: Vous entendez parler d'un sujet intéressant qui n'est pas couvert par ton cursus scolaire ou par ta formation. Que faites-vous ? | H46: Je recherche des ressources en ligne, comme des cours, des vidéos, ou des articles pour en apprendre davantage par moi-même.. | I46: J'emprunte ou j'achète des livres, je cherche des tutoriels en ligne pour approfondir mes connaissances sur le sujet. | J46: Je trouve ça intéressant, mais je ne vois pas l'intérêt d'en apprendre plus que ce que propose déjà ma formation.. | K46: Je pense que c'est la responsabilité des enseignants de nous apprendre ces choses, donc pas besoin d'explorer davantage par moi-même... | M46: =_xlfn.XLOOKUP(L46,'Questionnaire '!$R$2:$U$2,'Questionnaire '!$R46:$U46) | N46: =IF(L46="A",2,IF(L46="B",1,0)) | O46: Soft skills | P46: =IF(N46>=1,"","À développer") | R46: Vous savez vous autoformer. Vous n'avez pas besoin d'aide extérieure pour apprendre. ou d'un professeur quand le besoin s'en ressent. | S46: Vous savez vous autoformer. Vous n'avez pas besoin d'aide extérieure pour apprendre. ou d'un professeur quand le besoin s'en ressent. | T46: Vous avez du mal à vous autoformer et préférez être accompagné(e) par un mentor ou un professeur.. | U46: Vous avez du mal à vous autoformer et préférez être accompagné(e) par un mentor ou un professeur.. | W46: =IF(N46>0,"N","S")
A47: 44 | C47: La concentration | D47: Organisation | E47: Mode d'action ou style de vie (J-Organisation ou P-perception) | F47: Capacité à focaliser son esprit sur une tâche, ou un sujet particulier sans diverger. | G47: Vous devez compléter une tâche longue et répétitive, et ennuyeuse. Comment maintenez-vous votre concentration tout au long de cette tâche ? | H47: Je me fixe des petits objectifs à atteindre et je prends de courtes pauses pour rester concentré et motivé. | I47: J'alterne entre cette tâche et d'autres activités plus stimulantes pour garder mon esprit alerte. | J47: Je trouve cela très difficile et je me laisse souvent distraire par d'autres choses, comme votre téléphone. | K47: J'ai tendance à procrastiner ou à éviter la tâche, car je la trouve trop ennuyeuse | M47: =_xlfn.XLOOKUP(L47,'Questionnaire '!$R$2:$U$2,'Questionnaire '!$R47:$U47) | N47: =IF(L47="A",2,IF(L47="B",1,0)) | O47: Soft skills | P47: =IF(N47>=1,"","À développer") | R47: Vous n’avez pas besoin d’apprécier une tâche ou une activité, afin de vous concentrer pleinement dessus. | S47: Vous n’avez pas besoin d’apprécier une tâche ou une activité, afin de vous concentrer pleinement dessus. | T47: Si une tâche ou une activité ne vous intéresse pas, il vous est difficile de rester longtemps concentré dessus. | U47: Si vous trouvez une tâche ou une activité ennuyeuse, vous aurez énormément de mal à vous concentrer dessus, peu importe son importance. | W47: =IF(N47>0,"N","S")
A48: 45 | C48: La gestion du temps | D48: Organisation | E48: Mode d'action ou style de vie (J-Organisation ou P-perception) | F48: Capacité à organiser ce que l’on entreprend afin de respecter les délais accordés. | G48: Vous devez rendre un travail dans plusieurs mois, vous préférez : | H48: Vous organiser de façon à ce que vous puissiez travailler chaque jour dessus. À un rythme régulier. | I48: Identifier les tâches les plus simples et les réaliser rapidement pour pouvoir prendre plus de temps sur les autres. | J48: Réaliser le travail en fonction de votre motivation du jour. | K48: Attendre le dernier moment pour le réaliser, car c'est là que vous êtes le plus performant. | M48: =_xlfn.XLOOKUP(L48,'Questionnaire '!$R$2:$U$2,'Questionnaire '!$R48:$U48) | N48: =IF(L48="A",2,IF(L48="B",1,0)) | O48: Soft skills | P48: =IF(N48>=1,"","À développer") | R48: Vous aimez gérer votre temps correctement et prendre de l'avance sur les activités. | S48: Vous aimez gérer votre temps correctement et prendre de l'avance sur les activités. | T48: Vous avez du mal à gérer votre temps correctement, lorsque vous entreprenez quelque chose. | U48: Vous avez du mal à gérer votre temps correctement, lorsque vous entreprenez quelque chose. | W48: =IF(N48>0,"N","S")
A49: 46 | C49: La planification | D49: Organisation | E49: Mode d'action ou style de vie (J-Organisation ou P-perception) | F49: Capacité à organiser les actions et tâches selon un plan défini temporellement | G49: Pour passer les meilleures vacances possibles, il vaut mieux : | H49: Planifier chaque étape de vos vacances avec les dates, les lieux, les prix. | I49: Calculer les délais de chaque activité afin de les réaliser au bon moment, pour plus de fun. | J49: Surtout chercher à se reposer l’esprit, en se prélassant. | K49: Improviser une fois sur place, car ce qui est spontané est plus amusant. | M49: =_xlfn.XLOOKUP(L49,'Questionnaire '!$R$2:$U$2,'Questionnaire '!$R49:$U49) | N49: =IF(L49="A",2,IF(L49="B",1,0)) | O49: Soft skills | P49: =IF(N49>=1,"","À développer") | R49: Vous aimez planifier les choses. Vous n'aimez pas être débordé ou perturbé par un manque de prévision. | S49: Vous aimez planifier les choses. Vous n'aimez pas être débordé ou perturbé par un manque de prévision. | T49: Vous n'aimez pas planifier les choses et vous avez parfois du mal à le faire. | U49: Vous n'aimez pas planifier les choses et vous avez parfois du mal à le faire. | W49: =IF(N49>0,"N","S")
A50: 47 | C50: La visualisation | D50: Organisation | E50: Recueil d'information ou perception (S-sensation ou N-intuition) | F50: Capacité de se projeter mentalement dans une situation future. | G50: Lorsque vous vous préparez pour un projet important ou un événement à venir, comment planifiez-vous vos actions | H50: Vous vous imaginez toutes les étapes nécessaires pour atteindre mon objectif et je les visualise clairement clairement dans votre tête.. | I50: Vous utilisez des outils comme des cartes mentales ou des listes pour organiser mes pensées et visualiser comment vous allez aborder le projet. | J50: Vous vous sentez souvent dépassé(e) et je ne sais pas par où commencer, donc vous ne faites pas vraiment de planification visuelle.. | K50: Vous attendez que les choses se présentent et je réagis au fur et à mesure, sans visualiser à l'avance le processus ou le résultat.. | M50: =_xlfn.XLOOKUP(L50,'Questionnaire '!$R$2:$U$2,'Questionnaire '!$R50:$U50) | N50: =IF(L50="A",2,IF(L50="B",1,0)) | O50: Soft skills | P50: =IF(N50>=1,"","À développer") | R50: Vous avez de l'imagination et vous projetez facilement dans des situations futures.. | S50: Vous avez de l'imagination et visualisez facilement les étapes à venir.. | T50: Vous avez du mal à vous projeter mentalement dans une situation future. La planification visuelle est difficile pour vous.. | U50: Vous avez du mal à vous projeter mentalement dans une situation future. La planification visuelle est difficile pour vous.. | W50: =IF(N50>0,"N","S")
A51: 48 | C51: Le respect des délais | D51: Organisation | E51: Mode d'action ou style de vie (J-Organisation ou P-perception) | F51: Aptitude à arriver à l'heure et rendre les attendus au moment demandé | G51: Vous avez rendez-vous avec l'élu de votre cœur près d'un lac romantique, vous êtes plutôt du genre à : | H51: Arriver en avance afin d'être sûr de ne pas le faire attendre. | I51: Arriver pile à l'heure du rendez-vous pour profiter au maximum du temps passé avec lui. | J51: Arriver 5 minutes en retard pour ne pas passer pour celui ou celle qui était en train de l'attendre. | K51: Arriver en retard parce que vous mettez beaucoup de temps à vous préparer. | M51: =_xlfn.XLOOKUP(L51,'Questionnaire '!$R$2:$U$2,'Questionnaire '!$R51:$U51) | N51: =IF(L51="A",2,IF(L51="B",1,0)) | O51: Soft skills | P51: =IF(N51>=1,"","À développer") | R51: En général, vous faites tout pour respecter les délais et horaires fixés. | S51: En général, vous faites tout pour respecter les délais et horaires fixés. | T51: Vous avez du mal à respecter les délais et les horaires fixés. | U51: Vous avez du mal à respecter les délais et les horaires fixés. | W51: =IF(N51>0,"N","S")

Sheet Résultat test questionnaire
B2: Analyse Soft skills | C2: Max possible | D2: Score obtenu | E2: % de maîtrise | F2: Niveau
B3: Catégorie soft skills | C3: Barème | D3: Résultat | E3: Pourcentage de réponses en accord avec la catégorie | F3: Niveau | G3: Schéma de personnalité
B4: Communication | C4: =COUNTIF('Questionnaire '!D:D,B4)*2 | D4: =SUMIF('Questionnaire '!D:D,B4,'Questionnaire '!N:N) | E4: =D4/C4 | F4: =IF(E4<0.25,"Très peu développé",IF(E4<0.5,"Peu développé",IF(E4<0.75,"Développé","Très développé"))) | G4: =D4/D12
B5: Esprit critique | C5: =COUNTIF('Questionnaire '!D:D,B5)*2 | D5: =SUMIF('Questionnaire '!D:D,B5,'Questionnaire '!N:N) | E5: =D5/C5 | F5: =IF(E5<0.25,"Très peu développé",IF(E5<0.5,"Peu développé",IF(E5<0.75,"Développé","Très développé"))) | G5: =D5/D12
B6: Ethique | C6: =COUNTIF('Questionnaire '!D:D,B6)*2 | D6: =SUMIF('Questionnaire '!D:D,B6,'Questionnaire '!N:N) | E6: =D6/C6 | F6: =IF(E6<0.25,"Très peu développé",IF(E6<0.5,"Peu développé",IF(E6<0.75,"Développé","Très développé"))) | G6: =D6/D12
B7: Intelligence émotionnelle | C7: =COUNTIF('Questionnaire '!D:D,B7)*2 | D7: =SUMIF('Questionnaire '!D:D,B7,'Questionnaire '!N:N) | E7: =D7/C7 | F7: =IF(E7<0.25,"Très peu développé",IF(E7<0.5,"Peu développé",IF(E7<0.75,"Développé","Très développé"))) | G7: =D7/D12
B8: Intelligence sociale | C8: =COUNTIF('Questionnaire '!D:D,B8)*2 | D8: =SUMIF('Questionnaire '!D:D,B8,'Questionnaire '!N:N) | E8: =D8/C8 | F8: =IF(E8<0.25,"Très peu développé",IF(E8<0.5,"Peu développé",IF(E8<0.75,"Développé","Très développé"))) | G8: =D8/D12
B9: Management de projet | C9: =COUNTIF('Questionnaire '!D:D,B9)*2 | D9: =SUMIF('Questionnaire '!D:D,B9,'Questionnaire '!N:N) | E9: =D9/C9 | F9: =IF(E9<0.25,"Très peu développé",IF(E9<0.5,"Peu développé",IF(E9<0.75,"Développé","Très développé"))) | G9: =D9/D12
B10: Management et gestion d'équipe | C10: =COUNTIF('Questionnaire '!D:D,B10)*2 | D10: =SUMIF('Questionnaire '!D:D,B10,'Questionnaire '!N:N) | E10: =D10/C10 | F10: =IF(E10<0.25,"Très peu développé",IF(E10<0.5,"Peu développé",IF(E10<0.75,"Développé","Très développé"))) | G10: =D10/D12
B11: Organisation | C11: =COUNTIF('Questionnaire '!D:D,B11)*2 | D11: =SUMIF('Questionnaire '!D:D,B11,'Questionnaire '!N:N) | E11: =D11/C11 | F11: =IF(E11<0.25,"Très peu développé",IF(E11<0.5,"Peu développé",IF(E11<0.75,"Développé","Très développé"))) | G11: =D11/D12
B12: Totaux | C12: =SUM(C4:C11) | D12: =SUM(D4:D11) | G12: =SUM(G4:G11)
B20: MBTI
B21: Résultat MBTI | C21: Score max | D21: Score obtenu | E21: % de votes | F21: Lettre dominante
B22: E — Extraversion | C22: =COUNTIF('Questionnaire '!E$3:E$74,"*Energie*")*2 | D22: =SUMPRODUCT(('Questionnaire '!W$3:W$74="E")*('Questionnaire '!N$3:N$74)) | E22: =IFERROR(D22/C22,0) | F22: =IF(E22>=E23,"E","")
B23: I — Introversion | C23: =COUNTIF('Questionnaire '!E$3:E$74,"*Energie*")*2 | D23: =SUMPRODUCT(('Questionnaire '!W$3:W$74="I")*('Questionnaire '!N$3:N$74)) | E23: =IFERROR(D23/C23,0) | F23: =IF(E23>E22,"I","")
B24: N — Intuition | C24: =COUNTIF('Questionnaire '!E$3:E$74,"*perception*")*2 | D24: =SUMPRODUCT(('Questionnaire '!W$3:W$74="N")*('Questionnaire '!N$3:N$74)) | E24: =IFERROR(D24/C24,0) | F24: =IF(E24>=E25,"N","")
B25: S — Sensation | C25: =COUNTIF('Questionnaire '!E$3:E$74,"*perception*")*2 | D25: =SUMPRODUCT(('Questionnaire '!W$3:W$74="S")*('Questionnaire '!N$3:N$74)) | E25: =IFERROR(D25/C25,0) | F25: =IF(E25>E24,"S","")
B26: F — Sentiment | C26: =COUNTIF('Questionnaire '!E$3:E$74,"*sentiment*")*2 | D26: =SUMPRODUCT(('Questionnaire '!W$3:W$74="F")*('Questionnaire '!N$3:N$74)) | E26: =IFERROR(D26/C26,0) | F26: =IF(E26>=E27,"F","")
B27: T — Pensée | C27: =COUNTIF('Questionnaire '!E$3:E$74,"*sentiment*")*2 | D27: =SUMPRODUCT(('Questionnaire '!W$3:W$74="T")*('Questionnaire '!N$3:N$74)) | E27: =IFERROR(D27/C27,0) | F27: =IF(E27>E26,"T","")
B28: J — Organisation | C28: =COUNTIF('Questionnaire '!E$3:E$74,"*style de vie*")*2 | D28: =SUMPRODUCT(('Questionnaire '!W$3:W$74="J")*('Questionnaire '!N$3:N$74)) | E28: =IFERROR(D28/C28,0) | F28: =IF(E28>=E29,"J","")
B29: P — Perception | C29: =COUNTIF('Questionnaire '!E$3:E$74,"*style de vie*")*2 | D29: =SUMPRODUCT(('Questionnaire '!W$3:W$74="P")*('Questionnaire '!N$3:N$74)) | E29: =IFERROR(D29/C29,0) | F29: =IF(E29>E28,"P","")
B30: Type MBTI final | F30: =_xlfn.TEXTJOIN("",TRUE,F22:F29)

Sheet Synthése réponses questionnaire
A2: Prénom du sujet | B2: Nom du sujet | C2: Assertivité | D2: Communication à distance | E2: Communication écrite | F2: L’audace (ou le culot) | G2: L’enthousiasme et le dynamisme | H2: L’optimisme | I2: La clarté de communication | J2: La diplomatie | K2: La négociation | L2: La persuasion | M2: La posture ou la communication non verbale | N2: L'argumentation | O2: Prestance | P2: Prise de parole en public | Q2: Rhétorique ou storytelling | R2: Actualisation des connaissances | S2: L’acuité et le discernement | T2: L’humour | U2: L’ouverture d'esprit | V2: La créativité ou l'imagination | W2: La curiosité | X2: La pensée logique | Y2: La rigueur (travail) | Z2: Le sens artistique | AA2: L'innovation | AB2: Pensée critique | AC2: Penser "out of the box" | AD2: Résolution des problèmes | AE2: Savoir rechercher pour résoudre un problème | AF2: Fiabilité | AG2: L’honnêteté | AH2: L’intégrité | AI2: La conscience professionnelle | AJ2: La courtoisie, la cordialité, l’amabilité | AK2: La loyauté | AL2: La respectabilité, la dignité, l'honneur | AM2: Le sens des responsabilité | AN2: Le sens du sacrifice | AO2: L'éco-responsabilité | AP2: L'engagement | AQ2: Ponctualité | AR2: Respect des autres (doublon tolérance) | AS2: Acceptation des retours et critiques | AT2: Equanimité | AU2: Introspection | AV2: L’authenticité ou la sincérité. | AW2: L’empathie | AX2: L’humilité | AY2: La bienveillance | AZ2: La compassion | BA2: La confiance aux autres | BB2: La confiance en soi | BC2: La gestion du stress | BD2: La maitrise de soi | BE2: La reconnaissance ou considération | BF2: La résilience | BG2: La sensibilité | BH2: Aisance relationnelle | BI2: Altruisme | BJ2: Esprit d'équipe | BK2: Intelligence culturelle | BL2: L’interaction avec les autres | BM2: La coopération, la collaboration | BN2: La présence ou l'aura | BO2: La tolérance | BP2: Le networking | BQ2: Le partage d'idées | BR2: Sociabilité | BS2: L’Autonomie | BT2: La délégation de taches | BU2: La facilitation | BV2: La gestion des risques | BW2: La prise de décision | BX2: La supervision | BY2: La tolérance au changement | BZ2: L'agilité cognitive | CA2: Equité | CB2: Gérer et résoudre les conflits | CC2: Gérer les équipes à distances | CD2: Inclusivité | CE2: L’esprit d’initiative | CF2: La valorisation ou l'encouragement | CG2: Le charisme | CH2: Le coaching des autres | CI2: Leadership | CJ2: L’auto-formation | CK2: La concentration | CL2: La fixation d'objectifs | CM2: La gestion des ressources | CN2: La gestion du temps | CO2: La hiérarchisation et la priorisation | CP2: La patiente | CQ2: La persévérance | CR2: La planification | CS2: La ponctualité | CT2: La recherche d'efficacité | CU2: La visualisation | CV2: Le respect des délais
A3: Isoline | B3: VICHITH | C3: B | D3: B | E3: B | F3: A | G3: B | H3: D | I3: B | J3: B | K3: C | L3: A | M3: B | N3: A | O3: C | P3: C | Q3: D | R3: B | S3: B | T3: D | U3: D | V3: C | W3: B | X3: A | Y3: C | Z3: D | AA3: D | AB3: C | AC3: A | AD3: C | AE3: B | AF3: D | AG3: B | AH3: A | AI3: B | AJ3: B | AK3: A | AL3: A | AM3: D | AN3: B | AO3: C | AP3: A | AQ3: B | AR3: D | AS3: B | AT3: C | AU3: C | AV3: B | AW3: B | AX3: C | AY3: C | AZ3: D | BA3: C | BB3: A | BC3: C | BD3: D | BE3: C | BF3: A | BG3: C | BH3: A | BI3: B | BJ3: B | BK3: D | BL3: B | BM3: A | BN3: C | BO3: B | BP3: A | BQ3: C | BR3: B | BS3: B | BT3: A | BU3: A | BV3: C | BW3: B | BX3: C | BY3: A | BZ3: C | CA3: B | CB3: B | CC3: C | CD3: A | CE3: C | CF3: A | CG3: A | CH3: B | CI3: B | CJ3: D | CK3: A | CL3: C | CM3: B | CN3: B | CO3: D | CP3: A | CQ3: C | CR3: A | CS3: D | CT3: D | CU3: D | CV3: D
A4: Kaïs | B4: FOFANA

Sheet PUBLIPOSTAGE 
A2: Prénom du sujet | B2: Nom du sujet | C2: Communication | D2: Esprit critique | E2: Ethique | F2: Intelligence émotionnelle | G2: Intelligence sociale | H2: Management de projet | I2: Management et gestion d'équipe | J2: Organisation | K2: Assertivité | L2: Communication à distance | M2: Communication écrite | N2: L’audace (ou le culot) | O2: L’enthousiasme et le dynamisme | P2: L’optimisme | Q2: La clarté de communication | R2: La diplomatie | S2: La négociation | T2: La persuasion | U2: La posture ou la communication non verbale | V2: L'argumentation | W2: Prestance | X2: Prise de parole en public | Y2: Rhétorique ou storytelling | Z2: Actualisation des connaissances | AA2: L’acuité et le discernement | AB2: L’humour | AC2: L’ouverture d'esprit | AD2: La créativité ou l'imagination | AE2: La curiosité | AF2: La pensée logique | AG2: La rigueur (travail) | AH2: Le sens artistique | AI2: L'innovation | AJ2: Pensée critique | AK2: Penser "out of the box" | AL2: Résolution des problèmes | AM2: Savoir rechercher pour résoudre un problème | AN2: Fiabilité | AO2: L’honnêteté | AP2: L’intégrité | AQ2: La conscience professionnelle | AR2: La courtoisie, la cordialité, l’amabilité | AS2: La loyauté | AT2: La respectabilité, la dignité, l'honneur | AU2: Le sens des responsabilité | AV2: Le sens du sacrifice | AW2: L'éco-responsabilité | AX2: L'engagement | AY2: Ponctualité | AZ2: Respect des autres (doublon tolérance) | BA2: Acceptation des retours et critiques | BB2: Equanimité | BC2: Introspection | BD2: L’authenticité ou la sincérité. | BE2: L’empathie | BF2: L’humilité | BG2: La bienveillance | BH2: La compassion | BI2: La confiance aux autres | BJ2: La confiance en soi | BK2: La gestion du stress | BL2: La maitrise de soi | BM2: La reconnaissance ou considération | BN2: La résilience | BO2: La sensibilité | BP2: Aisance relationnelle | BQ2: Altruisme | BR2: Esprit d'équipe | BS2: Intelligence culturelle | BT2: L’interaction avec les autres | BU2: La coopération, la collaboration | BV2: La présence ou l'aura | BW2: La tolérance | BX2: Le networking | BY2: Le partage d'idées | BZ2: Sociabilité | CA2: L’Autonomie | CB2: La délégation de taches | CC2: La facilitation | CD2: La gestion des risques | CE2: La prise de décision | CF2: La supervision | CG2: La tolérance au changement | CH2: L'agilité cognitive | CI2: Equité | CJ2: Gérer et résoudre les conflits | CK2: Gérer les équipes à distances | CL2: Inclusivité | CM2: L’esprit d’initiative | CN2: La valorisation ou l'encouragement | CO2: Le charisme | CP2: Le coaching des autres | CQ2: Leadership | CR2: L’auto-formation | CS2: La concentration | CT2: La fixation d'objectifs | CU2: La gestion des ressources | CV2: La gestion du temps | CW2: La hiérarchisation et la priorisation | CX2: La patiente | CY2: La persévérance | CZ2: La planification | DA2: La ponctualité | DB2: La recherche d'efficacité | DC2: La visualisation | DD2: Le respect des délais | DE2: Assertivité | DF2: Communication à distance | DG2: Communication écrite | DH2: L’audace (ou le culot) | DI2: L’enthousiasme et le dynamisme | DJ2: L’optimisme | DK2: La clarté de communication | DL2: La diplomatie | DM2: La négociation | DN2: La persuasion | DO2: La posture ou la communication non verbale | DP2: L'argumentation | DQ2: Prestance | DR2: Prise de parole en public | DS2: Rhétorique ou storytelling | DT2: Actualisation des connaissances | DU2: L’acuité et le discernement | DV2: L’humour | DW2: L’ouverture d'esprit | DX2: La créativité ou l'imagination | DY2: La curiosité | DZ2: La pensée logique | EA2: La rigueur (travail) | EB2: Le sens artistique | EC2: L'innovation | ED2: Pensée critique | EE2: Penser "out of the box" | EF2: Résolution des problèmes | EG2: rechercher pour résoudre un problème | EH2: Fiabilité | EI2: L’honnêteté | EJ2: L’intégrité | EK2: La conscience professionnelle | EL2: La courtoisie | EM2: La loyauté | EN2: La respectabilité, l'honneur | EO2: Le sens des responsabilité | EP2: Le sens du sacrifice | EQ2: L'éco-responsabilité | ER2: L'engagement | ES2: Ponctualité | ET2: Respect des autres (doublon tolérance) | EU2: Acceptation des retours et critiques | EV2: Equanimité | EW2: Introspection | EX2: L’authenticité ou la sincérité. | EY2: L’empathie | EZ2: L’humilité | FA2: La bienveillance | FB2: La compassion | FC2: La confiance aux autres | FD2: La confiance en soi | FE2: La gestion du stress | FF2: La maitrise de soi | FG2: La reconnaissance ou considération | FH2: La résilience | FI2: La sensibilité | FJ2: Aisance relationnelle | FK2: Altruisme | FL2: Esprit d'équipe | FM2: Intelligence culturelle | FN2: L’interaction avec les autres | FO2: La coopération, la collaboration | FP2: La présence ou l'aura | FQ2: La tolérance | FR2: Le networking | FS2: Le partage d'idées | FT2: Sociabilité | FU2: L’Autonomie | FV2: La délégation de taches | FW2: La facilitation | FX2: La gestion des risques | FY2: La prise de décision | FZ2: La supervision | GA2: La tolérance au changement | GB2: L'agilité cognitive | GC2: Equité | GD2: Gérer et résoudre les conflits | GE2: Gérer les équipes à distances | GF2: Inclusivité | GG2: L’esprit d’initiative | GH2: La valorisation ou l'encouragement | GI2: Le charisme | GJ2: Le coaching des autres | GK2: Leadership | GL2: L’auto-formation | GM2: La concentration | GN2: La fixation d'objectifs | GO2: La gestion des ressources | GP2: La gestion du temps | GQ2: La hiérarchisation et la priorisation | GR2: La patiente | GS2: La persévérance | GT2: La planification | GU2: La ponctualité | GV2: La recherche d'efficacité | GW2: La visualisation | GX2: Le respect des délais
A3: Ligne | B3: Principal | C3: =_xlfn.XLOOKUP(C2,'Résultat test questionnaire'!$B:$B,'Résultat test questionnaire'!$F:$F) | D3: =_xlfn.XLOOKUP(D2,'Résultat test questionnaire'!$B:$B,'Résultat test questionnaire'!$F:$F) | E3: =_xlfn.XLOOKUP(E2,'Résultat test questionnaire'!$B:$B,'Résultat test questionnaire'!$F:$F) | F3: =_xlfn.XLOOKUP(F2,'Résultat test questionnaire'!$B:$B,'Résultat test questionnaire'!$F:$F) | G3: =_xlfn.XLOOKUP(G2,'Résultat test questionnaire'!$B:$B,'Résultat test questionnaire'!$F:$F) | H3: =_xlfn.XLOOKUP(H2,'Résultat test questionnaire'!$B:$B,'Résultat test questionnaire'!$F:$F) | I3: =_xlfn.XLOOKUP(I2,'Résultat test questionnaire'!$B:$B,'Résultat test questionnaire'!$F:$F) | J3: =_xlfn.XLOOKUP(J2,'Résultat test questionnaire'!$B:$B,'Résultat test questionnaire'!$F:$F) | K3: =_xlfn.XLOOKUP(K2,'Questionnaire '!$C:$C,'Questionnaire '!$M:$M) | L3: =_xlfn.XLOOKUP(L2,'Questionnaire '!$C:$C,'Questionnaire '!$M:$M) | M3: =_xlfn.XLOOKUP(M2,'Questionnaire '!$C:$C,'Questionnaire '!$M:$M) | N3: =_xlfn.XLOOKUP(N2,'Questionnaire '!$C:$C,'Questionnaire '!$M:$M) | O3: =_xlfn.XLOOKUP(O2,'Questionnaire '!$C:$C,'Questionnaire '!$M:$M) | P3: =_xlfn.XLOOKUP(P2,'Questionnaire '!$C:$C,'Questionnaire '!$M:$M) | Q3: =_xlfn.XLOOKUP(Q2,'Questionnaire '!$C:$C,'Questionnaire '!$M:$M) | R3: =_xlfn.XLOOKUP(R2,'Questionnaire '!$C:$C,'Questionnaire '!$M:$M) | ... DD3: =_xlfn.XLOOKUP(DD2,'Questionnaire '!$C:$C,'Questionnaire '!$M:$M) | DE3: =_xlfn.XLOOKUP('PUBLIPOSTAGE '!DE2,'Questionnaire '!$C:$C,'Questionnaire '!$P:$P) | DF3: =_xlfn.XLOOKUP('PUBLIPOSTAGE '!DF2,'Questionnaire '!$C:$C,'Questionnaire '!$P:$P) | DG3: =_xlfn.XLOOKUP('PUBLIPOSTAGE '!DG2,'Questionnaire '!$C:$C,'Questionnaire '!$P:$P) | DH3: =_xlfn.XLOOKUP('PUBLIPOSTAGE '!DH2,'Questionnaire '!$C:$C,'Questionnaire '!$P:$P) | DI3: =_xlfn.XLOOKUP('PUBLIPOSTAGE '!DI2,'Questionnaire '!$C:$C,'Questionnaire '!$P:$P) | DJ3: =_xlfn.XLOOKUP('PUBLIPOSTAGE '!DJ2,'Questionnaire '!$C:$C,'Questionnaire '!$P:$P) | DK3: =_xlfn.XLOOKUP('PUBLIPOSTAGE '!DK2,'Questionnaire '!$C:$C,'Questionnaire '!$P:$P) | DL3: =_xlfn.XLOOKUP('PUBLIPOSTAGE '!DL2,'Questionnaire '!$C:$C,'Questionnaire '!$P:$P) | ... EF3: =_xlfn.XLOOKUP('PUBLIPOSTAGE '!EF2,'Questionnaire '!$C:$C,'Questionnaire '!$P:$P) | EG3: ='Questionnaire '!P20 | EH3: =_xlfn.XLOOKUP('PUBLIPOSTAGE '!EH2,'Questionnaire '!$C:$C,'Questionnaire '!$P:$P) | EI3: =_xlfn.XLOOKUP('PUBLIPOSTAGE '!EI2,'Questionnaire '!$C:$C,'Questionnaire '!$P:$P) | EJ3: =_xlfn.XLOOKUP('PUBLIPOSTAGE '!EJ2,'Questionnaire '!$C:$C,'Questionnaire '!$P:$P) | EK3: =_xlfn.XLOOKUP('PUBLIPOSTAGE '!EK2,'Questionnaire '!$C:$C,'Questionnaire '!$P:$P) | EL3: ='Questionnaire '!#REF! | EM3: =_xlfn.XLOOKUP('PUBLIPOSTAGE '!EM2,'Questionnaire '!$C:$C,'Questionnaire '!$P:$P) | EN3: ='Questionnaire '!P24 | EO3: =_xlfn.XLOOKUP('PUBLIPOSTAGE '!EO2,'Questionnaire '!$C:$C,'Questionnaire '!$P:$P) | EP3: =_xlfn.XLOOKUP('PUBLIPOSTAGE '!EP2,'Questionnaire '!$C:$C,'Questionnaire '!$P:$P) | EQ3: =_xlfn.XLOOKUP('PUBLIPOSTAGE '!EQ2,'Questionnaire '!$C:$C,'Questionnaire '!$P:$P) | ER3: =_xlfn.XLOOKUP('PUBLIPOSTAGE '!ER2,'Questionnaire '!$C:$C,'Questionnaire '!$P:$P) | ES3: =_xlfn.XLOOKUP('PUBLIPOSTAGE '!ES2,'Questionnaire '!$C:$C,'Questionnaire '!$P:$P) | ET3: =_xlfn.XLOOKUP('PUBLIPOSTAGE '!ET2,'Questionnaire '!$C:$C,'Questionnaire '!$P:$P) | EU3: =_xlfn.XLOOKUP('PUBLIPOSTAGE '!EU2,'Questionnaire '!$C:$C,'Questionnaire '!$P:$P) | EV3: =_xlfn.XLOOKUP('PUBLIPOSTAGE '!EV2,'Questionnaire '!$C:$C,'Questionnaire '!$P:$P) | ... GX3: =_xlfn.XLOOKUP('PUBLIPOSTAGE '!GX2,'Questionnaire '!$C:$C,'Questionnaire '!$P:$P)
A4: Betty | B4: MATOKO | C4: Développé | D4: Développé | E4: Développé | F4: très développé | G4: très développé | H4: Développé | I4: très développé | J4: très développé | K4: #N/A | L4: #N/A | M4: Vous êtes particulièrement doué à l'écrit. | N4: Vous êtes quelqu'un de timide et réservé. | O4: Vous êtes quelqu'un d'enthousiaste et de dynamique. | P4: #N/A | Q4: Vous êtes clair quand vous vous exprimez à l'orale, ceux qui vous écoutent comprennent facilement vos propos. | R4: Vous êtes extrêmement diplomate dans vos propos, vous cherchez toujours les termes et tournures de phrases les moins choquantes. | S4: Vous préférez éviter les phases de négociations corsées, quitte à perdre des opportunités. | T4: #N/A | U4: Vous êtes quelqu'un de calme et réservé dans vos mouvements. | V4: #N/A | W4: #N/A | X4: Vous avez aussi tendance à éviter les prises de paroles en public. Ce n'est pas votre truc. | Y4: Vous savez raconter les histoires et les anecdotes. En général, les gens vous écoutent attentivement. | Z4: Vous n'êtes pas du type à systématiquement actualiser vos connaissances lorsque vous parlez d'un sujet. Vous préférez utiliser votre expérience et vos souvenirs. | AA4: Vous avez une faculté de discernement élevé. | AB4: Vous avez très peu d'humour quand vous vous retrouvez dans une situation qui demande de l'observation et de la concentration ! | AC4: Vous pouvez vous montrer ouvert d'esprit même quand une personne n'est pas d'accord avec vous sur certains sujets. | AD4: Vous êtes quelqu'un de créatif. | AE4: Vous n'êtes pas quelqu'un de curieux. En général, vous préférez que l'information vienne à vous. | AF4: #N/A | AG4: #N/A | AH4: #N/A | AI4: #N/A | AJ4: Vous êtes attentifs aux détails et aimez suggérer des améliorations à ce que vous observez. | AK4: #N/A | AL4: Lorsque vous rencontrez un problème, vous avez tendance à vous baser essentiellement sur votre intuition et vos aptitudes. Ce qui peut vous empêcher d'en identifier la source véritable. | AM4: Face à une complexité, vous préférez vous renseigner sur la source du problème pour pouvoir les résoudre. | AN4: #N/A | AO4: #N/A | AP4: En général, vous préférez perdre dans l'honneur que gagner dans le déshonneur. | AQ4: Vous avez une conscience professionnelle accrue. | AR4: #N/A | AS4: Vous êtes quelqu’un de loyal. | AT4: Pour vous, demander de l’aide ou utiliser des astuces pour réussir n’est pas un signe de faiblesse. Cela ne diminue en rien la valeur de vos succès. | AU4: Vous avez le sens des responsabilités et souhaitez souvent assumer vos erreurs. | AV4: Vous pensez plus aux autres qu'à vous-même quand vous avez le choix. | AW4: Vous n'êtes pas spécialement écoresponsable. | AX4: Vous êtes capable de vous engager même si cela peut vous nuire. | AY4: #N/A | AZ4: Vous pouvez souvent faire preuve d'intolérance quant aux avis des autres. | BA4: Les critiques vous irritent, mais vous préférez les écouter que de perdre un moyen de vous améliorer. | BB4: #N/A | BC4: Vous arrivez à comprendre vos émotions et à les expliquer, mais pas facilement. | BD4: #N/A | BE4: Vous êtes quelqu'un d'empathique. Vous arrivez à vous mettre à la place des autres. | BF4: #N/A | BG4: Vous avez tendance à vous soucier plus de votre bien-être qu'a celui des autres. | BH4: #N/A | BI4: #N/A | BJ4: Vous manquez parfois de confiance en vos capacités. | BK4: Vous savez gérer vos émotions dans une situation stressantes. | BL4: Vous n’êtes pas du genre à perdre vos moyens facilement quand une personne tente de vous rabaisser. | BM4: Vous avez de la considération pour les autres. Vous aimez les encourager dans les moments difficiles. | BN4: #N/A | BO4: Vous êtes quelqu'un de sensible et on peut vous émouvoir facilement. | BP4: Vous aimez rester dans votre coin, surtout dans une salle remplie de monde. | BQ4: Il faut vraiment que vous appréciiez quelqu'un pour que vous puissiez partager vos avantages avec lui. | BR4: Vous aimez le travail en équipe tant que vous avez des affinité avec vos collaborateurs. | BS4: Vous avez un attrait pour la découverte d'autres cultures et d'autres langues. | BT4: Vous aimez parler et discuter avec les autres. | BU4: Vous avez une facilité à coopérer avec les gens. Mais il faut quand même un minimum de cordialité entre vous. | BV4: #N/A | BW4: Vous êtes tolérant envers les avis des autres. Même quand les avis négatifs peuvent vous concerner. | BX4: Vous prenez du plaisir à créer une communauté ou un réseau autour de vous. Vous êtes du genre à vous faire des amis rapidement. | BY4: #N/A | BZ4: Vous n'aimez pas les moments de silence et de gène. Votre sociabilité vous incite à lancer les conversations. | CA4: Vous pouvez parfois manquer d'autonomie dans ce que vous entreprenez. | CB4: Vous aimez déléguer une partie de votre travail, car cela vous permet de vous concentrer sur ce que vous considérez comme important. | CC4: Vous aimez faciliter le travail des autres lorsque vous travaillez en groupe. | CD4: Vous n'êtes pas du genre à vouloir prévoir les évènements nuisibles. Vous préférez réagir aux conséquences que les prévenir. | CE4: Vous avez du mal à prendre des décisions qui peuvent entraîner des conséquences graves sur les autres. | CF4: Lorsque vous travaillez en groupe, vous aimez contrôler régulièrement l'avancée des travaux. vous avez un attrait pour la supervision. | CG4: Vous êtes plutôt quelqu'un de flexible, vous essayer de vous adapter aux changements. | CH4: Vous n'êtes pas perturbé par l'apparition d'évènements imprévus. | CI4: Vous cherchez à être équitable dans vos choix et décisions. Surtout quand cela peut impacter la vie des gens. | CJ4: Vous aimez résoudre les conflits entre les gens. Surtout ceux qui sont liés aux personnes de votre entourage proche. | CK4: Vous n'avez pas de difficulté à vouloir maintenir un travail de groupe efficace en travaillant à distance. | CL4: Vous n'aimez pas l'exclusion. Vous avez tendance à inclure les gens dans votre groupe si vous les sentez seuls ou isolés. | CM4: Vous avez un esprit d'initiative développé, et êtes courageux dans ce que vous entreprenez. | CN4: Vous valorisez facilement le travail ou les réussites des personnes de votre entourage. | CO4: Vous avez du charisme, mais vous pouvez encore le développer. | CP4: Vous aimez aider les autres à s’élever et se parfaire. Vous prodiguez souvent des conseils. | CQ4: Vous aimez prendre le lead quand un projet doit se mettre en place. Vous aimez montrer la voie à suivre. | CR4: Vous avez peu de difficulté à vous autoformer quand cela vous semble nécessaire. | CS4: Si vous trouvez une tâche ou une activité ennuyeuse, vous aurez énormément de mal à vous concentrer dessus, peu importe son importance. | CT4: Vous n'aimez pas vous fixer des objectifs qui vous semblent disproportionnés par rapport à vos capacités. Vous êtes réaliste. | CU4: Dans un projet de groupe, votre attention se porte plus sur les relations entre les membres que sur les outils nécessaires à sa réalisation. | CV4: Vous aimez gérer votre temps correctement et prendre de l'avance sur les activités. | CW4: Vous préférez prioriser les choses en fonction de ce qui est nécessaire de faire plutôt qu'en fonction de ce que vous préférez faire. | CX4: #N/A | CY4: #N/A | CZ4: Vous aimez planifier les choses. Vous n'aimez pas être débordé ou perturbé par un manque de prévision. | DA4: #N/A | DB4: Vous êtes souvent à la recherche de l'efficacité. Vous n'aimez pas les choses qui prennent trop de temps. | DC4: Vous êtes du type à facilement vous projeter mentalement dans une situation. Vous avez de l'imagination. | DD4: En général, vous faites tout pour respecter les délais et horaires fixés. | DE4: #N/A | DF4: #N/A | DH4: Oui. | DJ4: #N/A | DM4: Oui. | DN4: #N/A | DO4: Oui. | DP4: #N/A | DQ4: #N/A | DR4: Oui. | DT4: Oui. | DV4: Oui. | DY4: Oui. | DZ4: #N/A | EA4: #N/A | EB4: #N/A | EC4: #N/A | EE4: #N/A | EF4: Oui. | EH4: #N/A | EI4: #N/A | EL4: #REF! | EN4: Oui. | EQ4: Oui. | ES4: #N/A | ET4: Oui. | EV4: #N/A | EX4: #N/A | EZ4: #N/A | FA4: Oui. | FB4: #N/A | FC4: #N/A | FD4: Oui. | FH4: #N/A | FJ4: Oui. | FK4: Oui. | FP4: #N/A | FS4: #N/A | FU4: Oui. | FX4: Oui. | FY4: Oui. | GM4: Oui. | GO4: Oui. | GR4: #N/A | GS4: #N/A | GU4: #N/A
A5: Kaïs | B5: FOFANA | C5: Peu développé | D5: Peu développé | E5: Développé | F5: Peu développé | G5: très développé | H5: très développé | I5: Développé | J5: Développé | K5: #N/A | L5: #N/A | M5: Vous savez aussi vous exprimer à l'écrit. En général, les gens comprennent facilement vos propos quand ils vous lisent. | N5: Vous avez de l'audace et êtes relativement spontané. | O5: Vous aimez motiver les autres à s'amuser. | P5: #N/A | Q5: Vous avez du mal à vous exprimer correctement. | R5: Vous êtes extrêmement diplomate dans vos propos, vous cherchez toujours les termes et tournures de phrases les moins choquantes. | S5: Vous considérez les phases de négociation comme des échanges agressifs et inutiles. | T5: #N/A | U5: Vous êtes quelqu'un de calme et réservé dans vos mouvements. | V5: #N/A | W5: #N/A | X5: Vous avez aussi tendance à éviter les prises de paroles en public. Ce n'est pas votre truc. | Y5: Vous avez de vraies difficultés à structurer vos pensées et votre discours lorsque vous évoquez un évènement ou des anecdotes. | Z5: Vous n'êtes pas du type à systématiquement actualiser vos connaissances lorsque vous parlez d'un sujet. Vous préférez utiliser votre expérience et vos souvenirs. | AA5: Vous avez une faculté de discernement élevé. | AB5: Vous avez aussi beaucoup d'humour. Vous riez parfois quand personne ne le fait, car vous êtes attentifs aux effets comiques. | AC5: Vous pouvez vous montrer ouvert d'esprit même quand une personne n'est pas d'accord avec vous sur un sujet qui vous concerne. | AD5: Vous pouvez souvent manquer d’imagination ou de créativité. | AE5: Vous n'êtes pas quelqu'un de curieux. En général, vous préférez que l'information vienne à vous. | AF5: #N/A | AG5: #N/A | AH5: #N/A | AI5: #N/A | AJ5: Vous préférez vous servir de votre intuition plutôt que de vos sens afin d'émettre un jugement. | AK5: #N/A | AL5: Lorsque vous rencontrez un problème, vous avez tendance à vous baser essentiellement sur votre intuition et vos aptitudes. Ce qui peut vous empêcher d'en identifier la source véritable. | AM5: Face à une complexité, vous préférez vous renseigner sur la source du problème pour pouvoir les résoudre. | AN5: #N/A | AO5: #N/A | AP5: En général, vous préférez perdre dans l'honneur que gagner dans le déshonneur. | AQ5: Vous avez une conscience professionnelle accrue. | AR5: #N/A | AS5: Vous trouvez idiot de se mettre en danger pour les autres, et détester quand leur faiblesse à un impact sur vous. | AT5: Vous êtes quelqu'un de digne. Vous n'aimez pas avoir la sensation d'avoir été aidé pour réussir. | AU5: Vous avez le sens des responsabilités et souhaitez souvent assumer vos erreurs. | AV5: Vous avez aussi le sens du sacrifice. | AW5: Vous n'êtes pas spécialement écoresponsable. | AX5: Vous êtes capable de vous engager même si cela peut vous nuire. | AY5: #N/A | AZ5: Vous pouvez souvent faire preuve d'intolérance quant aux avis des autres. | BA5: Les critiques vous irritent, mais vous préférez les écouter que de perdre un moyen de vous améliorer. | BB5: #N/A | BC5: Vous avez des difficultés à expliquer qui vous êtes vraiment. Comme si vous ne vous connaissez pas réellement. | BD5: #N/A | BE5: Vous manquez souvent d'empathie dans les situations ou cette faculté est de rigueur. | BF5: #N/A | BG5: Vous avez tendance à vous soucier plus de votre bien-être qu'a celui des autres. | BH5: #N/A | BI5: #N/A | BJ5: Vous manquez parfois de confiance en vos capacités. | BK5: Vous savez gérer vos émotions dans une situation stressantes. | BL5: Vous avez du mal à vous maîtriser quand vous vous sentez insulté ou rabaissé. | BM5: Vous avez de la considération pour les autres. Vous aimez les encourager dans les moments difficiles. | BN5: #N/A | BO5: Vous êtes quelqu'un de sensible et on peut vous émouvoir facilement. | BP5: Vous avez un aisance relationnel développée. Vous aimez découvrir les autres. | BQ5: Vous n'êtes pas du genre à partager vos avantages sans contrepartie. | BR5: Vous aimez le travail en équipe. | BS5: Vous avez un attrait pour la découverte d'autres cultures et d'autres langues. | BT5: Vous aimez parler et discuter avec les autres. | BU5: Vous avez une facilité à coopérer avec les gens. Mais il faut quand même un minimum de cordialité entre vous. | BV5: #N/A | BW5: Il vous arrive d’être peu tolérant et ouvert d’esprit quand quelqu’un à un avis contraire au vôtre. | BX5: Vous prenez du plaisir à créer une communauté ou un réseau autour de vous. Vous êtes du genre à vous faire des amis rapidement. | BY5: #N/A | BZ5: Vous êtes extrèmement sociable. | CA5: Vous pouvez parfois manquer d'autonomie dans ce que vous entreprenez. | CB5: Vous n'avez pas de difficulté déléguer une partie de votre travail aux autres. | CC5: Vous aimez faciliter le travail des autres lorsque vous travaillez en groupe. | CD5: Vous préférez prévoir les évènements néfastes d’un projet avant de le commencer, par peur de ne pas le mener à bien. | CE5: Vous avez du mal à prendre certaines décisions importantes, seul. Surtout quand elles vous touchent émotionnellement. | CF5: Vous aimez superviser et surveiller les activités ou les tâches qui doivent être réalisées. | CG5: Vous êtes plutôt quelqu'un de flexible, vous essayer de vous adapter aux changements. | CH5: Vous n'êtes pas perturbé par l'apparition d'évènements imprévus. | CI5: Vous recherchez plus l'égalité de traitement à l'équité de traitement. Vous aimez que tout le monde soit traité de la même façon, peu importe leur condition. | CJ5: Vous aimez résoudre les conflits entre les gens. Surtout ceux qui sont liés aux personnes de votre entourage proche. | CK5: Vous n'êtes pas un spécialiste de la coordination du travail à distance, vous préférez gérer les choses en présentiel. | CL5: Vous n'aimez pas l'exclusion. Vous avez tendance à inclure les gens dans votre groupe si vous les sentez seuls ou isolés. | CM5: Vous avez un esprit d'initiative développé. | CN5: Vous valorisez facilement le travail ou les réussites des personnes de votre entourage. | CO5: Vous devez probablement manquer de charisme. | CP5: Vous aimez aider les autres à s’élever et se parfaire. Vous prodiguez souvent des conseils. | CQ5: Vous n'aimez pas prendre le lead même quand vous le pouvez. Vous préférez laisser ça aux autres. | CR5: Vous n'aimez pas vous autoformer. Vous préférez avoir l'aide d'un mentor ou d'un professeur quand le besoin s'en ressent. | CS5: Si une tâche ou une activité ne vous intéresse pas, il vous est difficile de rester longtemps concentré dessus. | CT5: Vous n'aimez pas vous fixer des objectifs qui vous semblent disproportionnés par rapport à vos capacités. Vous êtes réaliste. | CU5: Dans un projet de groupe, vous vous focalisez plus sur les outils nécessaires sa réalisation qu'aux relations entre les membres. | CV5: Vous avez du mal à gérer votre temps correctement, lorsque vous entreprenez quelque chose. | CW5: Vous préférez prioriser les choses en fonction de ce que vous préférez faire, parfois au détriment de ce qui est urgent et important. | CX5: #N/A | CY5: #N/A | CZ5: Vous aimez planifier les choses. Vous n'aimez pas être débordé ou perturbé par un manque de prévision. | DA5: #N/A | DB5: Vous êtes souvent à la recherche de l'efficacité. Vous n'aimez pas les choses qui prennent trop de temps. | DC5: Vous êtes du type à facilement vous projeter mentalement dans une situation. Vous avez de l'imagination. | DD5: En général, vous faites tout pour respecter les délais et horaires fixés. | DE5: #N/A | DF5: #N/A | DJ5: #N/A | DK5: Oui. | DM5: Oui. | DN5: #N/A | DO5: Oui. | DP5: #N/A | DQ5: #N/A | DR5: Oui. | DS5: Oui. | DT5: Oui. | DX5: Oui. | DY5: Oui. | DZ5: #N/A | EA5: #N/A | EB5: #N/A | EC5: #N/A | ED5: Oui. | EE5: #N/A | EF5: Oui. | EH5: #N/A | EI5: #N/A | EL5: #REF! | EM5: Oui. | EQ5: Oui. | ES5: #N/A | ET5: Oui. | EV5: #N/A | EW5: Oui. | EX5: #N/A | EY5: Oui. | EZ5: #N/A | FA5: Oui. | FB5: #N/A | FC5: #N/A | FD5: Oui. | FF5: Oui. | FH5: #N/A | FK5: Oui. | FP5: #N/A | FQ5: Oui. | FS5: #N/A | FU5: Oui. | FY5: Oui. | GC5: Oui. | GE5: Oui. | GI5: Oui. | GK5: Oui. | GL5: Oui. | GM5: Oui. | GP5: Oui. | GQ5: Oui. | GR5: #N/A | GS5: #N/A | GU5: #N/A
A6: Frédéric | B6: DAYAS | C6: Développé | D6: très développé | E6: très développé | F6: très développé | G6: très développé | H6: Développé | I6: Développé | J6: très développé | K6: #N/A | L6: #N/A | M6: Vous faites beaucoup de faute de français à l'écrit. | N6: Cependant vous avez peu d'audace ou de culot quand il s'agit de s'adresser aux personnes qui vous semblent impressionnantes. | O6: Vous êtes quelqu'un d'enthousiaste et de dynamique. | P6: #N/A | Q6: Vous êtes clair quand vous vous exprimez à l'orale, ceux qui vous écoutent comprennent facilement vos propos. | R6: Vous aimez relater les faits de façon claire et précise, vous n'aimez pas les discours fallacieux. | S6: Vous préférez éviter les phases de négociations corsées, quitte à perdre des opportunités. | T6: #N/A | U6: Lorsque vous parlez, vous avez une attitude corporelle théâtrale. Vous bougez énormément. | V6: #N/A | W6: #N/A | X6: Vous n'avez aucun problème à vous exprimer devant une foule. Vous n'êtes pas timide. | Y6: Vous savez raconter les histoires et les anecdotes. En général, les gens vous écoutent attentivement. | Z6: Vous n'êtes pas du type à systématiquement actualiser vos connaissances lorsque vous parlez d'un sujet. Vous préférez utiliser votre expérience et vos souvenirs. | AA6: Vous avez une faculté de discernement élevé. | AB6: Vous avez très peu d'humour quand vous vous retrouvez dans une situation qui demande de l'observation et de la concentration ! | AC6: Vous pouvez vous montrer ouvert d'esprit même quand une personne n'est pas d'accord avec vous sur certains sujets. | AD6: Vous êtes quelqu'un de créatif. Vous avez beaucoup d'imagination. | AE6: Vous êtes aussi quelqu'un de curieux, et vous aimez aller à la recherche de l'information quand un sujet vous plaît. | AF6: #N/A | AG6: #N/A | AH6: #N/A | AI6: #N/A | AJ6: Vous utilisez plus vos sens que votre intuition pour juger et prendre des décisions. Vous aimez les éléments tangibles aux théories. Vous êtes observateur. | AK6: #N/A | AL6: Afin de résoudre un problème, vous préférez vous renseigner sur le sujet dans le but d'avoir tous les paramètres nécessaires à sa résolution. | AM6: Face à une complexité, vous préférez vous renseigner sur la source du problème pour pouvoir les résoudre. | AN6: #N/A | AO6: #N/A | AP6: Dans les situations qui peuvent vous avantager, vous pouvez transgresser certaines règles seulement si vous êtes sûr de ne jamais vous faire prendre. | AQ6: Vous avez une conscience professionnelle accrue. | AR6: #N/A | AS6: Vous êtes quelqu’un de loyal. | AT6: Vous êtes quelqu'un de digne. Vous n'aimez pas avoir la sensation d'avoir été aidé pour réussir. | AU6: Vous avez le sens des responsabilités et souhaitez souvent assumer vos erreurs. | AV6: Vous pensez plus aux autres qu'à vous-même quand vous avez le choix. | AW6: Vous avez un attrait pour la protection de l'environnement. | AX6: Vous ne pouvez pas vous engager si vous ressentez que cela peut vous nuire. | AY6: #N/A | AZ6: Vous êtes tolérant envers les autres et considérer leur avis même s'ils sont à l'opposé de vos croyances.. | BA6: Les critiques vous irritent, mais vous préférez les écouter que de perdre un moyen de vous améliorer. | BB6: #N/A | BC6: Vous arrivez à comprendre vos émotions et à les expliquer, mais pas facilement. | BD6: #N/A | BE6: Vous êtes quelqu'un d'empathique. Vous arrivez à vous mettre à la place des autres. | BF6: #N/A | BG6: Vous êtes bienveillant avec les personnes que vous appréciez. | BH6: #N/A | BI6: #N/A | BJ6: En général, vous avez confiance en vos capacités. Vous êtes courageux dans ce que vous entreprenez | BK6: Vous savez gérer vos émotions dans une situation stressantes. | BL6: Vous avez du mal à vous maîtriser quand vous vous sentez insulté ou rabaissé. | BM6: Vous avez de la considération pour les autres. Vous aimez les encourager dans les moments difficiles. | BN6: #N/A | BO6: Vous pouvez parfois manquer de sensibilité sur des sujets que d'autres trouveraient émouvant. | BP6: Vous avez un aisance relationnel développée. | BQ6: Vous n'êtes pas du genre à être généreux avec les gens sans un minimum d'affinités. | BR6: Vous aimez le travail en équipe. | BS6: Vous avez un attrait pour la découverte d'autres cultures et d'autres langues. | BT6: Vous aimez parler et discuter avec les autres. | BU6: Vous avez une facilité à coopérer avec les gens. Mais il faut quand même un minimum de cordialité entre vous. | BV6: #N/A | BW6: Il vous arrive d’être peu tolérant et ouvert d’esprit quand quelqu’un à un avis contraire au vôtre. | BX6: Vous préférez avoir un petit groupe d'amis plutôt qu’une multitude de connaissances. Ce qui peut vous empêcher d’avoir un réseau de connaissances large. | BY6: #N/A | BZ6: Vous n'aimez pas les moments de silence et de gène. Votre sociabilité vous incite à lancer les conversations. | CA6: Vous pouvez parfois manquer d'autonomie dans ce que vous entreprenez. | CB6: Vous aimez déléguer une partie de votre travail, car cela vous permet de vous concentrer sur ce que vous considérez comme important. | CC6: Vous aimez faciliter le travail des autres lorsque vous travaillez en groupe. | CD6: Vous préférez prévoir les évènements néfastes d’un projet avant de le commencer, par peur de ne pas le mener à bien. | CE6: Vous n'avez aucun mal prendre des décisions seul, même quand elles peuvent être dificilles et avoir de lourdes conséquences sur les autres. | CF6: Vous aimez superviser et surveiller les activités ou les tâches qui doivent être réalisées. | CG6: Vous pouvez parfois être intransigeant quant au changement de dernières minutes, à la modification de règles ou de processus. | CH6: Vous détestez être pris de court. Vous avez d'ailleurs du mal à gérer émotionnellement avec les évènements imprévus. | CI6: Vous cherchez à être équitable dans vos choix et décisions. Surtout quand cela peut impacter la vie des gens. | CJ6: Vous n'aimez pas intervenir et gérer les conflits entre les gens. Vous trouvez cet exercice fatigant ou risqué. | CK6: Vous n'avez pas de difficulté à vouloir maintenir un travail de groupe efficace en travaillant à distance. | CL6: Vous n'êtes pas du genre à vouloir inclure des gens dans votre groupe si vous estimez qu'ils ne vous apporteront rien. | CM6: Vous avez un esprit d'initiative développé. | CN6: Vous valorisez facilement le travail ou les réussites des personnes de votre entourage. | CO6: Vous avez du charisme, mais vous pouvez encore le développer. | CP6: Vous aimez aider les autres à s’élever et se parfaire. Vous prodiguez souvent des conseils. | CQ6: Vous n'aimez pas prendre le lead même quand vous le pouvez. Vous préférez laisser ça aux autres. | CR6: Vous n'aimez pas vous autoformer. Vous préférez avoir l'aide d'un mentor ou d'un professeur quand le besoin s'en ressent. | CS6: Vous n’avez pas besoin d’apprécier une tâche ou une activité, afin de vous concentrer pleinement dessus. | CT6: Vous n'aimez pas vous fixer des objectifs qui vous semblent disproportionnés par rapport à vos capacités. Vous êtes réaliste. | CU6: Dans un projet de groupe, vous vous focalisez plus sur les outils nécessaires sa réalisation qu'aux relations entre les membres. | CV6: Vous aimez gérer votre temps correctement et prendre de l'avance sur les activités. | CW6: Vous préférez prioriser les choses en fonction de ce qui est nécessaire de faire plutôt qu'en fonction de ce que vous préférez faire. | CX6: #N/A | CY6: #N/A | CZ6: Vous n'aimez pas planifier les choses et vous avez parfois du mal à le faire. | DA6: #N/A | DB6: Vous êtes souvent à la recherche de l'efficacité. Vous n'aimez pas les choses qui prennent trop de temps. | DC6: En général, vous avez du mal à vous projeter mentalement dans une situation future. | DD6: En général, vous faites tout pour respecter les délais et horaires fixés. | DE6: #N/A | DF6: #N/A | DG6: Oui. | DH6: Oui. | DJ6: #N/A | DL6: Oui. | DM6: Oui. | DN6: #N/A | DP6: #N/A | DQ6: #N/A | DT6: Oui. | DV6: Oui. | DZ6: #N/A | EA6: #N/A | EB6: #N/A | EC6: #N/A | EE6: #N/A | EH6: #N/A | EI6: #N/A | EJ6: Oui. | EL6: #REF! | ER6: Oui. | ES6: #N/A | EV6: #N/A | EX6: #N/A | EZ6: #N/A | FB6: #N/A | FC6: #N/A | FF6: Oui. | FH6: #N/A | FI6: Oui. | FP6: #N/A | FQ6: Oui. | FR6: Oui. | FS6: #N/A | FU6: Oui. | GA6: Oui. | GB6: Oui. | GD6: Oui. | GF6: Oui. | GK6: Oui. | GL6: Oui. | GR6: #N/A | GS6: #N/A | GT6: Oui. | GU6: #N/A

Sheet mode de lecture soft skills
C3: Développé | E3: Métier | F3: Peu développé | H3: Métier
B4: Catégories | C4: Forces | D4: Faiblesses : | F4: Forces | G4: Faiblesses
B5: Esprit critique | C5: Votre esprit essaye de réagir avec logique et pragmatisme, ce qui peut vous permettre de prendre des décisions logiques et rationnelles. vous avez une capacité de discernement et d'analyse développée. Vous savez vous poser les bonnes question et prendre des décisions les plus adaptées. ce qui peut vous permettre d'identifier la source de problème complexes. Vous avez aussi un certain sens de l'observation ce qui peut parfois s'apparenter au sens esthétique ou artistique. vous aimer donner des conseils afin d'améliorer les choses. vous avez un esprit créatif qui recherche souvent l'amélioration et la nouvauté. vous êtes aussi quelqu'un de curieux car vous aimez connaitre les choses pour pouvoir mieux les comprendre. vous avez aussi la faculter de préparer des argumentaire précis et convaincant basé sur un raisonement logique et des preuves. vous avez aussi une capacité et un besoin de résoudre les problème complexe, l'inverse serait un gène mental pour vous. votre capacité à juger les choses est surtout basé sur les éléments tangibles à votre disposition. | D5: vous pouvoir avoir tendance à tous remettre en questions tout ce que vous voyez et entendez. De plus cela peut vous rendre indécis, a un point ou vous pouvez hésiter à prendre la moindre décisions par peur de ne pas prendre la meilleur. votre franchise est parfois mal apprécié par des personnes ayant besoin d'encouragement, ou sensible aux critiques, notamment les personnes proches. votre sens du discernement peut ne pas fonctionner dans le cadre de la lecture des émotions des autres, car elle sont rarement tangibles.Vous pouvez aussi ne jamais être satisfait, ce qui peut vous empêcher d'avancer rapidement sur ce que vous entreprenez. vous pouvez aussi avoir tendance à sur argumenter la il faudrait juste se taire. le silence est d'or est un dicton que vous avez parfois mal à suivre. ceux qui ont un esprit critique développé peuvent aussi avoir du mal à recevoir des critiques, si leur intélligence émotionnelle n'est pas développée. | E5: Avocats, actuaires,analystes commercial,analyste financier, analystes des risques, ingénieur prévisionnistes, économistes, expert comptable, contrôleur de gestion, documentalistes Médecins, Ingénieurs, veille stratégique, journalistes, détective, scientifiques, désinateur ou designer, web designer, esthétique, mode, métier artistique, dessinateur critique littéraire ou cinématographiques. Consultant d'entreprise, juges des affaires familliales, juges des enfants, inspecteurs, policie des polices, | F5: Vous avez un vue d'ensemble et ne vous arrêtez pas forcément aux détails qui pourrait vous ralentir votre compréhension des choses, ou l'avancement de vos projets. Vous pensez simplement et avancer rapidement la ou d'autres bloqueraient sur des détails parfois inutiles. vous ne passer pas votre temps a vouloir changer les choses, vous préferer profiter du moment présent. vous pouvez être terre à terre, et plutot simple dans vos choix de vie. vous êtes dans l'éfficacité et l'impulsion. vous avez un certains sens de la hierarchie, vous respecter facilement les ordres ce qui faite de vous un très bon soutient. | G5: Vous ne remetez pas beaucoup de choses en questions et croyez parfois trop rapidement ce qu'on vous dit ou ce que vous lisez. vous pouvez donc avoir tendance à suivre le courant au lieu de créer et suivre vos propres idées ou les imposer. vous êtes sensible aux théories qui peuvent paraître vrai mais qui n'on pas été prouvés, ce qui peut parfois vous empêcher de penser simplement quand la réponse est juste devant vous. Vos travaux et analyses peuvent parfois manquer de profondeur, ce qui peut vous induire en erreur ou surtout diminuer la qualité de vos travaux. parfois, il peut vous arriver d'oublier un détail qui pourraient remettre en question tous vos travaux ou projet. vous n'êtes pas trop curieux sur les sujet qui ne vous interesse pas, de ce fait vous ne penser pas a réactualiser vos connaissance. vous pouvez aussi manquer d'imagination et de créativité. ce qui vous empèche d'être dans des emploie neccessitant d'innover ou de résoudre des problèmes complexes. vous pouvez parfois manquer d'ouverture d'esprit. vous pouvez aussi anquer de rigueur dans votre travail, les métier trop pointilleux peuvent vous poser des difficultés. | H5: Soldat, militaire, sportif, agent de police, agent administratif
B6: Organisation | C6: vous êtes une personnes méthodique. vous pouvez donc vous montrer patient dans mise en place de vos projets ou réalisations. Vous n'aimez rien laisser au hasard. Vous savez organisez et planifier les évènements et les projets. lorsque vous établisser un marche à suivre vous souhaitez la respecter à la lettre. ce qui veut qire que vous avez un facilité a fixer des objectifs. Vous aimez que les choses aient un place bien défini et que les activités aient des horaires bien définis. vous aimez respecter les délais et les horaires et êtes plutot ponctuel. vous êtes quelqu'un de rigoureux et vous pouvez vous montrer persévérent et strict quand il s'agit de finir ce que vous avez commencé. Vous avez la capacité de faire gagner du temps. vous pouvez aussi être bon dans la gestion de l'argent, car vous ne souhaite pas être prix au dépourvu financièrement. on eput aussi compter sur vous car vous êtes un personne de confiance. | D6: vous pouvez être rigide quand aux des régles et procédure à suivre. De plus si votre organisation est perturbé par un évènement hasardeux, vous pouver vous enerver vite ou perdre vos moyens. vous détester les environnements trop flexible et au changement régulier. Vous pouvez être allergique au changement et pouvez parfois manquez de spontanéïté.vous préferez les évènement planifiés et pouvez être perturbé quand on vous prend de court. vous pouvez aussi stresser quand les choses sont faites à la dernière minute. vous avez tendance à ne pas savoir profiter du moment car vous passez votre temps à vouloir anticiper, organiser les choses, d'ailleurs ce manque de spontaénité peut aussi vous faire stresser car vous avez toujours besoin d'avoir la sensation de maitriser les évènement et avez peur de tout voir s'écrouler si vous n'êtes pas au commande des process. attention à la charge mentale car à tout vouloir maitriser vous risquer d'avoir un surcharge de stress. Ce besoin d'organisation peut aussi avoir tendance à agacer les autres surtout vos proches. | E6: Assistant de gestion, Adjoint administratifs, responsable administratifs, agent général d'assurance, assistant de projet, chef de projet, assistant conducteur de travaux, administrateur réseaux, assistant conducteur de travaux, assistant de direction, assistant manager, chargée de production musicale, chef de comptable, expert comptable, chef de fabrication, chef de mission humanitaire, chef de produit touristique, chef de rayon, chef de secteur, chef magasinier, directeur logistique, logisticien, responsable des transport,directeur de club de football, directeur des opérations, directeur des ressources humaines, directeur des soins mileux hospitalier, directeur système d'information, directeur financier, directeur marketing, directeur technique. directeur territorial, ergonome, fiscaliste, gestionaire de paie, gestionnaire de parc automobile, gestionnaire de par informatique, gestionnaire de stock, ingénieur en fonderie, ingenieur en génie civie, responsable d'atelier, responsable d'entrepôt, responsable de gestion, administrative, responsable rémunération, responsable Qualité, sous préfet, wedding planner, organisateur d'évènement. | F6: Vous êtes plutôt quelqu'un qui agit en fonction de la situation et vous n'aimer pas passer trop de temps à préparer un plan. Vous avez donc un esprit flexible qui souhaite s'adapter en fonction des évènement. De plus vous êtes plutôt spontané dans vos actions ce qui vous permets d'agir la ou d'autres réfléchirait trop. vous êtes un personnes d'action. votre étourderie peu signifier que votre esprit fonctionne trop rapidement ou que vous penser beaucoup de choses en même temps. ceci est un signe de grand potentiel. vous êtes un personne d'action et votre impulsion vous permez souvent de réaliser certaines choses que d'autres ne ferons pas. de plus vous êtes plutot doué pourréaliser les tâches quotidiennes. | G6: Votre manque de structure peut parfois vous mettre en une situation ou vous êtes vites déborder. Vous avez du mal a prévoir et visualiser les évènements à venir ce qui peut qui vous handicaper sur certain types d'emploies. Vous pouvez passer pour quelqu'un d'étourdi et oublier parfois les choses, et même si elles sont essentielles à la réalisations d'un projet. il vous arrive d'avoir du mal a organiser vos idées. vous avez du mal a planifier les choses sur le long terme et à prioriser ce les taches importantes et urgentes de celles qui ne le sont pas. il vous arrive d'être en retard et de ne pas respecter les délais. vous avez aussi du mal à vous former tout seul, vous trouvez cette exercice difficille et préferez être accompagnée dans les taches qui demande un expertise particulière. vous avez du mal a vous fixer des objectifs logique à atteindre et de les mettre en relation avec des les besoins réèls que nécessite la réalisation de votre objectifs. attention à la persevérence car dès que la difficulté est trop élevé vous pouvez vite abandonner votre objectif.
B7: Intelligence sociale | C7: Vous avez une capacité a comprendre les comportements, pensée des autres personnes. Vous avez la capacité d'intégrer facilement des cercles sociaux différents des votres. Vous savez établir des relations harmonieuses avec les autres, et vous aimez réunir les gens. D'ailleurs vous aimez rencontrer des gens et en apprendre plus sur leur culture. vous savez créer et entretenir un réseau. vous avez donc un aisance relationelle.vous êtes quelqu'un de respectueux envers les autres car vous en cherchez pas à juger les autres mais plutot à essayer de les comprendre. d'ailleur vous y arriver plutot bien. vous avez aussi un capacité sous jacente celle de désamorcer les confilts entre un ou plusieur individus car vous comprennez d'ou peut venir la source de conflit. vous pouvez aussi être diplomate et savoir quoi dire et ne pas dire au bon moment. vous êtes aussi humble car sans cette capacité vous ne pourriez pas pouvoir ecouteret observer le point de vue les autres correctement. | D7: vous avez tendances à faire confiance trop rapidement aux autres, mais aussi à voir seulement le bien qu'il y a dans les personnes que vous rencontrer. Ce qui peut se retourner contre vous. De plus votre identité adaptable peut vraiment se modifier en fonction des rencontres, ce qui peut diminuer votre propre identité au dépend des autres. votre ouverture sociale d'esprit peut vous rendre moins critique sur des situation discutable en temps normals si cela implique un contact social. cette capacité peut aussi vous rendre manipulateur à certains moment surtout quand il s'agit d'obtenir quelque chose. | E7: Commercial, médiateur, psychologue, diplomate, auxiliaire de vie, chargé d'insertion sociale, guide touristique, steward , hôtesse de l'air, maitre de l'hotel, instructeur ou moniteur de plongé, animateur, explorateur, archéologue, journaliste, bloggeur, agent de voyage. agent immobilier, directeur marketing, directeur des ressources humaines, gestionnaire en patrimoine, agent sportif, directeur marketing, enseignant, formateur en entreprises, infirmier(ière), aides a domiciles, | F7: Vous avez tendance à ne pas vouloir changer de groupe d'amis ce qui vous rends plutôt fidèle avec vos proches. Vous préferez avoir un petit groupe d'amis en qui vous avez confiance que d'avoir une multitude de relations. Vous n'avez aucune difficulté à travailler seul quand il le faut ce qui peut avoir pour conséquences de vous rendre très autonome. vous avez une identité forte et très marqué vous êtes donc moins manipulable que les autres. vous êtes dynamisés en passant des moments tranquilles seuls ou en petit groupe. vous avez tendance à être plus réservés et réfléchis. | G7: vous pouvez paraître froid dans vos rapport avec les autres, même avec les membres de votre famille. Vous avez du mal à nouer des relations avec les gens même si vous le souhaitez. Il arrive que vous soyez parfois maladroit dans votre approche car vous ne comprenez pas vraiment ce que les gens veulent ou attendent de vous. vous avez donc très peu d'aptitudes sociales. c'est a dire que vous n'essayer ou n'arriver pas à comprendre ce que les gens pensent et veulent. vous ne tentez pas non plus de lé découvrir ou du moins quand vous essayer vous viser à coté. vous pouvez parfois manquez d'humilité ce qui vous empèche de vous placer à niveau égale des autres et de les comprendre et de les ecouter au mieux. Cela a pour conséquences de vous faire passer pour quelqu'un d'hautain. Ce qui indique que vous avez du mal à vous adapter à la personalité des autres et intégrer d'autres cercles sociaux que ce que vous connaissez déja. vous aimez rester dans votre coin, vous êtes donc plutot quelqu'un d'introvertie. dans le travail vous pouvez a voir du mal à travailler en équipe ou être un leader connecté. | H7: informaticien, ingénieur en informatique, ingénieur du son chercheur en laboratoires, bibliothécaire, documentaliste, Chargé / Chargée des ressources documentaires, rédacteur, écrivain, gardien, veileur de nuit, graphiste designer, transorteur routier, auditeur, comptable, contrôleur de gestion, mécanicien, grutier, entrepreneur, scénariste, géologue, polisseur, charpentier, artistes, ouvrier métallurgistes, berger, agent de chambre mortuaire, artisan, agent d'entretien, géomatitien
B8: Intelligence émotionnelle | C8: Vous avez la capacité de comprendre, expliquer et gerer vos émotions et celles des autres. Vous êtes quelqu'un d'empathique qui se soucie sincèrement des autres. votre humilité vous permet de vous intérresser aux émotions des autres plus qu'aux votress. Les gens ont un facilité a se confier à vous et vous aimez être a l'écoute. On peut vous définir comme quelqu'un de sensible. vous êtes aussi quelqu'un de sociable et avez la capacité de d'intégrer différents cercle sociaux. vous souhaitez sincèrement découvrir les autres afin de vouloir echanger, apprendre et partager. Vous avez une certaines maitrise de vous ce qui vous permet de moins stresser dans certaines situations mais aussi d'avoir moins de saut d'humeur ( stress, colère, chagrin, fou rire sans controle, joie exagérée...etc). vous êtes aussi quelqu'un de très motivé quand un cause ou un projet réponds à vos valeurs. Vous avez aussi la possibilité de solutionner les conflits entre individus en identifier la source émotionnelle du conflit. vous ne voulez pas forcément les manipuler les autres mais vous pouvez les influencer. de plus les décision émotionnelle sont plus facile à prendre pour vous. | D8: Vous êtes parfois trop empathique. Vous souciez trop du bien être des autres peut vous engouffrer dans leur problèmes. faites donc attention au syndrome du sauveur. Beaucoup de vos décision sont pris avec le cœur, ce qui peut parfois vous empécher de prendre des décision logiques ou rationnelles. votre sensibilité est à la fois votre meilleur atout et votre plus grand point faible. vous êtes parfois trop sensible à ce que le gens peuvent penser de vous, ce qui peut rapidement vous faire complexé. vous n'aimez pas spécialement les conflit surtout avec vos proches. ce qui signifie que vous préferez installez un climat sain et positif dans votre environnement. Même si vous ne souhaitez pas spécialement manipuler et influencer les autres vous avez la capacité de le faire, surtout les esprit faible. Selon les moment ceci est un avantage ou un inconvéniant. | E8: Stewart, hôtesse de l'air, manager d'équipe, coach de vie,psychothérapeute, enseignant, vétérinaire, infirmier, vendeur, commerciale, puériculteur, pédiatre, accompagnateur educatif, aides a domiciles, assistant maternel, animateur socio-culturel, médiateur sociale, chargé d'instertion. conseiller d'orientation. gestionaire en patrimoine, agent sportif, coach sportif | G8: Vous avez peu d'aptitude sociale ce qui vous empéche de facilement vous faire des amis ou d'intégrer d'autres groupe sociale que ceux dans lesquelles vous vous sentez à l'aise. vous pouvez parfois manquez de sensibilité et d'emphatie par rapport à ce que peu resentir votre entourage.Votre flegme dans certains moment d'émotion peut vous faitre passer pour quelqu'un d'insensible et de méprisant. Vous apporter peu de confiance aux gens ce qui peut vous faire passer pour quelqu'un d'associal.vous avez parfois du mal a prendre en comptes les besoins de considérations des autres personnes. il vous arrive de ne pas être motiver a faire quoi que ce soit et vous demander pourquoi vous vous levez le matin. vous n'avez pas beaucoup de maitrise de vous même c'est à dire que vous êtes sujet au saut d'humeur, vous vous énervez vite par exemple. il vous arrive donc d'être impulsif vous avez du mal a écouter les avis divergeant du votre et vous etes alergiques au critiques. dans le travail vous pouvez a voir du mal à travailler en équipe ou être un leader connecté.
B9: Management et gestion d'équipe https://www.cadremploi.fr/editorial/conseils/conseils-carriere/detail/article/tes-vous-un-mauvais-manager.html#ancre-2 | C9: on peut vous définir comme quelqu'un de charismatique.vous aimez diriger et influencer les gens. Vous savez communiquer vos idées et être compris par vos collaborateurs et camarades. Vous avez un capacité à réunir les individus, les motiver et les encourager. Vous aimez mettre en place des projets et les voir fonctionner. votres esprit d'initiative vous permet de tester la ou d'autres ne ferais que penser. Pour cela vous allez trouver et réunir les bons outils et les personnes pour que tout fonctionne. vous savez trancher et prendre les décisions même si celles-ci ne plaise pas, mais vous essayer toujour d'en expliquer les raisons. vous savez vous rendre disponible pour elever les autres et êtes à l'écoute des besoins. et vous prenez du plaisir à former les autre et les voir évoluer. vous essayer de solutionner les conflits entre lorsque vous en voyez un dans votre groupe. vous savez aussi vous adapter au imprévues. vous adorer l'effervécence que peut générer le travaille en équipe. | D9: vous pouvez avoir le syndrome du sauveur. C'est à dire que vous souhaitez systématiquement aider les autres, même ceux qui ne le mérite pas. Vous voulez même les élever au point de parfois trop vous donner pour les autres. Vous avez tendance à avoir un relation trop paternalistes avec les autres, en voulant leur donner trop de conseils par exemple et en les considérant parfois comme des gens proches aux risque de vous exposer émotionnelement au trahison. | E9: Manager d'équipe, coach, gestionnaire de projet, Consultant, entrepreneur, organisateur d'évènement, coach sportif, entraîneur, | F9: vous travaillez très bien seul. Vous avez un forte personnalité affirmée, ce qui vous rends moins influencable au avis des autres, vous ne souhaitez rien laisser au hasard dans les choses entreprises, et aimez controler tout ce qui se passe. votre esprit est donc en alerte de tous ce qui se passe.Vous savez imposer votre autorité aux autres et mettre en place des sanction quand il le faut. vous avez un facilité à donner des ordres ou d'autres auraient des réticences à prendre les reines. | G9: Vous avez du mal à diriger ou influencer les autres a vous suivre, même quand il s'agit d'une bonne cause. De ce fait, vous avez tendance à remettre en question votre force mental et votre crédibilité. cela implique que vous avez du mal à communiquer et transmettre vos idées correctement. Vous pouvez parfois considerez les autres comme des outils et oublier de considerer leur efforts même les plus grands, car vous vous concentrer surtout sur les résultats obtenus. Il vous est difficille de vouloir former les autres.vous aimez bien donnez des ordres mais pas forcément donner l'exemple.Vous pouvez parfois manquer de prise d'initiative. vous avez tendance à créer un climat trop compétitifs ce qui peut avoir pour effet de créer des conflits. vous même aussi tendance à faire favoritisme dans le cadre de la gestion d'équipe. vous avez aussi tedance à mal réagir à la pression. Vous pouvez aussi être réticent au changement. vous pouvez parfois manquer de vision ce qui vous empeche de prendre de la hauteur sur certaines situation et prendre des décision cohérentes. il vous arrive d'avoir du mal à pendre un décision difficille par peur qu'elle est des répercussions graves sur votre personnes. vous avez donc du mal à trancher quand ça vous concerne. vous préferez donc tansmettre ce prise de décision à quelqu'un d'autres. vous pouvez aussi vous défausser en cas de problème et rejeter la faute sur les autres. vous pouvez parfois vous montrer impulsifs dans vos réactions et manquer de respects à vos camarades et collaborateurs.
B10: Communication | C10: Vous avez la capacité de vous exprimer en public. vous êtes d'ailleurs audacieux et n'hésitez pas aborder les gens quand la situation l'exige. Lorsque vous parlez on vous comprend parfaitement et vous savez capter l'attention. vous tentez parfois d'apter votre discours dans le fond et la forme aux personnes qui vous écoute.Vous êtes plutôt quelqu'un d'extraverti, de conviviale et vous aimez allez vers les autres. vous avez la capacité de convraincre les autres et leur transmetter vos idées, mais aussi leur faire imaginer des concepts compliqués. vous avez de la prestance, lorsque vous entrer dans une salle ont vous remarque. Lorsque vous débattez vous êtes diplomate, vous essayer de persuader ou de prouver ce que vous avancer sans blesser. vous essayer d'avoir de l'humour pour mettre les gens à l'aise. vous savez aussi être à l'écoute des autres pour pouvoir mieux répondre. | D10: Vous manquer parfois de réserve à des moment ou il le faudrait. Votre énergie peut parfois fatigué ou effrayé certaines personnes, notamment les introvertis. Vous pouvez parfois passer pour quelqu'un de superficiel qui cherche à plaire à tout le monde même si ce n'est pas le cas. vous pouvez aussi avoir tendance a vous concetrer plus sur la forme que le fond dans vos propos ou communication, au point de sonner creux pour ceux qui observe et analyse attentivement. faites attention à votre exposition car à vouloir trop se motrer on s'expose au critiques acerbes de ceu qui observent. | E10: humoriste, acteur, présentateur télé, influenceur, agent immobilier, agent sportif, commercial, gestionnaire de patrimoine, agent sportif, agent musical, artiste musical, coach sportif, entraîneur, chef d'équipe, politicien | F10: Vous êtes quelqu'un de discret et ne fais pas dans l'esbrouffe. Vous vous concentrer plus sur la fond que la forme. Votre calme peut être apprécier. Vous avez tendance à être plus réservés et réfléchis. Vous êtes plus performant dans les environement calme et réservée. sont dynamisés en passant des moments tranquilles seuls ou en petit groupe. | G10: vous avez du mal à exprimez vos idées et à faire en sorte qu'elles soit comprises parfaitement.Il vous arrive par exemple d'avoir du mal à raconter des histoires et à susciter l'intérêt de vos interlocuteurs facilement. vous pouvez avoir peur de vous adresser à un publique et perdre vos moyens ce qui peut renforcer votre timidité. A cause de tout cela, vous pouvez parfois manquer de confiance. Vous n'êtes pas du genre à aller facilement vers les autres et préférez rester en retrait lors de grand évènement. ce manque d'extraversion peut vous empécher de rencontrer les bonnes personnes aux bon moment, ou de saisir de bonne opportunités de rencontre. | H10: informaticien, ingénieur en informatique, ingénieur du son chercheur en laboratoires, technicien en laboratoire, bibliothécaire, documentaliste, Chargé / Chargée des ressources documentaires, rédacteur, écrivain, gardien, veileur de nuit, graphiste designer, transorteur routier, auditeur, comptable, contrôleur de gestion, mécanicien, grutier, entrepreneur, scénariste, géologue, polisseur, charpentier, artistes, ouvrier métallurgistes, berger, agent de chambre mortuaire, artisan, Orthodontiste, assistant administratif
B11: Ethique | C11: Vous êtes le genre de personnes qui croient en des principes fort et aux valeurs d'honnêteté, d'intégrité, de loyauté, et d'équité. ce qui veut dire que vous susciter la confiance chez les autres. Vous meprisez l'injustice et les personne corrompu par le pouvoir. vous n'aimez pas prendre des décisions ou transgresser des régles qui vont à l'encontre de vos valeurs et croyances. vous avez tendances a ne pas vouloir tricher dans ce que vous entreprenez, préférant pedre dans l'honneur que de gagner des le déshonneur. si cela avantage le bien commun, vous êtes capable de prendre un décision qui vous handicaperait. vous changer très peu d'avis vous n'êtes pas versatile. lors que vous engager vous le faites vraiment et vous essayer toujours de tenir vos promesses. les problème globaux vous intérresse, comme l'environnement, la gestion des ressources. | D11: il vous est parfois très difficile voir impossible de faire des compromis quand il vont à l'encontre de vos croyances et valeurs. Cela vous rend rigide dans vos relations avec les autres et peut vous faire perdre des opportunités. Vous pouvez parfois vous mettre dans un état d'engagement trop fort, au point de défendre des causes perdu ou vous engager pour des amis ou connaissances qui n'en valent pas la peine. vous pouvez vous montrer rigides aux compromis qui ne sont pas complétement ethique ou qui ne respecte pas vos valeurs, votre sens de l'honneur, ou votre personalité. cela peut vous faire rater certaines oportunités. | E11: Défenseur des droit de l'homme, Responsable qualité. Responsable sécurité, avocat, juges, procureur de la république, procureur, police des polices, Officier de gendarmerie, policier, juges des affaires familliales,juges des enfants, animateur nature, chargé de communication environnement,chef de projet innovation et transformation, conseiller info-énergie,juriste en droit de l’environnement,chef de projet biodiversité, comissiaire de police, députés, entrepreneur sociale,ecotoxicologiques,chargé d'hygiène et de sécurité,responsable HSE ou QSE,technicien de trauitement de déchet, conseiller(ière) en environnement, inspecteur du travail,ecotoxicologue, directeur environnement, géologue,biochimiste,ingénieur de dépolution,sismologues, technicien de mesure de la pollution, volcanologue, hydrobiologiste, coéanologue, responsable d'usine d'eau potable, chargé d’affaires en génie thermique et climatique, chef de chantier en génie climatique et sanitaire, chef de projet en énergies renouvelables, ingénieur en énergies renouvelables, ingénieur en génie thermique, technicien thermicien, technico-commercial thermicien,agent technique d’entretien des cours d’eau, agent technique forestier, chargé d’études en environnement, écologue, élagueur,expert naturaliste, garde du littoral,garde-chasse, garde-pêche,garde-moniteur du parc national,ingénieur des travaux des eaux et forêt, ingénieur du génie rural des eaux et forêts,technicien de rivière,ingénieur agronome, | F11: vous avez un facilité à mettre en place des compromis quand il le faut. vous n'êtes pas du genre vous emporter pas facilement lorsque qu'un injustice arrive. Vous êtes plutôt flexible et adaptable en fonction des situations. | G11: vous pouvez parfois changer très facilement d'avis au point de transgresser facilement vos propres règles pour arriver a vos fins. Vous placez souvent votre intérêt avant l'intérêt général, ce qui peut vous créer des ennemis la ou vous n'en n'auriez normalement. On peut parfois vous considérez comme une personne avec peu principe et d'honneur même si ce n'es pas le cas, certaines personnes auront parfois du mal à vous faire confiance. vous pouvez transgresser vos propres principes pour arriver à vos fins. car ce qui compte surtout c'est le résultat. vous pouvez parfois manquez de loyauté dans vos relations. vous pouvez aussi | H11: Négociateur d'affaires, commercial en assurances, banquier, trader, conseiller financier, politiciens, influenceur, conseiler en image, Avocat, diplomate,

Sheet liste déroulante
B2: Catégories de soft skill | C2: Catégorie MBTI | D2: Lettres MBTI | E2: Réponse
B3: Esprit critique | C3: Energie (E-extraverti ou I-Introverti) | D3: E | E3: A
B4: Organisation | C4: Recueil d'information ou perception (S-sensation ou N-intuition) | D4: I | E4: B
B5: Intelligence sociale | C5: Prise de décision (T-pensée ou F-sentiment) | D5: S | E5: C
B6: Intelligence émotionnelle | C6: Mode d'action ou style de vie (J-Organisation ou P-perception) | D6: N | E6: D
B7: Management et gestion d'équipe | D7: T
B8: Management de projet | D8: F
B9: Communication | D9: J
B10: Etat d'esprit et attitude | D10: P
B11: Ethique

Sheet Feuil1
B2: Catégorie | C2: Communication | D2: Communication | E2: Communication | F2: Communication | G2: Communication | H2: Communication | I2: Communication | J2: Communication | K2: Communication | L2: Esprit critique | M2: Esprit critique | N2: Esprit critique | O2: Esprit critique | P2: Esprit critique | Q2: Esprit critique | R2: Esprit critique | S2: Esprit critique | T2: Esprit critique | U2: Ethique | V2: Ethique | W2: Ethique | X2: Ethique | Y2: Ethique | Z2: Ethique | AA2: Ethique | AB2: Ethique | AC2: Ethique | AD2: Intelligence émotionnelle | AE2: Intelligence émotionnelle | AF2: Intelligence émotionnelle | AG2: Intelligence émotionnelle | AH2: Intelligence émotionnelle | AI2: Intelligence émotionnelle | AJ2: Intelligence émotionnelle | AK2: Intelligence émotionnelle | AL2: Intelligence émotionnelle | AM2: Intelligence sociale | AN2: Intelligence sociale | AO2: Intelligence sociale | AP2: Intelligence sociale | AQ2: Intelligence sociale | AR2: Intelligence sociale | AS2: Intelligence sociale | AT2: Intelligence sociale | AU2: Intelligence sociale | AV2: Management de projet | AW2: Management de projet | AX2: Management de projet | AY2: Management de projet | AZ2: Management de projet | BA2: Management de projet | BB2: Management de projet | BC2: Management de projet | BD2: Management de projet | BE2: Management et gestion d'équipe | BF2: Management et gestion d'équipe | BG2: Management et gestion d'équipe | BH2: Management et gestion d'équipe | BI2: Management et gestion d'équipe | BJ2: Management et gestion d'équipe | BK2: Management et gestion d'équipe | BL2: Management et gestion d'équipe | BM2: Management et gestion d'équipe | BN2: Organisation | BO2: Organisation | BP2: Organisation | BQ2: Organisation | BR2: Organisation | BS2: Organisation | BT2: Organisation | BU2: Organisation | BV2: Organisation
B3: Soft skill | C3: Communication écrite | D3: L’audace (ou le culot) | E3: L’enthousiasme et le dynamisme | F3: La clarté de communication | G3: La diplomatie | H3: La négociation | I3: La posture ou la communication non verbale | J3: Prise de parole en public | K3: Rhétorique ou storytelling | L3: Actualisation des connaissances | M3: L’acuité et le discernement | N3: L’humour | O3: L’ouverture d'esprit | P3: La créativité ou l'imagination | Q3: La curiosité | R3: Pensée critique | S3: Résolution des problèmes | T3: Savoir rechercher pour résoudre un problème | U3: L’intégrité | V3: La conscience professionnelle | W3: La loyauté | X3: La respectabilité, la dignité, l'honneur | Y3: Le sens des responsabilité | Z3: Le sens du sacrifice | AA3: L'éco-responsabilité | AB3: L'engagement | AC3: Respect des autres (doublon tolérance) | AD3: Acceptation des retours et critiques | AE3: Introspection | AF3: L’empathie | AG3: La bienveillance | AH3: La confiance en soi | AI3: La gestion du stress | AJ3: La maitrise de soi | AK3: La reconnaissance ou considération | AL3: La sensibilité | AM3: Aisance relationnelle | AN3: Altruisme | AO3: Esprit d'équipe | AP3: Intelligence culturelle | AQ3: L’interaction avec les autres | AR3: La coopération, la collaboration | AS3: La tolérance | AT3: Le networking | AU3: Sociabilité | AV3: L’Autonomie | AW3: La délégation de taches | AX3: La facilitation | AY3: La fixation d'objectifs | AZ3: La gestion des risques | BA3: La prise de décision | BB3: La supervision | BC3: La tolérance au changement | BD3: L'agilité cognitive | BE3: Equité | BF3: Gérer et résoudre les conflits | BG3: Gérer les équipes à distances | BH3: Inclusivité | BI3: L’esprit d’initiative | BJ3: La valorisation ou l'encouragement | BK3: Le charisme | BL3: Le coaching des autres | BM3: Leadership | BN3: L’auto-formation | BO3: La concentration | BP3: La gestion des ressources | BQ3: La gestion du temps | BR3: La hiérarchisation et la priorisation | BS3: La planification | BT3: La recherche d'efficacité | BU3: La visualisation | BV3: Le respect des délais
B4: Classe MBTI | C4: Energie (E-extraverti ou I-Introverti) | D4: Mode d'action ou style de vie (J-Organisation ou P-perception) | E4: Energie (E-extraverti ou I-Introverti) | F4: Energie (E-extraverti ou I-Introverti) | G4: Prise de décision (T-pensée ou F-sentiment) | H4: Energie (E-extraverti ou I-Introverti) | I4: Energie (E-extraverti ou I-Introverti) | J4: Energie (E-extraverti ou I-Introverti) | K4: Energie (E-extraverti ou I-Introverti) | L4: Recueil d'information ou perception (S-sensation ou N-intuition) | M4: Recueil d'information ou perception (S-sensation ou N-intuition) | N4: Recueil d'information ou perception (S-sensation ou N-intuition) | O4: Mode d'action ou style de vie (J-Organisation ou P-perception) | P4: Recueil d'information ou perception (S-sensation ou N-intuition) | Q4: Recueil d'information ou perception (S-sensation ou N-intuition) | R4: Recueil d'information ou perception (S-sensation ou N-intuition) | S4: Prise de décision (T-pensée ou F-sentiment) | T4: Recueil d'information ou perception (S-sensation ou N-intuition) | U4: Prise de décision (T-pensée ou F-sentiment) | V4: Prise de décision (T-pensée ou F-sentiment) | W4: Prise de décision (T-pensée ou F-sentiment) | X4: Prise de décision (T-pensée ou F-sentiment) | Y4: Prise de décision (T-pensée ou F-sentiment) | Z4: Prise de décision (T-pensée ou F-sentiment) | AA4: Prise de décision (T-pensée ou F-sentiment) | AB4: Prise de décision (T-pensée ou F-sentiment) | AC4: Prise de décision (T-pensée ou F-sentiment) | AD4: Prise de décision (T-pensée ou F-sentiment) | AE4: Prise de décision (T-pensée ou F-sentiment) | AF4: Energie (E-extraverti ou I-Introverti) | AG4: Prise de décision (T-pensée ou F-sentiment) | AH4: Energie (E-extraverti ou I-Introverti) | AI4: Mode d'action ou style de vie (J-Organisation ou P-perception) | AJ4: Prise de décision (T-pensée ou F-sentiment) | AK4: Prise de décision (T-pensée ou F-sentiment) | AL4: Prise de décision (T-pensée ou F-sentiment) | AM4: Energie (E-extraverti ou I-Introverti) | AN4: Energie (E-extraverti ou I-Introverti) | AO4: Energie (E-extraverti ou I-Introverti) | AP4: Energie (E-extraverti ou I-Introverti) | AQ4: Energie (E-extraverti ou I-Introverti) | AR4: Energie (E-extraverti ou I-Introverti) | AS4: Mode d'action ou style de vie (J-Organisation ou P-perception) | AT4: Energie (E-extraverti ou I-Introverti) | AU4: Energie (E-extraverti ou I-Introverti) | AV4: Mode d'action ou style de vie (J-Organisation ou P-perception) | AW4: Prise de décision (T-pensée ou F-sentiment) | AX4: Prise de décision (T-pensée ou F-sentiment) | AY4: Prise de décision (T-pensée ou F-sentiment) | AZ4: Prise de décision (T-pensée ou F-sentiment) | BA4: Prise de décision (T-pensée ou F-sentiment) | BB4: Mode d'action ou style de vie (J-Organisation ou P-perception) | BC4: Mode d'action ou style de vie (J-Organisation ou P-perception) | BD4: Mode d'action ou style de vie (J-Organisation ou P-perception) | BE4: Prise de décision (T-pensée ou F-sentiment) | BF4: Prise de décision (T-pensée ou F-sentiment) | BG4: Energie (E-extraverti ou I-Introverti) | BH4: Energie (E-extraverti ou I-Introverti) | BI4: Mode d'action ou style de vie (J-Organisation ou P-perception) | BJ4: Prise de décision (T-pensée ou F-sentiment) | BK4: Energie (E-extraverti ou I-Introverti) | BL4: Energie (E-extraverti ou I-Introverti) | BM4: Mode d'action ou style de vie (J-Organisation ou P-perception) | BN4: Mode d'action ou style de vie (J-Organisation ou P-perception) | BO4: Mode d'action ou style de vie (J-Organisation ou P-perception) | BP4: Prise de décision (T-pensée ou F-sentiment) | BQ4: Mode d'action ou style de vie (J-Organisation ou P-perception) | BR4: Prise de décision (T-pensée ou F-sentiment) | BS4: Mode d'action ou style de vie (J-Organisation ou P-perception) | BT4: Mode d'action ou style de vie (J-Organisation ou P-perception) | BU4: Recueil d'information ou perception (S-sensation ou N-intuition) | BV4: Mode d'action ou style de vie (J-Organisation ou P-perception)
B5: Explication | C5: Capacité à être facilement lu et compris mais aussi de susciter l'intérêt lorsque l'on transmet un message par écrit. | D5: Capacité à mettre en place ou réaliser des actions qui semblent risquées, difficiles et/ou irréalisables. | E5: Aptitude à exprimer sa joie ouvertement sans réfréner son émotion. | F5: Capacité à exprimer clairement ses idées lorsque l’on s’adresse à un ou plusieurs individus. | G5: Qualité qui permet d'apprécier intuitivement ce qu'il convient de dire, de faire ou d'éviter dans les relations humaines. | H5: Capacité à trouver un accord avec un ou plusieurs partis. | I5: Capacité à communiquer avec son corps. Par les gestes, le regard, les déplacements, la position de son corps. | J5: Capacité à s'exprimer devant une foule, ou lors d'évènements. | K5: L’art de savoir raconter ou narrer une histoire. | L5: Capacité à renouveler les connaissances et les compétences acquises. | M5: Capacité de l'esprit à juger clairement et sainement des choses | N5: Forme d'esprit qui s'attache à souligner le caractère comique, ridicule, absurde ou insolite de certains aspects de la réalité | O5: Tolérer et manifester de l'intérêt, de la curiosité et de la compréhension pour les idées qui diffèrent en partie ou totalement des siennes. | P5: Faculté de former des images d'objets qui n'ont pas été perçus ou de créer de nouvelles combinaisons d'images ou d'idées, de se représenter des situations possibles. | Q5: Désir de rechercher et trouver l’information dont on ne dispose pas, dans le but d’apprendre. | R5: Disposition intellectuelle qui permet de raisonner correctement, de tirer des conclusions qui ne soient pas prématurées, mais réfléchies et étayées par des arguments.Capacité à questionner et remettre en cause des préjugés et des opinions "toutes faites". | S5: Capacité à comprendre et résoudre les problèmes. | T5: Savoir mener des recherches, pour répondre à une question, pour résoudre un problème. | U5: Capacité à ne pas être corrompu ou influencé, à respecter les règles établis sans tricher. Être droit en toutes circonstances. | V5: Être soigneux et appliqué dans la réalisation d’une tâche ou d'un projet, d'un travail peu importe son état mental. | W5: Capacité à respecter les engagements fixés et être fidèle envers un organisme, un ou plusieurs individus, une loi, une doctrine, une croyance une religion…etc. | X5: Être honorable dans les actions entreprises. Susciter le respect. | Y5: Aptitude à s'assurer de la qualité des actions entreprises et en assumer les conséquences, qu'elles soient bonnes ou mauvaises. | Z5: Réfréner ses besoins personnels afin de favoriser la réussite du groupe | AA5: Respecter les règles de protection de l'environnement | AB5: Capacité de se lier par une promesse ou une convention à la réalisation (ou non réalisation) d'une action et de s'y tenir. | AC5: Avoir de la considération pour les idées, les opinions, les sentiments, les croyances, les coutumes d'un ou plusieurs individus sans émettre de jugement à leur encontre. | AD5: Capacité à recevoir des critiques constructives sans se vexer. | AE5: Aptitude à analyser ses propres émotions, ses aptitudes, ses faiblesses dans le but de se perfectionner. | AF5: Capacité à ressentir les émotions d’autres individus (joie, tristesse, honte, frustration, etc.). | AG5: Aptitude à se montrer attentif au bien-être et au bonheur des autres par le biais de conseils donnés ou d'actions menées en leur faveur. | AH5: Avoir toujours confiance en ses capacités ou ses actions. | AI5: Capacité à supporter la pression liée à la réalisation d’une ou plusieurs tâches sans paniquer (examens, projets, demandes hiérarchiques, présentations, etc.). | AJ5: Rester maître de ses émotions peu importe l'intensité émotionnelle de la situation. | AK5: Apprécier les idées, l'investissement, le travail d'autres individus et les féliciter quand les résultats sont positifs. | AL5: Aptitude à s'émouvoir, à éprouver des sentiments d'humanité, de compassion, de tendresse envers autrui, autre chose ou un évènement. | AM5: Capacité à nouer des relations et de les entretenir. | AN5: Capacité à se soucier du bien des autres et de s'y consacrer de façon désintéressée. | AO5: Aptitude à faire preuve d'altruisme et de solidarité avec les membres de son groupe. | AP5: Capacité de s'adapter à différents contextes ou groupes culturels. | AQ5: Capacité à échanger discuter et côtoyer d’autres individus. | AR5: Aptitude à travailler avec un ou plusieurs autres individus dans le but d'une réalisation commune. | AS5: Attitude qui consiste à admettre chez autrui une manière de penser ou d'agir différente de celle qu'on adopte soi-même | AT5: Capacité à nouer et maintenir des liens avec d'autres individus et de se créer un réseau sur le long terme. | AU5: Capacité à vivre en société ou avec un groupe d'individu. Recherche de compagnie. | AV5: Ne pas avoir besoin d’accompagnement lorsque l’on entreprend une action. | AW5: Capacité à déléguer et répartir les tâches. | AX5: Capacité à générer un cadre, des méthodes et des processus de travail favorisant l’émergence d’idées et l'atteinte d'objectifs. | AY5: Capacité à fixer des objectifs spécifiques, mesurables, atteignables, réalistes et temporels. | AZ5: Capacité à lister et évaluer les scénarios problématiques et trouver des solutions pouvant les résoudre. | BA5: Aptitude à effectuer un choix entre plusieurs modalités d'actions possibles lors de la confrontation à un problème. | BB5: Capacité à exercer un contrôle et à effectuer une vérification sur l'activité ou le travail d'une ou plusieurs personnes. | BC5: Capacité à accepter la rupture ou la modification de processus, d'une routine, d’un mode vie, d'une méthode de travail, d'un groupe social. | BD5: Aptitude à s'adapter facilement aux changements et à réagir aux problématiques qui ne répondent pas à notre mode de fonctionnement mental. | BE5: Capacité à traiter les situations et les individus de manière juste et impartiale, sans parti pris. | BF5: Capacité à être médiateur et trouver les solutions aux situations de tension entre deux ou plusieurs individus. | BG5: Capacité à diriger d'autres individus sans être physiquement présent. | BH5: Aptitude à intégrer facilement un individu à un groupe. C'est différent de l'exclusion. | BI5: Capacité à entreprendre des actions sans que l'on y soit poussé. | BJ5: Mettre en avant les qualités ou les résultats d'un ou plusieurs individus pour renforcer leur confiance en soi et leur permettre de faire mieux. | BK5: Capacité à plaire et à s’imposer naturellement. Sans forcer les autres à nous apprécier. | BL5: Capacité à stimuler l'intérêt des autres sur un sujet, une mission, un travail et faire ressortir le meilleur d'eux même. | BM5: Capacité à réunir et diriger plusieurs individus sans utiliser la force, pour mener à bien un projet ou une action. | BN5: Capacité à se former sans aide extérieure d’un mentor, professeur ou guide | BO5: Capacité à focaliser son esprit sur une tâche, ou un sujet particulier sans diverger. | BP5: Capacité à identifier et quantifier les ressources (humaines, matérielles, financières, etc.) nécessaires la réalisation d'un projet, d’une action, d’une entreprise. | BQ5: Capacité à organiser ce que l’on entreprend afin de respecter les délais accordés. | BR5: Capacité à prioriser les tâches selon leur importance et leur urgence | BS5: Capacité à organiser les actions et tâches selon un plan défini temporellement | BT5: Capacité à fournir un résultat, en fonction des délais et moyens accordés. | BU5: Capacité de se projeter mentalement dans une situation future. | BV5: Aptitude à arriver à l'heure et rendre les attendus au moment demandé
B6: Question | C6: Lorsque vous rédigez une note ou un écrit à destination d'autres individus : | D6: Lors d'une réunion professionnelle, on vous propose soudainement de présenter vos idées sur un projet complexe devant des plusieurs supérieurs. Vous n'avez pas préparé de présentation formelle. Comment réagissez-vous ? | E6: Lorsque vous êtes avec votre groupe d'amis, vous êtes : | F6: Lorsque vous parlez, devez-vous répéter régulièrement vos phrases pour être parfaitement compris ? | G6: Lorsqu'on vous demande de donner votre avis sur un sujet sensible, vous avez tendance à : | H6: Vous trouvez un objet que vous souhaitiez acheter depuis longtemps, simplement le prix est trop élevé par rapport à votre budget. | I6: Lorsque vous vous exprimez, vous avez tendance à : | J6: Lorsqu'on vous demande de vous présenter devant une foule de personnes, votre première pensée est : | K6: Lorsque vous racontez une histoire, un évènement ou le résumé d'un film : | L6: Lors d'une conversation avec des collègues, un nouveau logiciel révolutionnaire dans votre secteur est mentionné, mais vous ne le connaissez pas. Que faites-vous ensuite ? | M6: Un de vos amis de confiance partage une publication qui affirme que l'utilisation fréquente des téléphones mobiles peut causer de graves problèmes de santé. Quelle est votre réaction ? | N6: Êtes-vous le type de personnes à toujours trouver ce qu'il y a de drôle même dans les situations Malaisantes ? | O6: Une nouvelle personne intègre votre groupe de travail. Elle vous informe qu'une des méthodes que vous utilisez est totalement obsolète. | P6: On vous demande de créer une histoire : | Q6: Une de vos amis vous conseille une nouvelle série phénomène qui sort le mois prochain. Votre réaction : | R6: Vous devez partir en voyage dans un pays pour les vacances. Vous découvrez que le journal télévisé décrit ce pays comme dangereux. | S6: Lorsque vous vous retrouvez en face d'un problème difficile à résoudre : | T6: Vous devez assembler un meuble complexe chez vous. Cependant, vous vous rendez compte que vous avez perdu le mode d'emploi. | U6: Après avoir payé vos achats, vous remarquez que le caissier vous a rendu trop de monnaie. Comment réagissez-vous ? | V6: Vous avez un travail de groupe important à finir pour le lendemain. Votre meilleur(e) ami(e) vous appelle, en vous expliquant qu'il/elle part 6 mois au Mexique et qu'il/elle aimerait passer sa dernière soirée avec vous. | W6: Vous devez réaliser un travail de groupe entre amis. Cependant, le groupe de travail sympathique dans lequel vous êtes ne fonctionne pas du tout. Votre réaction : | X6: Vous jouez à un jeu vidéo extrêmement difficile et vous trouvez un cheat code qui vous permet de le terminer beaucoup plus facilement, sans que personne le sache. | Y6: En jouant au foot près d'une maison vous brisez une fenêtre. Tous vos amis se mettent à courir, votre réaction : | Z6: Un génie vous propose la possibilité de réaliser un seul vœu parmi ces propositions. Lequel choisissez-vous ? | AA6: Vous avez la possibilité d'acheter une voiture, vous avez le choix entre plusieurs possibilités : | AB6: Seriez-vous capable de tenir une promesse faite à une amie, même si cette promesse pourrait vous faire du mal ? | AC6: Pourriez-vous prendre en considération une opinion qui bafoue vos principes, vos croyances et/ou votre culture ? | AD6: Vous avez mis 3 mois à réaliser un dossier complexe, vous le montrer à un inconnu qui juge les résultats déplorables. | AE6: Si on vous demande de citer vos qualités et vos défauts, y arrivez-vous facilement ? | AF6: Vous assistez à un spectacle, l'un des acteurs oublie son texte et ne sait plus quoi dire. C'est le silence | AG6: La veille d'un examen, vous tombez par hasard sur les réponses qui peuvent vous assurer la réussite aux examens : | AH6: Vous avez l'opportunité de diriger un projet important au travail. Cela implique de prendre des décisions clés et de gérer une équipe. | AI6: Une heure avant une présentation orale importante, votre ordinateur plante et vous perdez tous vos documents. Votre réaction : | AJ6: Une personne prend du plaisir à vous humilier public, comment réagissez-vous ? | AK6: Vous avez confié une tâche simple à l'un de vos collaborateurs. Il réussit avec brio. Il attend une réaction de votre part : | AL6: Vous venez d'apprendre que la femme d'un voisin, avec qui vous peu d'affinité, vient d'être hospitalisé dans un état grave, vous êtes du genre à : | AM6: Lorsque vous vous rendez dans un évènement, une soirée, vous êtes du genre à : | AN6: Vous vous rendez compte que vous êtes le seul à avoir bien noté les informations liées à un examen important. | AO6: Vous devez réaliser un travail, mais il sera pris en compte uniquement si vous le réalisez en groupe, votre réaction : | AP6: Si vous deviez aller dans un pays étranger en vacances, vous seriez : | AQ6: Avez-vous une facilité à interagir avec les gens que vous ne connaissez pas ? | AR6: Avez-vous une facilité à collaborer avec des personnes avec qui vous n'avez aucunes affinités ? | AS6: Quelqu'un affirme que vous êtes une mauvaise personne. | AT6: Aimez-vous nouer des liens avec les gens et entretenir les relations sur le long terme ? | AU6: Lorsque vous devez aller en soirée ou à un anniversaire vous êtes du genre à : | AV6: Lorsqu'un qu'on vous confie un projet ou une tâche sans instructions détaillées, comment procédez-vous ? | AW6: Avez-vous des difficultés à confier des tâches aux autres ? | AX6: Si vous deviez choisir un rôle dans un groupe de travail, ce serait : | AY6: Vous envisagez d'apprendre une nouvelle langue cette année. Comment prévoyez-vous de gérer ce projet ? | AZ6: Lorsque l'on met en place un projet, quel qu’il soit, que faut-il prendre en compte en premier lieu ? | BA6: Il reste 3 mois à vivre à une personne que vous aimez. Un médecin propose une solution qui pourrait prolonger sa vie de 10 ans en cas de réussite, ou le tuer en cas d'échec. | BB6: Lorsque vous effectuez un travail de groupe, ce que vous préférez c'est : | BC6: Vous avez un planning établi pour les deux prochains mois à venir. Du jour au lendemain, on vous le change. Votre réaction : | BD6: Imaginons que vous êtes en train de jouer à un jeu de société avec des amis. D'un coup, toutes les règles établies sont modifiées. Comment réagissez-vous ? | BE6: Comment pensez-vous que les richesses du monde devraient être réparties ? | BF6: Lorsque deux personnes que vous connaissez sont en conflit, vous avez tendance à : | BG6: Vous devez gerer un travail de groupe important et votre équipe est dispersée dans différentes régions. Comment gérez-vous la situation ? | BH6: Vous êtes dans une soirée en appartement, vous remarquez qu'un(e) des invité(e)s est seul(e) dans son coin : | BI6: Vous êtes en face d'un travail qui nécessite une compétence que vous n'avez pas, allez-vous chercher à le réaliser quand même ? | BJ6: Quelqu’un de votre entourage veut s'aventurer dans un domaine dans lequel il a vraiment peu de chance de réussir. | BK6: Lorsque vous proposez des activités à des personnes que vous côtoyez, ils ont tendance : | BL6: Vous remarquez qu’un membre de votre groupe de travail a du mal à réaliser les travaux qui lui sont confiés. | BM6: Lorsque vous êtes dans un groupe de travail, vous êtes celui : | BN6: Tu entends parler d'un sujet intéressant qui n'est pas couvert par ton cursus scolaire ou par ta formation. Que fais-tu ? | BO6: Vous devez compléter une tâche longue et répétitive, et ennuyeuse. Comment maintenez-vous votre concentration tout au long de cette tâche ? | BP6: Lorsque l'on met en place un travail de groupe pour un projet, de quoi faut-il s'assurer en premier ? | BQ6: Vous devez rendre un travail dans plusieurs mois, vous préférez : | BR6: Comment faites-vous pour gérer différentes tâches lorsqu’il y en a vraiment beaucoup ? | BS6: Pour passer les meilleures vacances possibles, il vaut mieux : | BT6: Vous avez 5 jours pour réaliser un travail qui en prend normalement 9, votre réaction sera : | BU6: Lorsque tu te prépares pour un projet important ou un événement à venir, comment planifies-tu tes actions | BV6: Vous avez rendez-vous avec l'élu de votre cœur près d'un lac romantique, vous êtes plutôt du genre à :
B7: A | C7: Vous ne recevez jamais de retour négatif car vous êtes un expert de la communication écrite. | D7: J'accepte l'opportunité spontanément, en me fiant à ma connaissance du sujet pour guider ma présentation. | E7: Celui qui rigole tout le temps, qui cherche à mettre l'ambiance. | F7: Non, ça ne m'arrive jamais. | G7: Donner votre opinion sans mentir, même si votre avis peut blesser. | H7: Vous allez contacter le commerçant afin de trouver un accord gagnant-gagnant qui pourrait tous les deux vous satisfaire. | I7: Bouger beaucoup les mains comme si vous souhaitiez dessiner ce que vous expliquez, vous vous déplacez vers les gens, regardez les gens dans les yeux et vous souriez. | J7: Super vous allez faire le show, vous êtes pressé d'être sur la scène. | K7: Les personnes qui écoutent sont captivées et ont envie d'en savoir plus. | L7: Lire les articles et les ouvrages les plus récents sur le sujet et allez aux conférences sur le sujet. | M7: Vous vérifierez l'information en cherchant des sources vraisemblables et des études scientifiques sur le sujet. | N7: Non pas du tout, certaines situations n'ont rien de drôle. | O7: Vous l'envoyez balader. Elle devrait écouter au lieu de critiquer dès son arrivée. | P7: Vous n'arrivez pas à imaginer quoi que ce soit, et vous détestez cet exercice. | Q7: Vous allez sur les sites spécialisés pour savoir qui réalise la série, qui sont les acteurs, le nombre d'épisodes…etc. | R7: Je vais me renseigner auprès de personnes qui y sont déjà allées, afin d'avoir un avis précis de la situation. | S7: Vous cherchez toutes les sources du problème afin de savoir comment il s'est créé. | T7: Vous allez contacter le constructeur ou le magasin afin qu’il vous fournisse le mode d'emploi. | U7: Je signale l'erreur au caissier et lui rends l'argent en trop. | V7: Je termine quand même mon travail car il doit être fait pour demain. Je pleurerai après. | W7: Vous cherchez à intégrer un groupe plus travailleur et performant. | X7: Je l'utilise sans hésiter. Ce qui compte c'est de terminer le jeu. | Y7: Je m'enfuis aussi. Il serait bête de rester là et se faire attraper. Pas vu pas pris. | Z7: La paix dans le monde, donc plus de guerre. | AA7: Je préfère acheter un vélo car c'est moins polluant et plus amusant. | AB7: Non, c'est complètement idiot. | AC7: Oui, c'est tout à fait possible. | AD7: Vous vous empressez de noter ses commentaires afin de comprendre ce qui ne va pas. | AE7: Non, je n'y arrive jamais. | AF7: Vous vous sentez mal à l'aise et vous ressentez un sentiment de gêne. | AG7: Vous conservez cet avantage, afin d'avoir la meilleure note. | AH7: Je suis excité(e) par le défi et confiant(e) dans ma capacité à diriger le projet et à prendre les bonnes décisions. | AI7: Vous déprimez et perdez vos moyens car tout est fini. Vous avez les larmes aux yeux. | AJ7: Vous l'ignorez tout simplement. Il/elle ne mérite pas votre attention. | AK7: Vous ne comprenez pas ce qu'il attend. Il a juste fait ce qu'on lui a demandé de faire. | AL7: À ne rien ressentir, car vous n'êtes pas très proche de votre voisin. | AM7: Essayer de parler avec tout le monde. | AN7: Vous les partagez avec tous ceux qui doivent passer l'examen. | AO7: Vous êtes heureux de pouvoir travailler à plusieurs, c'est plus amusant. | AP7: La personne qui va essayer de parler la langue, apprendre les coutumes, aborder les styles vestimentaires. | AQ7: Oui, j'aime beaucoup échanger avec les gens. | AR7: Oui tant qu'il réalise leur tâche au mieux. Les sentiments polluent le travail. | AS7: Vous n'avez pas envie de l'écouter tant qu'il ne prouve pas ce qu'il dit. | AT7: Oui carrément j'adore ça, et je le fais très bien. | AU7: Aller parler à tout le monde car vous voulez absolument savoir qui est qui. | AV7: Je recherche des informations en ligne, comme des tutoriels ou des forums, le réaliser au mieux | AW7: Oui, parce qu’ils ne les font jamais comme je le souhaite. | AX7: Celui qui prend les décisions et donne les directives. | AY7: Je planifie un certain nombre d'heures par semaine à l'étude de la langue et je fixe des délais pour évaluer mes progrès, comme maîtriser les bases d'ici trois mois. | AZ7: Les divers évènements qui pourraient faire en sorte que le projet soit annulé. | BA7: Dans tous les cas il va mourir donc vous demandez qu’on mette en place la solution. | BB7: Etablir des outils qui permettront de contrôler l'avancée des travaux. | BC7: Vous vous énervez car vous n'aimez pas que les choses changent du jour au lendemain. | BD7: J'arrête de jouer car il n'est pas normal de changer les règles en cours de jeu. | BE7: Les pays riches devraient aider les pays pauvres. | BF7: Chercher quelle est l'origine du conflit et trouver une solution. | BG7: Je préfère que tout le monde se déplace pour travailler dans un lieu centralisé, c'est plus pratique. | BH7: Vous allez le/la chercher pour l'intégrer à votre groupe de discussion. | BI7: Non, car le travail sera mal réalisé. | BJ7: Vous allez être réaliste et lui dire qu'il devrait abandonner. | BK7: À vous accompagner même si les activités ne leur plaisent pas. | BL7: Vous allez chercher à comprendre pourquoi et ensuite lui prodiguer des conseils. | BM7: qu'on laisse prendre la direction du groupe pour montrer la direction à suivre. | BN7: Je recherche des ressources en ligne, comme des cours, des vidéos, ou des articles pour en apprendre davantage par moi-même. | BO7: Je me fixe des petits objectifs à atteindre et je prends de courtes pauses pour rester concentré et motivé. | BP7: Que nous disposons de tous les moyens nécessaires à la réalisation du projet. | BQ7: Vous organiser de façon à ce vous puissiez travailler chaque jour dessus. À un rythme régulier. | BR7: Vous classez les tâches par urgence et par importance et ensuite vous les traitez. | BS7: Planifier chaque étape de vos vacances avec les dates, les lieux, les prix. | BT7: Analyser le temps de réalisation de chaque tâche pour savoir laquelle prend le plus ou le moins de temps. | BU7: Je m'imagine toutes les étapes nécessaires pour atteindre mon objectif et je les visualise clairement dans ma tête. | BV7: Arriver en avance afin d'être sûr de ne pas le faire attendre.
B8: B | C8: Vous recevez rarement des retours d'incompréhension. | D8: Bien que surpris, je saisis l'occasion de partager mes idées, en improvisant une présentation concise basée sur mes connaissances actuelles. | E8: Celui qui motive et propose les sorties et les activités funs. | F8: Rarement, une fois comme ça. | G8: Expliquer quels sont les faits, sans chercher à transformer la réalité. | H8: Vous allez chercher tous les défauts possibles pour pouvoir diminuer la valeur et le prix de l'article auprès du commerçant. | I8: Utiliser vos mains et beaucoup d'expression faciales différentes. | J8: Ça ne me dérange pas, je vais le faire. | K8: Les auditeurs sont attentifs. | L8: je pose des questions à mes collègues pour en savoir plus, et j'envisage de m'informer davantage par la suite. | M8: Vous lui demandez où il a obtenu cette information. | N8: Non, cela ne me correspond pas vraiment. | O8: Vous ne changez pas de méthode car elle a déjà fonctionné. | P8: Vous demandez de l'aide à une amie qui a plus d'imagination que vous. | Q8: Vous allez voir les revues, les avis et des critiques pour en savoir plus. | R8: Avant d'acheter mon billet, je vais me renseigner auprès de l'ambassade du pays. | S8: Vous vous documentez sur le sujet et interrogez des experts en la matière avant d'essayer de le résoudre. | T8: Vous allez rechercher sur internet si vous trouver des vidéos explicatives. | U8: Je vérifie le montant rendu et, constatant l'erreur, je retourne à la caisse pour rectifier la situation. | V8: Je marque une pause dans mon travail pour prendre des nouvelles et lui dire au revoir. Mais je reprends le travail juste après car il doit être terminé. | W8: Vous les quittez pour travailler tout seul. | X8: J’utilise le cheat code, ça n'enlèvera pas le fun. | Y8: Je fais comme si je ne jouais pas au foot et j'indique que le coupable est parti en courant. | Z8: Faire en sorte que plus personne ne manque de faim dans le monde. | AA8: Achetez une voiture qui fonctionne à l'air mais qui ne roule pas super vite et qui n'est pas très jolie. | AB8: Non, je n'aime pas la douleur. | AC8: Oui, ça ne me dérange pas. | AD8: Ça vous énerve, mais vous savez qu'aucun travail n'est parfait donc vous écoutez. | AE8: En général, j'ai besoin qu'on m'aide à le faire. | AF8: Vous avez envie d'aller l'aider en lui soufflant son texte. | AG8: Vous gardez les réponses pour vous, car vous craignez que quelqu'un vous trahisse. | AH8: Même si je ressens une certaine pression, je suis sûr(e) de mes compétences et prêt(e) à assumer ce rôle de leadership. | AI8: Vous faites tout pour annuler la présentation car vous ne pourrez pas vous souvenir de tout. | AJ8: Vous n'allez rien faire…pour le moment. | AK8: Vous êtes satisfait parce que ça fait une tâche en moins à faire. | AL8: À ne pas vouloir vous mêler de ce qui ne vous regarde pas. | AM8: Lancer les blagues, et vous diriger vers les gens les plus drôles. | AN8: Vous partagez cette information uniquement à ceux que vous aimez bien. | AO8: Vous êtes pressé(e) de connaître vos futurs collaborateurs. | AP8: La personne qui va vouloir aller dormir chez les gens, aller visiter les lieux historiques. | AQ8: Oui plutôt, je trouve ça enrichissant. | AR8: Oui, tant que l'on s'entend un minimum on n’est pas obligé de s'apprécier. | AS8: Vous allez couper court à la discussion, car vous savez que vous ne l'êtes pas. | AT8: Plutôt oui, mais je ne suis pas encore expert en la matière. | AU8: Lancer les conversations même si vous n'y êtes pas obligé. | AV8: Je me fixe mes propres objectifs et échéances pour m'assurer que le travail est fait efficacement et à temps. | AW8: Oui parce qu’ils les font mal. | AX8: Celui qui analyse les résultats. | AY8: Je m'inscris à un cours en ligne et je me fixe des objectifs clairs, par exemple atteindre un niveau intermédiaire en six mois, en suivant régulièrement les leçons et en pratiquant quotidiennement. | AZ8: Avoir un plan de secours pour chaque imprévu. | BA8: Vous lisez toutes les études concernant l'opération et son taux de réussite. Ensuite vous prenez votre décision. | BB8: Vérifier au fur et à mesure que les tâches ont bien été réalisées | BC8: Vous êtes gravement perturbé(e) par ce manque d'ordre. | BD8: Ce changement me perturbe et m’énerve au plus haut point. Je ne sais pas quoi faire. | BE8: Tout le monde devrait avoir assez pour vivre correctement. | BF8: Tenter de mettre en place une médiation afin qu'il puisse s'expliquer calmement. | BG8: J'ai tendance à communiquer davantage avec ceux qui sont proches géographiquement ou dans mon fuseau horaire. | BH8: Vous allez lui parler pour qu'il/elle se sente moins seul(e). | BI8: Non, sauf si un expert peut m'aider. | BJ8: Vous ne préférez rien dire par peur de le décourager. | BK8: À être intéressé parce que vous allez réaliser les activités ensemble. | BL8: Vous allez vouloir le former afin d'être sûr qu'il comprenne et réalise mieux la tâche. | BM8: dont les idées sont écoutées et réalisées. | BN8: J'emprunte ou j'achète des livres, je cherche des tutoriels en ligne pour approfondir mes connaissances sur le sujet. | BO8: J'alterne entre cette tâche et d'autres activités plus stimulantes pour garder mon esprit alerte. | BP8: D’avoir une équipe avec les bonnes compétences techniques. | BQ8: Identifier les tâches les plus simples et les réaliser rapidement pour pouvoir prendre plus de temps sur les autres. | BR8: Vous priorisez les tâches qui auront le plus d'impact sur l'activité. | BS8: Calculer les délais de chaque activité afin de les réaliser au bon moment, pour plus de fun. | BT8: Essayer de trouver les outils qui vous permettront de travailler deux fois plus vite. | BU8: J'utilise des outils comme des cartes mentales ou des listes pour organiser mes pensées et visualiser comment je vais aborder le projet. | BV8: Arriver pile à l'heure du rendez-vous pour profiter au maximum du temps passé avec lui.
B9: C | C9: On comprend mais certains vous signalent qu'il y a beaucoup de fautes de français. | D9: Je m'excuse en expliquant que je ne suis pas prêt à présenter et je suggère de reporter à un moment où je pourrais mieux me préparer. | E9: Celui qui n'aime pas trop les sorties et préfère les soirées pizza, maison et jeux vidéo. | F9: Ça m'arrive régulièrement. | G9: Mesurer votre franchise afin de ne pas créer de malaise. | H9: Vous allez voir chez un autre concurrent si ça peut coûter moins cher. | I9: Faire très peu de mouvement. Vous préférez resté assis, et avoir une posture correcte et simple. | J9: Je n’aime pas trop ça, mais je vais quand même essayer. | K9: Les auditeurs comprennent l’histoire mais ont l'air de s'ennuyer. | L9: Je ne m'en préoccupe pas vraiment, si c'est important, quelqu'un m'en parlera plus en détail. | M9: Vous partagez immédiatement l'information sur vos propres réseaux sociaux pour alerter vos amis et votre famille. | N9: Oui, cela peut m'arriver. | O9: Vous vous renseignez quand même sur les autres méthodes existantes. | P9: Vous arrivez immédiatement à imaginer une trame et quelques personnages. | Q9: Vous allez attendre la sortie parce c'est fatigant de chercher des informations. | R9: Je vais me fier à l'information transmise par le journal télévisé et changer de destination. | S9: Vous vous basez sur votre intuition et votre expérience pour le résoudre. | T9: Vous appelez un expert pour qu'il construise le meuble à votre place. | U9: Je garde l'argent , en car c'est une chance inattendue. | V9: Je lâche tout ce que je dois faire pour aller au rendez-vous, par peur que mon ami(e) pense que je ne tiens pas à lui/elle. | W9: Vous allez chercher à travailler plus que les autres pour compenser leur manque de performance. | X9: Je ne l'utilise pas car je ne savourerai pas ma victoire. | Y9: J’attends dehors afin de me dénoncer. Si on doit me sanctionner on me sanctionnera. | Z9: Obtenir la capacité d'un super héros, n’importe quelle capacité. | AA9: Une voiture simple et pratique qui va durer dans le temps. | AB9: Oui même si cela doit faire mal. | AC9: Non, je ne préfère pas. | AD9: Vous l'ignorez tout simplement, cette personne vous veut du mal. | AE9: Plutôt oui. | AF9: Vous trouvez la situation comique. | AG9: Vous transmettez les réponses uniquement aux personnes que vous appréciez. | AH9: Je suis inquiet(e) à l'idée de ne pas être à la hauteur et j'hésite à accepter le rôle. | AI9: Vous prenez une respiration, et tentez de reproduire votre présentation en puisant dans vos souvenirs. | AJ9: Vous allez chercher à l'humilier de la même façon qu'il/elle l'a fait en divulguant une anecdote croustillante sur lui/elle. | AK9: Vous le félicitez et vous l'encouragez à continuer car il a réussi sa mission | AL9: À vouloir pleurer quand vous voyez votre voisin triste et désespéré. | AM9: Eviter les conversations. | AN9: Vous partagez cette information avec ceux qui peuvent vous apporter eux aussi des réponses. | AO9: Vous le faites mais uniquement parce que vous n'avez pas le choix. Sinon, vous auriez évité. | AP9: Celle qui va préférer aller au Macdonald à la place de découvrir la cuisine locale. | AQ9: Non, je préfère rester dans mon coin. | AR9: Non pas vraiment, il faut un minimum de points communs entre nous. | AS9: Vous êtes curieux de savoir pourquoi, et bizarrement vous n'êtes pas énervé. | AT9: Non pas du tout, je préfère avoir un petit groupe d'amis. | AU9: A chercher un moyen de vous échapper pour éviter de parler aux gens. | AV9: Je préfère me faire accompagner par un expert afin d'être sûr qu'il soit bien réalisé. | AW9: Non, parce que j’aime partager mon travail. | AX9: Celui qui va chercher les outils qui permettront de travailler efficacement. | AY9: J'achète des livres de langue et des applications, mais sans plan précis sur comment et quand les utiliser. | AZ9: Que la qualité de l'évènement soit bien au rendez-vous. | BA9: Vous préférez vous réunir avec d'autres amis à lui pour en parler et prendre la décision à plusieurs. | BB9: Terminer vite, contrôler la qualité, et ensuite tout corriger. | BC9: Vous vous en fichez, vous allez vous adapter. | BD9: Je lis les nouvelles règles du jeu et j'essaie de gagner quand même. | BE9: Je pense que la répartition des richesses est un reflet de la compétence et du talent individuel, et qu'il n'est pas nécessaire d'ajuster le système. | BF9: Ne pas vouloir intervenir par crainte que cela vous retombe dessus. | BG9: Je mets en place des réunions régulières via visioconférence pour nous synchroniser et je m'assure que chacun dispose des outils nécessaires.. | BH9: Vous le/la laissez dans son coin il/elle se fera des amis par il/elle-même. | BI9: Oui et je vais m'autoformer grâce à internet. | BJ9: Vous allez lui dire que tout est possible, avec une bonne formation. | BK9: À vouloir vous accompagner uniquement si les activités leur plaisent. . | BL9: Vous le laissez trouver les solutions seul. | BM9: qui va suivre le plan de manière rigoureuse, pour que tout se passe bien. | BN9: Je trouve ça intéressant, mais je ne voit pas l'intéret d'en apprendre plus que ce que propose déjà ma formation. | BO9: Je trouve cela très difficile et je me laisse souvent distraire par d'autres choses, comme mon téléphone. | BP9: De fédérer les membres du groupe autour de la réussite du projet. | BQ9: Réaliser le travail en fonction de votre motivation du jour. | BR9: Vous réalisez d'abord les tâches les plus difficiles car elles prennent du temps. | BS9: Surtout chercher à se reposer l’esprit, en se prélassant. | BT9: Trouver un moyen d'obtenir deux jours supplémentaires. | BU9: Je me sens souvent dépassé(e) et je ne sais pas par où commencer, donc je ne fais pas vraiment de planification visuelle. | BV9: Arriver 5 minutes en retard pour ne pas passer pour celui ou celle qui était en train de l'attendre.
B10: D | C10: Vous recevez plusieurs messages vous demandant d'être plus explicite parce qu'on ne comprend rien du tout. | D10: La situation me met mal à l'aise, donc je décline poliment, préférant ne pas prendre le risque de me présenter sans préparation. | E10: Celui qui est discret et réservé, qui n'aime pas faire du bruit pour rien. | F10: Ça m'arrive tout le temps, je dois souvent reprendre depuis le début. | G10: Bien choisir vos mots afin de ne blesser personne. | H10: Vous préférez attendre d'avoir plus d'argent ou que le prix baisse pour l'acheter. | I10: Vous sentir crispé et immobile. Vous avez du mal à regarder les gens dans les yeux. Vous préférez parler du fond de la salle. | J10: Ce n'est pas du tout mon truc. Je vais paniquer et perdre mes moyens. | K10: Les personnes qui écoutent froncent les sourcils, comme si vous parliez un langage extraterrestre. | L10: Je ne suis pas sûr(e) de vouloir investir du temps pour comprendre ce logiciel, s'il ne m'apporte rien dans immédiatement. | M10: Vous arrêtez d'utiliser votre téléphone mobile par peur des risques pour la santé. | N10: Oui, c'est tout à fait moi. | O10: Par curiosité vous lui demandez quelle méthode serait la meilleure selon elle. | P10: Vous arrivez tout de suite à imaginer les lieux, l'époque, les costumes, des personnages, les langues, les voix et accents des personnages. | Q10: Vous allez attendre la date de sortie, car vous aimez être surpris. | R10: Je préfère me fier à mon intuition pour me décider. | S10: Vous vous servez de votre cœur, vos valeurs et vos croyances pour le résoudre. | T10: Vous utilisez votre intuition pour construire le meuble au fur et à mesure, et vous adapter. | U10: Je garde l'argent, car c'est le caissier qui à fait l'erreur, pas moi. | V10: Je demande aux autres membres du groupe de terminer sans moi. Le travail ce n'est pas tout, les amis d'abord, question de principe. | W10: Vous restez dans le groupe quoi qu'il en coûte. | X10: Je ne l'utilise pas, même si cela implique que je ne gagnerai jamais. | Y10: Je me dirige vers la maison pour m'excuser et trouver un moyen de réparer l'erreur. | Z10: Devenir la personne la plus riche de la planète. | AA10: Acheter une voiture à essence super puissante et qui en jette comme dans un fast and furious. | AB10: Oui je le ferai car je m'y suis engagé. | AC10: Non, c'est tout à fait impossible. | AD10: Vous l'envoyez valser, il ne sait pas à quel point vous vous êtes appliqué(e) dans votre travail. | AE10: Oui, j'y arrive très facilement. | AF10: Vous êtes déçu par sa prestation. | AG10: Vous transmettez les réponses en priorité à ceux qui rencontrent des difficultés dans la matière. | AH10: La peur de l'échec me pousse à envisager de décliner l'offre, même si une partie de moi sait que je suis capable. | AI10: Vous y allez au talent. Ça passe ou ça casse. | AJ10: Vous allez directement entrer en confrontation avec cette personne. | AK10: Vous lui dites que vous êtes impressionné(e) et lui indiquez que vous ferez appel à lui plus tard. | AL10: À vouloir l'aider et le réconforter même si vous n'êtes pas très proche. | AM10: Rester dans votre coin, sans qu'on vous dérange. | AN10: Vous gardez cette information secrète. | AO10: Cette idée vous fatigue déjà. Vous détestez les travaux de groupe. | AP10: La personne qui va préférer rester à l'hôtel pour profiter du calme et de la piscine un maximum. | AQ10: Non, j'ai l'impression que je suis trop différent d'eux. | AR10: Non, il faut absolument que je puisse apprécier les personnes avec qui je travaille. | AS10: Vous allez écouter son avis car tout le monde doit être écouté, peu importe qu'il ait tort ou raison. | AT10: Non, je préfère être seul. | AU10: Essayer de ne pas alle en soirée ou aux anniversaires. | AV10: je vais demander de l'aide à certains de mes amis qui s'y connaissent mieux. | AW10: Non, parce que ça allège mon travail. | AX10: Celui qui fait en sorte de mettre une bonne ambiance pour que tout le monde travaille dans la bonne humeur. | AY10: J'ai l'intention d'apprendre quand j'ai du temps libre, sans me fixer d'objectifs ou de calendrier spécifiques. | AZ10: L’avis des participants, car l'essentiel c'est que ça leurs plaise. | BA10: Vous ne pouvez pas faire de choix, car c'est la vie d’une personne qui est en jeu. | BB10: Réaliser en premier lieu les tâches qui vous plaisent le plus et les autres ensuite. | BC10: Ce n'est pas grave, vous ne vous callez jamais sur le planning. | BD10: Je continue à jouer car ça pourra être amusant. | BE10: Je ne crois pas qu'il soit nécessaire de redistribuer les richesses du monde ; si certains pays ou personnes sont plus riches, c'est parce qu'ils ont travaillé plus dur pour l'être. | BF10: Ne pas vouloir intervenir car vous craignez de créer plus de problèmes entre eux. | BG10: J'adapte mes horaires pour répondre aux besoins des membres de l'équipe en fonction de leurs fuseaux horaires. | BH10: Vous faites comme si vous ne l'avez pas vu. | BI10: Oui, et je m'adapterai au fur et à mesure. | BJ10: Vous allez l'encourager à le faire. | BK10: À mettre beaucoup de temps avant de vouloir adhérer et vous accompagner à ces activités. | BL10: Vous allez chercher à réaliser les travaux vous-même, afin d'éviter de perdre du temps. | BM10: qui écoute ce que les gens ont à dire d'intéressant sans s'imposer. | BN10: Je pense que c'est la responsabilité des enseignants de nous apprendre ces choses, donc pas besoin d'explorer d'avantage, par moi-même. | BO10: J'ai tendance à procrastiner ou à éviter la tâche, car je la trouve trop ennuyeuse | BP10: Que l'équipe s'entende le mieux possible sinon c'est l'anarchie. | BQ10: Attendre le dernier moment pour le réaliser, car c'est là que vous êtes le plus performant. | BR10: Vous réalisez d'abord les tâches les plus rapides et celles que vous maîtrisez le mieux. | BS10: Improviser une fois sur place, car ce qui est spontané est plus amusant. | BT10: Faire en sorte de reporter le travail. | BU10: J'attends que les choses se présentent et je réagis au fur et à mesure, sans visualiser à l'avance le processus ou le résultat. | BV10: Arriver en retard parce que vous mettez beaucoup de temps à vous préparer.
B11: Votre choix
B12: Explication réponse | C12: =_xlfn.XLOOKUP(C11,'Questionnaire '!$B$17:$B$20,'Questionnaire '!C17:C20,,1) | D12: =_xlfn.XLOOKUP(D11,'Questionnaire '!$B$17:$B$20,'Questionnaire '!D17:D20,,1) | E12: =_xlfn.XLOOKUP(E11,'Questionnaire '!$B$17:$B$20,'Questionnaire '!E17:E20,,1) | F12: =_xlfn.XLOOKUP(F11,'Questionnaire '!$B$17:$B$20,'Questionnaire '!F17:F20,,1) | G12: =_xlfn.XLOOKUP(G11,'Questionnaire '!$B$17:$B$20,'Questionnaire '!G17:G20,,1) | H12: =_xlfn.XLOOKUP(H11,'Questionnaire '!$B$17:$B$20,'Questionnaire '!H17:H20,,1) | I12: =_xlfn.XLOOKUP(I11,'Questionnaire '!$B$17:$B$20,'Questionnaire '!I17:I20,,1) | J12: =_xlfn.XLOOKUP(J11,'Questionnaire '!$B$17:$B$20,'Questionnaire '!J17:J20,,1) | ... BV12: =_xlfn.XLOOKUP(BV11,'Questionnaire '!$B$17:$B$20,'Questionnaire '!BV17:BV20,,1)
B13: Point soft skill | C13: =IF(OR(C11="A",C11="B"),1," ") | D13: =IF(OR(D11="A",D11="B"),1," ") | E13: =IF(OR(E11="A",E11="B"),1," ") | F13: =IF(OR(F11="A",F11="B"),1," ") | G13: =IF(OR(G11="C",G11="D"),1," ") | H13: =IF(OR(H11="A",H11="B"),1," ") | I13: =IF(OR(I11="A",I11="B"),1," ") | J13: =IF(OR(J11="A",J11="B"),1," ") | K13: =IF(OR(K11="a",K11="b"),1," ") | L13: =IF(OR(L11="a",L11="b"),1," ") | M13: =IF(OR(M11="a",M11="b"),1," ") | N13: =IF(OR(N11="C",N11="D"),1," ") | O13: =IF(OR(O11="C",O11="D"),1," ") | P13: =IF(OR(P11="c",P11="d"),1," ") | Q13: =IF(OR(Q11="a",Q11="b"),1," ") | R13: =IF(OR(R11="a",R11="b"),1," ") | S13: =IF(OR(S11="a",S11="b"),1," ") | T13: =IF(OR(T11="a",T11="b"),1," ") | U13: =IF(OR(U11="A",U11="B"),1," ") | V13: =IF(OR(V11="a",V11="b"),1," ") | W13: =IF(OR(W11="c",W11="d"),1," ") | X13: =IF(OR(X11="c",X11="d"),1," ") | Y13: =IF(OR(Y11="c",Y11="d"),1," ") | Z13: =IF(OR(Z11="a",Z11="b"),1," ") | AA13: =IF(OR(AA11="a",AA11="b"),1," ") | AB13: =IF(OR(AB11="c",AB11="d"),1," ") | AC13: =IF(OR(AC11="a",AC11="b"),1," ") | AD13: =IF(OR(AD11="a",AD11="b"),1," ") | AE13: =IF(OR(AE11="c",AE11="d"),1," ") | AF13: =IF(OR(AF11="a",AF11="b"),1," ") | AG13: =IF(OR(AG11="c",AG11="d"),1," ") | AH13: =IF(OR(AH11="a",AH11="b"),1," ") | AI13: =IF(OR(AI11="c",AI11="d"),1," ") | AJ13: =IF(OR(AJ11="a",AJ11="b"),1," ") | AK13: =IF(OR(AK11="c",AK11="d"),1," ") | AL13: =IF(OR(AL11="c",AL11="d"),1," ") | AM13: =IF(OR(AM11="a",AM11="b"),1," ") | AN13: =IF(OR(AN11="a",AN11="b"),1," ") | AO13: =IF(OR(AO11="a",AO11="b"),1," ") | AP13: =IF(OR(AP11="a",AP11="b"),1," ") | AQ13: =IF(OR(AQ11="a",AQ11="b"),1," ") | AR13: =IF(OR(AR11="a",AR11="b"),1," ") | AS13: =IF(OR(AS11="c",AS11="d"),1," ") | AT13: =IF(OR(AT11="a",AT11="b"),1," ") | AU13: =IF(OR(AU11="a",AU11="b"),1," ") | AV13: =IF(OR(AV11="A",AV11="B"),1," ") | AW13: =IF(OR(AW11="c",AW11="d"),1," ") | AX13: =IF(OR(AX11="c",AX11="d"),1," ") | AY13: =IF(OR(AY11="a",AY11="b"),1," ") | AZ13: =IF(OR(AZ11="a",AZ11="b"),1," ") | BA13: =IF(OR(BA11="a",BA11="b"),1," ") | BB13: =IF(OR(BB11="a",BB11="b"),1," ") | BC13: =IF(OR(BC11="c",BC11="d"),1," ") | BD13: =IF(OR(BD11="c",BD11="d"),1," ") | BE13: =IF(OR(BE11="a",BE11="b"),1," ") | BF13: =IF(OR(BF11="a",BF11="b"),1," ") | BG13: =IF(OR(BG11="c",BG11="d"),1," ") | BH13: =IF(OR(BH11="a",BH11="b"),1," ") | BI13: =IF(OR(BI11="c",BI11="d"),1," ") | BJ13: =IF(OR(BJ11="c",BJ11="d"),1," ") | BK13: =IF(OR(BK11="a",BK11="b"),1," ") | BL13: =IF(OR(BL11="a",BL11="b"),1," ") | BM13: =IF(OR(BM11="a",BM11="b"),1," ") | BN13: =IF(OR(BN11="A",BN11="B"),1," ") | BO13: =IF(OR(BO11="a",BO11="b"),1," ") | BP13: =IF(OR(BP11="a",BP11="b"),1," ") | BQ13: =IF(OR(BQ11="a",BQ11="b"),1," ") | BR13: =IF(OR(BR11="a",BR11="b"),1," ") | BS13: =IF(OR(BS11="a",BS11="b"),1," ") | BT13: =IF(OR(BT11="a",BT11="b"),1," ") | BU13: =IF(OR(BU11="a",BU11="b"),1," ") | BV13: =IF(OR(BV11="a",BV11="b"),1," ")
B14: Sélection soft skills | C14: Soft skills | D14: Soft skills | E14: Soft skills | F14: Soft skills | G14: Soft skills | H14: Soft skills | I14: Soft skills | J14: Soft skills | K14: Soft skills | L14: Soft skills | M14: Soft skills | N14: Soft skills | O14: Soft skills | P14: Soft skills | Q14: Soft skills | R14: Soft skills | S14: Soft skills | T14: Soft skills | U14: Soft skills | V14: Soft skills | W14: Soft skills | X14: Soft skills | Y14: Soft skills | Z14: Soft skills | AA14: Soft skills | AB14: Soft skills | AC14: Soft skills | AD14: Soft skills | AE14: Soft skills | AF14: Soft skills | AG14: Soft skills | AH14: Soft skills | AI14: Soft skills | AJ14: Soft skills | AK14: Soft skills | AL14: Soft skills | AM14: Soft skills | AN14: Soft skills | AO14: Soft skills | AP14: Soft skills | AQ14: Soft skills | AR14: Soft skills | AS14: Soft skills | AT14: Soft skills | AU14: Soft skills | AV14: Soft skills | AW14: Soft skills | AX14: Soft skills | AY14: Soft skills | AZ14: Soft skills | BA14: Soft skills | BB14: Soft skills | BC14: Soft skills | BD14: Soft skills | BE14: Soft skills | BF14: Soft skills | BG14: Soft skills | BH14: Soft skills | BI14: Soft skills | BJ14: Soft skills | BK14: Soft skills | BL14: Soft skills | BM14: Soft skills | BN14: Soft skills | BO14: Soft skills | BP14: Soft skills | BQ14: Soft skills | BR14: Soft skills | BS14: Soft skills | BT14: Soft skills | BU14: Soft skills | BV14: Soft skills
B15: Soft skill à développer ? | C15: =IF(C13=1,"","Oui.") | D15: =IF(D13=1,"","Oui.") | E15: =IF(E13=1,"","Oui.") | F15: =IF(F13=1,"","Oui.") | G15: =IF(G13=1,"","Oui.") | H15: =IF(H13=1,"","Oui.") | I15: =IF(I13=1,"","Oui.") | J15: =IF(J13=1,"","Oui.") | ... BV15: =IF(BV13=1,"","Oui.")
B16: remarque affirmation
B17: A | C17: Vous êtes particulièrement doué à l'écrit. | D17: Vous avez de l'audace et êtes relativement spontané. | E17: Vous êtes quelqu'un d'enthousiaste et de dynamique. | F17: Vous savez vous exprimer extrêmement bien. | G17: Vous pouvez parfois manquer de diplomatie et de tact quand vous vous adressez aux gens. | H17: Vous aimez négocier et trouver des accords profitables pour tous. | I17: Lorsque vous parlez, vous avez une attitude corporelle théâtrale. Vous bougez énormément. | J17: Vous aimez être le centre de l'attention et vous exprimer en public. | K17: Vous avez un sens de l'art oratoire développé. | L17: Vous aimez vous documenter, et cela, même sur sujet où vous avez déjà une certaine expertise. | M17: Vous avez une faculté de discernement élevé. | N17: Vous avez très peu d'humour quand vous vous retrouvez dans une situation qui demande de l'observation et de la concentration ! | O17: Votre ouverture d’esprit s’arrête au moment où vous vous sentez directement visé par les critiques. | P17: Vous pouvez souvent manquer d’imagination ou de créativité. | Q17: Vous êtes aussi quelqu'un de curieux, et vous aimez aller à la recherche de l'information quand un sujet vous plaît. | R17: Vous êtes attentifs aux détails et aimez suggérer des améliorations à ce que vous observez. | S17: Afin de résoudre un problème, vous ne vous concentrez pas sur votre intuition ou votre expérience, mais plutôt sur des éléments tangibles. | T17: Face à un problème, vous êtes du genre à rechercher toutes les informations pouvant vous permettre de le résoudre avant de demander l'aide d'un expert. | U17: Vous saisissez les opportunités, surtout quand une situation peut vous avantager, quitte à transgresser certaines règles. | V17: Vous avez une conscience professionnelle développée. | W17: Vous préférez une grande réussite en solitaire plutôt qu'une défaite liée à une loyauté fanatique. | X17: Pour vous, demander de l’aide ou utiliser des astuces pour réussir n’est pas un signe de faiblesse. Cela ne diminue en rien la valeur de vos succès. | Y17: Vous n'aimez pas vous mettre en danger, même quand vous êtes le responsable des tracas. | Z17: Vous pensez plus aux autres qu'à vous-même quand vous avez le choix. | AA17: Vous avez un attrait pour la protection de l'environnement. | AB17: Vous ne pouvez pas vous engager si vous ressentez que cela peut vous nuire. | AC17: Vous êtes tolérant envers les autres et considérer leur avis même s'ils sont à l'opposé de vos croyances.. | AD17: Votre recherche d'amélioration vous permet d'apprécier et étudier les critiques. | AE17: Vous avez des difficultés à expliquer qui vous êtes vraiment. Comme si vous ne vous connaissez pas réellement. | AF17: Vous êtes quelqu'un d'empathique. Vous arrivez à vous mettre à la place des autres. | AG17: Vous avez tendance à vous soucier plus de votre bien-être qu'a celui des autres. | AH17: Vous débordez de confiance en vous, ce qui peut vous rendre téméraire parfois. | AI17: Vous avez du mal à supporter les situations de stress intenses. Au point de perdre vos moyens. | AJ17: Vous n’êtes pas du genre à perdre vos moyens facilement quand une personne tente de vous rabaisser. | AK17: Vous manquez parfois de considération pour le travail ou les succès des autres. Vous oubliez parfois de les féliciter quand vous considérez que leurs tâches ne sont pas difficiles. | AL17: Vous pouvez parfois manquer de sensibilité sur des sujets que d'autres trouveraient émouvant. | AM17: Vous avez un aisance relationnel développée. Vous aimez découvrir les autres. | AN17: Vous êtes quelqu'un d'altruiste, car vous aimez aider ceux dans le besoin. | AO17: Vous aimez le travail en équipe. | AP17: Vous avez un attrait pour la découverte d'autres cultures et d'autres langues. | AQ17: Vous aimez parler et discuter avec les autres. | AR17: Vous avez une facilité à coopérer avec les gens. Même quand vous n'avez pas d'affinité avec eux. | AS17: Il vous arrive d’être peu tolérant et ouvert d’esprit quand quelqu’un à un avis contraire au vôtre. | AT17: Vous prenez du plaisir à créer une communauté ou un réseau autour de vous. Vous êtes du genre à vous faire des amis rapidement. | AU17: Vous êtes extrèmement sociable. | AV17: Vous aimez être autonome dans ce que vous entreprenez. | AW17: Vous n'aimez pas déléguer les tâches qui incombent votre responsabilité. | AX17: Dans un travail de groupe, vous préférez donner la direction. | AY17: Vous n'aimez pas vous fixer des objectifs qui vous semblent disproportionnés par rapport à vos capacités. Vous êtes réaliste. | AZ17: Vous préférez prévoir les évènements néfastes d’un projet avant de le commencer, par peur de ne pas le mener à bien. | BA17: Vous n'avez aucun mal prendre des décisions seul, même quand elles peuvent être dificilles et avoir de lourdes conséquences sur les autres. | BB17: Vous aimez superviser et surveiller les activités ou les tâches qui doivent être réalisées. | BC17: Vous pouvez parfois être intransigeant quant au changement de dernières minutes, à la modification de règles ou de processus. | BD17: Vous détestez être pris de court. Vous avez d'ailleurs du mal à gérer émotionnellement avec les évènements imprévus. | BE17: Vous cherchez à être équitable dans vos choix et décisions. Surtout quand cela peut impacter la vie des gens. | BF17: Vous aimez résoudre les conflits entre les gens. Surtout ceux qui sont liés aux personnes de votre entourage proche. | BG17: Vous n'êtes pas un spécialiste de la coordination du travail à distance, vous préférez gérer les choses en présentiel. | BH17: Vous n'aimez pas l'exclusion. Vous avez tendance à inclure les gens dans votre groupe si vous les sentez seuls ou isolés. | BI17: Vous pouvez parfois manquer d'esprit d'initiative. | BJ17: Vous préférez confronter les gens à la réalité plutôt que de les valoriser inutilement. | BK17: Vous êtes du type à plaire aux gens naturellement. Vous avez probablement beaucoup de charisme. | BL17: Vous aimez aider les autres à s’élever et se parfaire. Vous prodiguez souvent des conseils. | BM17: Vous aimez prendre le lead quand un projet doit se mettre en place. Vous aimez montrer la voie à suivre. | BN17: Vous n'aimez pas vous autoformer. Vous préférez avoir l'aide d'un mentor ou d'un professeur quand le besoin s'en ressent. | BO17: Vous n’avez pas besoin d’apprécier une tâche ou une activité, afin de vous concentrer pleinement dessus. | BP17: Dans un projet de groupe, vous vous focalisez plus sur les outils nécessaires sa réalisation qu'aux relations entre les membres. | BQ17: Vous aimez gérer votre temps correctement et prendre de l'avance sur les activités. | BR17: Vous préférez prioriser les choses en fonction de ce qui est nécessaire de faire plutôt qu'en fonction de ce que vous préférez faire. | BS17: Vous aimez planifier les choses. Vous n'aimez pas être débordé ou perturbé par un manque de prévision. | BT17: Vous cherchez à être efficace quand vous êtes dos au mur. | BU17: En général, vous avez du mal à vous projeter mentalement dans une situation future. | BV17: En général, vous faites tout pour respecter les délais et horaires fixés.
